{
    "url": "https://www.neptun.mk/categories/prenosni_kompjuteri/ASUS-Zenbook-S-13-UX5304MA-NQ039W-13-3--OLED-Ultra-7-155U-32GB-DDR5X-1TB-WIN11",
    "title": "\u041b\u0410\u041f\u0422\u041e\u041f ASUS ZENBOOK S 13 UX5304MA-NQ039W 13.3\" OLED ULTRA 7 155U/32GB DDR5X/1TB/WIN11",
    "warranty_months": 24,
    "regular_price_mkd": 89999,
    "happy_price_mkd": 84999,
    "category": "prenosni_kompjuteri",
    "device_type": "Laptop",
    "description": "\u041b\u0430\u043f\u0442\u043e\u043f\n\u0414\u0438\u0441\u043f\u043b\u0435\u0458: 13.3\"(33.7cm)\n\u0420\u0435\u0437\u043e\u043b\u0443\u0446\u0438\u0458\u0430:3K (2880 x 1800) OLED, 60Hz, 600nits, response time 0.2ms\n\u041f\u0440\u043e\u0446\u0435\u0441\u043e\u0440:Intel Core Ultra 7 Processor 155U 1.7 GHz (12MB Cache, up to 4.8 GHz, 12 cores, 14 Threads)\n\u0413\u0440\u0430\u0444\u0438\u043a\u0430:Intel Iris Xe Graphics\nRAM \u043c\u0435\u043c\u043e\u0440\u0438\u0458\u0430:32GB DDR5X\n\u0414\u0438\u0441\u043a (Storage):1TB M.2 NVMe PCIe 4.0 SSD\n\u041e\u043f\u0435\u0440\u0430\u0442\u0438\u0432\u0435\u043d \u0441\u0438\u0441\u0442\u0435\u043c: Windows 11 Home\n\u041a\u0430\u043c\u0435\u0440\u0430:FHD camera with IR function to support Windows Hello\n\u0412\u0433\u0440\u0430\u0434\u0435\u043d \u043c\u0438\u043a\u0440\u043e\u0444\u043e\u043d\n\u0410\u0443\u0434\u0438\u043e: harman/kardon (Premium)\nSmart Amp Technology\nWi-Fi 6E(802.11ax) (Dual band) 2*2\nBluetooth 5.3\nTouchpad\nBacklit Chiclet Keyboard\n\u041f\u043e\u0440\u0442\u0438:\n1x USB 3.2 Gen 2 Type-A\n2x Thunderbolt    4 supports display / power delivery\n1x HDMI 2.1 TMDS\n1x 3.5mm Combo Audio Jack\n65W AC Adapter\n\u0411\u0430\u0442\u0435\u0440\u0438\u0458\u0430:63WHrs, 2S2P, 4-cell Li-ion",
    "features": {
        "screen_size_inches": 13.3,
        "screen_resolution": "2880 x 1800",
        "screen_refresh_rate_hz": 60,
        "screen_brightness_nits": 600,
        "screen_type": "OLED",
        "processor_model": "Intel Core Ultra 7 Processor 155U",
        "processor_cores": 12,
        "processor_threads": 14,
        "processor_base_clock_ghz": 1.7,
        "processor_max_clock_ghz": 4.8,
        "gpu_model": "Intel Iris Xe Graphics",
        "ram_size_gb": 32,
        "ram_type": "DDR5X",
        "storage_size_gb": 1000,
        "storage_type": "M.2 NVMe PCIe 4.0 SSD",
        "operating_system": "Windows 11 Home",
        "wifi_standard": "Wi-Fi 6E",
        "bluetooth_version": 5.3,
        "usb_type_c_ports": 2,
        "usb_type_a_ports": 1,
        "hdmi_ports": 1,
        "audio_jack_ports": 1,
        "keyboard_type": "Backlit Chiclet Keyboard",
        "audio_feature_1": "harman/kardon (Premium)",
        "battery_capacity_wh": 63,
        "battery_cells": 4
    }
}