{
    "url": "https://www.neptun.mk/categories/prenosni_kompjuteri/ASUS-Vivobook-S-14-Flip-TP3402ZA-OLED-KN511W-14--Touch-i5-12500H-8GB-512GB-WIN11",
    "title": "\u041b\u0410\u041f\u0422\u041e\u041f ASUS VIVOBOOK S 14 FLIP TP3402ZA-OLED-KN511W 14\" TOUCH I5-12500H/8GB/512GB/WIN11",
    "warranty_months": 24,
    "regular_price_mkd": 62999,
    "happy_price_mkd": 50999,
    "category": "prenosni_kompjuteri",
    "device_type": "Laptop",
    "description": "\u041b\u0430\u043f\u0442\u043e\u043f\n\u0414\u0438\u0441\u043f\u043b\u0435\u0439:14.0\" (35.5cm)\n\u0420\u0435\u0437\u043e\u043b\u0443\u0446\u0438\u0458\u0430:(2880 x 1800) 2.8K OLED Touch, 90Hz, 16:10 aspect ratio\n\u041f\u0440\u043e\u0446\u0435\u0441\u043e\u0440:Intel Core i5-12500H Processor 2.5 GHz (18M Cache, up to 4.5 GHz, 4P+8E cores)\n\u0413\u0440\u0430\u0444\u0438\u043a\u0430:Intel Iris X Graphics\nRAM \u043c\u0435\u043c\u043e\u0440\u0438\u0458\u0430: 8GB DDR4\n\u0414\u0438\u0441\u043a (Storage): 512GB M.2 NVMe PCIe 3.0 SSD\n\u041e\u043f\u0435\u0440\u0430\u0442\u0438\u0432\u0435\u043d \u0441\u0438\u0441\u0442\u0435\u043c:Windows 11 Home\nFront-facing camera 1080p FHD  With privacy shutter\nWi-Fi 6(802.11ax) (Dual band) 2*2 + Bluetooth 5\nSupport NumberPad\nFingerPrint\n\u041f\u043e\u0440\u0442\u0438:\n1x USB 2.0 Type-A\n1x USB 3.2 Gen 2 Type-A\n1x Thunderbolt 4 supports display / power delivery\n1x HDMI 2.1 TMDS\n1x 3.5mm Combo Audio Jack\n1x DC-in\n\u0412\u0433\u0440\u0430\u0434\u0435\u043d \u043c\u0438\u043a\u0440\u043e\u0444\u043e\u043d harman/kardon (Premium)\nVoice control with Cortana and Alexa voice-recognition support\nAC Adapter 4.5, 90W AC Adapter, Output: 19V DC, 4.74A, 90W, Input: 100~240V AC 50/60Hz universal\n\u0411\u0430\u0442\u0435\u0440\u0438\u0458\u0430:70WHrs, 3S1P, 3-cell Li-ion",
    "features": {
        "screen_size_inches": 14.0,
        "screen_resolution": "2880 x 1800",
        "screen_refresh_rate_hz": 90,
        "screen_type": "OLED Touch",
        "processor_model": "Intel Core i5-12500H Processor",
        "processor_cores": 4,
        "processor_threads": 8,
        "processor_base_clock_ghz": 2.5,
        "processor_max_clock_ghz": 4.5,
        "gpu_model": "Intel Iris X Graphics",
        "ram_size_gb": 8,
        "ram_type": "DDR4",
        "storage_size_gb": 512,
        "storage_type": "M.2 NVMe PCIe 3.0 SSD",
        "operating_system": "Windows 11 Home",
        "wifi_standard": "Wi-Fi 6",
        "bluetooth_version": 5,
        "usb_type_c_ports": 1,
        "usb_type_a_ports": 2,
        "hdmi_ports": 1,
        "audio_jack_ports": 1,
        "keyboard_type": null,
        "audio_feature_1": "harman/kardon",
        "battery_capacity_wh": 70,
        "battery_cells": 3
    }
}