{
    "url": "https://www.neptun.mk/categories/prenosni_kompjuteri/ASUS-Vivobook-16-X1605ZA-MB321-16--i3-1215U-8GB-512GB",
    "title": "\u041b\u0410\u041f\u0422\u041e\u041f ASUS VIVOBOOK 16 X1605ZA-MB321 16\" I3-1215U/8GB/512GB",
    "warranty_months": 24,
    "regular_price_mkd": 28999,
    "happy_price_mkd": 21999,
    "category": "prenosni_kompjuteri",
    "device_type": "Laptop",
    "description": "\u041b\u0430\u043f\u0442\u043e\u043f\n\u0414\u0438\u0441\u043f\u043b\u0435\u0458:16.0\" (40.64cm)\n\u0420\u0435\u0437\u043e\u043b\u0443\u0446\u0438\u0458\u0430:WUXGA (1920 x 1200), 60Hz, IPS, 300nits\n\u041f\u0440\u043e\u0446\u0435\u0441\u043e\u0440:Intel Core i3-1215U 1.2 GHz (10M Cache, up to 4.4 GHz, 6 cores)\n\u0413\u0440\u0430\u0444\u0438\u043a\u0430:Intel UHD Graphics\nRAM \u043c\u0435\u043c\u043e\u0440\u0438\u0458\u0430:8GB DDR4\n\u0414\u0438\u0441\u043a (Storage): 512GB M.2 NVMe PCIe 3.0 SSD\n\u0411\u0435\u0437\u0430 \u043e\u043f\u0435\u0440\u0430\u0442\u0438\u0432\u0435\u043d \u0441\u0438\u0441\u0442\u0435\u043c.\nWi-Fi 6(802.11ax) (Dual band) 2*2 + Bluetooth 5\n\u041f\u043e\u0440\u0442\u0438:\n1x USB 2.0 Type-A\n1x USB 3.2 Gen 1 Type-C\n2x USB 3.2 Gen 1 Type-A\n1x HDMI 1.4\n1x 3.5mm Combo Audio Jack\n1x DC-in\n\u0410\u0443\u0434\u0438\u043e:SonicMaster\n\u0412\u0433\u0440\u0430\u0434\u0435\u043d\u0438 \u0437\u0432\u0443\u0447\u043d\u0438\u0446\u0438\n\u0412\u0433\u0440\u0430\u0434\u0435\u043d \u043c\u0438\u043a\u0440\u043e\u0444\u043e\u043d\nBIOS Booting User Password Protection\n\u0411\u0430\u0442\u0435\u0440\u0438\u0458\u0430:42WHrs, 3S1P, 3-cell Li-ion\n45W AC Adapter, Output: 19V DC, 2.37A, 45W, Input: 100~240V AC 50/60Hz universal",
    "features": {
        "screen_size_inches": 16.0,
        "screen_resolution": "1920 x 1200",
        "screen_refresh_rate_hz": 60,
        "screen_brightness_nits": 300,
        "screen_type": "IPS",
        "processor_model": "Intel Core i3-1215U",
        "processor_cores": 6,
        "processor_base_clock_ghz": 1.2,
        "processor_max_clock_ghz": 4.4,
        "gpu_model": "Intel UHD Graphics",
        "ram_size_gb": 8,
        "ram_type": "DDR4",
        "storage_size_gb": 512,
        "storage_type": "M.2 NVMe PCIe 3.0 SSD",
        "wifi_standard": "Wi-Fi 6",
        "bluetooth_version": 5,
        "usb_type_c_ports": 1,
        "usb_type_a_ports": 3,
        "hdmi_ports": 1,
        "audio_jack_ports": 1,
        "audio_feature_1": "SonicMaster",
        "battery_capacity_wh": 42,
        "battery_cells": 3,
        "security_feature_1": "BIOS Booting User Password Protection"
    }
}