{
    "url": "https://www.neptun.mk/categories/prenosni_kompjuteri/NB-LENOVO-IdeaPad-3-15IAU7-i3-1215U-8GB-256GB-82RK008VRM",
    "title": "\u041b\u0410\u041f\u0422\u041e\u041f LENOVO IDEAPAD 3 15IAU7 I3-1215U/8GB/256GB",
    "warranty_months": 24,
    "regular_price_mkd": 27999,
    "happy_price_mkd": 20499,
    "category": "prenosni_kompjuteri",
    "device_type": "Laptop",
    "description": "\u041b\u0430\u043f\u0442\u043e\u043f\n\u0414\u0438\u0441\u043f\u043b\u0435\u0458:15.6\" (39.6cm)\n\u0420\u0435\u0437\u043e\u043b\u0443\u0446\u0438\u0458\u0430:(1920x1080) FHD IPS\n\u0427\u0438\u043f\u0441\u0435\u0442: Intel SoC Platform\n\u041f\u0440\u043e\u0446\u0435\u0441\u043e\u0440:Intel Core i3-1215U (6 cores, 8 threads, 3.30GHz base up to 4.40GHz max, 10MB Cache)\n\u0413\u0440\u0430\u0444\u0438\u043a\u0430:Integrated Intel UHD Graphics\nRAM \u043c\u0435\u043c\u043e\u0440\u0438\u0458\u0430: 8GB DDR4, 3200 MHz\n\u0414\u0438\u0441\u043a (Storage): 256GB SSD M.2 2242 PCIe 3.0x4 NVMe\n\u041f\u043e\u0440\u0442\u0438:\n1 x USB 2.0\n1 x USB 3.2 Gen 1\n1 x USB 3.2 Gen 1(Support Data Transfer, Power Delivery 3.0, and DisplayPort 1.2)\n1 x HDMI 1.4b\n1 x Card reader\n1 x Headphone / microphone combo jack (3.5mm)\n1 x Power connector\n\u0417\u0432\u0443\u043a:\n(HD) Audio, Realtek ALC3287 codec\n\u0412\u0433\u0440\u0430\u0434\u0435\u043d\u0438 \u0437\u0432\u0443\u0447\u043d\u0438\u0446\u0438:Stereo speakers, 1.5W x2, Dolby Audio\n\u0412\u0435\u0431 \u043a\u0430\u043c\u0435\u0440\u0430:720p HD\n\u041c\u0438\u043a\u0440\u043e\u0444\u043e\u043d:2x, Array\nWireless: Wi-Fi 6 (802.11ax)\nBluetooth: 5.1\n\u0411\u0430\u0442\u0435\u0440\u0438\u0458\u0430: 38Wh, 5 hr\n\u041f\u043e\u043b\u043d\u0430\u0447: 65W Round Tip (3-pin)",
    "features": {
        "screen_size_inches": 15.6,
        "screen_resolution": "1920x1080",
        "screen_type": "FHD IPS",
        "processor_model": "Intel Core i3-1215U",
        "processor_cores": 6,
        "processor_threads": 8,
        "processor_base_clock_ghz": 3.3,
        "processor_max_clock_ghz": 4.4,
        "gpu_model": "Integrated Intel UHD Graphics",
        "ram_size_gb": 8,
        "ram_type": "DDR4",
        "storage_size_gb": 256,
        "storage_type": "SSD M.2 2242 PCIe 3.0x4 NVMe",
        "usb_type_a_ports": 2,
        "usb_type_c_ports": 1,
        "hdmi_ports": 1,
        "audio_jack_ports": 1,
        "card_reader": "Card reader",
        "webcam": "720p HD",
        "microphone": "Array",
        "wifi_standard": "Wi-Fi 6 (802.11ax)",
        "bluetooth_version": 5.1,
        "battery_capacity_wh": 38
    }
}