{
    "url": "https://www.neptun.mk/categories/prenosni_kompjuteri/DELL-XPS-13-Plus--9320--13-4--i7-1360P-16GB-DDR5-1TB-WIN11PRO",
    "title": "\u041b\u0410\u041f\u0422\u041e\u041f DELL XPS 13 PLUS (9320) 13.4\" I7-1360P/16GB DDR5/1TB/WIN11PRO",
    "warranty_months": 36,
    "regular_price_mkd": 139999,
    "happy_price_mkd": 125999,
    "category": "prenosni_kompjuteri",
    "device_type": "Laptop",
    "description": "\u041b\u0430\u043f\u0442\u043e\u043f\n\u0414\u0438\u0441\u043f\u043b\u0435\u0458:13.4\" (34cm)\n\u0420\u0435\u0437\u043e\u043b\u0443\u0446\u0438\u0458\u0430: (1920 x 1200) FHD+ 60Hz, Touch, Anti-Reflect, 500 nit, InfinityEdge\n\u041f\u0440\u043e\u0446\u0435\u0441\u043e\u0440:13th Gen Intel\u00ae Core\u2122 i7-1360P (18 MB cache, 12 cores, up to 5.00 GHz Turbo)\n\u0413\u0440\u0430\u0444\u0438\u043a\u0430:Intel\u00ae Iris\u00ae Xe Graphics\nRAM \u043c\u0435\u043c\u043e\u0440\u0438\u0458\u0430: 16 GB: LPDDR5, 6000 MT/s (onboard), dual-channel\n\u0414\u0438\u0441\u043a (Storage): 1 TB, M.2, PCIe NVMe, SSD\nWi-Fi 6E 1675 (AX211), 2x2, 802.11ax, Bluetooth\u00ae 5.3\n\u041a\u0430\u043c\u0435\u0440\u0430:720p at 30 fps HD RGB camera, 400p at 30 fps IR camera, dual-array microphones\nBacklit Keyboard + FingerPrint\n\u041e\u043f\u0435\u0440\u0430\u0442\u0438\u0432\u0435\u043d \u0441\u0438\u0441\u0442\u0435\u043c:Windows 11 Pro\n\u041f\u043e\u0440\u0442\u0438:\n2 x Thunderbolt\u2122 4 (USB Type-C\u2122 with DisplayPort and Power Delivery)\nUSB-C to USB-A 3.0 adapter (included in the box)\nUSB-C to 3.5mm headset adapter (included in the box)\n\u0411\u0430\u0442\u0435\u0440\u0438\u0458\u0430: 3 Cell, 55 Wh, integrated\n\u041f\u043e\u043b\u043d\u0430\u0447: 60 Watt AC Adapter USB-C\n\u041f\u043e\u0434\u0441\u0432\u0435\u0442\u043b\u0443\u0432\u0430\u045a\u0435 \u043d\u0430 \u0442\u0430\u0441\u0442\u0430\u0442\u0443\u0440\u0430: Platinum Backlit English Keyboard\nFingerprint Reader\n\u0411\u043e\u0458\u0430: Platinum",
    "features": {
        "screen_size_inches": 13.4,
        "screen_resolution": "1920 x 1200",
        "screen_refresh_rate_hz": 60,
        "screen_brightness_nits": 500,
        "processor_model": "13th Gen Intel\u00ae Core\u2122 i7-1360P",
        "processor_cores": 12,
        "gpu_model": "Intel\u00ae Iris\u00ae Xe Graphics",
        "ram_size_gb": 16,
        "ram_type": "LPDDR5",
        "storage_size_gb": 1000,
        "storage_type": "M.2, PCIe NVMe, SSD",
        "operating_system": "Windows 11 Pro",
        "wifi_standard": "Wi-Fi 6E 1675",
        "bluetooth_version": 5.3,
        "usb_type_c_ports": 2,
        "keyboard_type": "Backlit Keyboard",
        "security_feature_1": "Fingerprint Reader"
    }
}