{
    "url": "https://www.neptun.mk/categories/prenosni_kompjuteri/DELL-Vostro-3520-i3-1215U-8GB-512GB",
    "title": "\u041b\u0410\u041f\u0422\u041e\u041f DELL VOSTRO 3520 I3-1215U/8GB/512GB",
    "warranty_months": 36,
    "regular_price_mkd": 23999,
    "happy_price_mkd": 21999,
    "category": "prenosni_kompjuteri",
    "device_type": "Laptop",
    "description": "\u041b\u0430\u043f\u0442\u043e\u043f\n\u0414\u0438\u0441\u043f\u043b\u0435\u0458:15.6\" (39.6cm)\n\u0420\u0435\u0437\u043e\u043b\u0443\u0446\u0438\u0458\u0430: (1920 x 1080) FHD, 120Hz, 250nits, IPS\n\u041f\u0440\u043e\u0446\u0435\u0441\u043e\u0440:12th  Generation Intel\u00ae Core\u2122 i3-1215U (10 MB cache, 6 core, 8 threads, 1.20 GHz to 4.40 GHz, 15 W)\n\u0413\u0440\u0430\u0444\u0438\u043a\u0430: Intel\u00ae UHD Graphics\nRAM \u043c\u0435\u043c\u043e\u0440\u0438\u0458\u0430: 8GB DDR4 2666MHz\n\u0414\u0438\u0441\u043a (Storage): 512GB M.2 PCIe NVMe, SSD\nWi-Fi (Wi-Fi 802.11ac)+ Bluetooth\n\u041a\u0430\u043c\u0435\u0440\u0430: 720p at 30 fps HD camera Single integrated microphone\n\u041e\u043f\u0435\u0440\u0430\u0442\u0438\u0432\u0435\u043d \u0441\u0438\u0441\u0442\u0435\u043c:Ubuntu 20.04\n\u041f\u043e\u0440\u0442\u0438:\n2 USB 3.2 Gen 1 port\n1 USB 2.0 port\n1 headset (headphone and microphone combo) port\n1 HDMI 1.4 port\nHDMI 1.4 (Maximum resolution supported over HDMI is 1920x1080 @60Hz. No 4K/2K output)\n1 RJ45 Ethernet port (flip-down)\n\u0411\u0430\u0442\u0435\u0440\u0438\u0458\u0430: 4-Cell Battery, 54WHr",
    "features": {
        "screen_size_inches": 15.6,
        "screen_resolution": "1920 x 1080",
        "screen_refresh_rate_hz": 120,
        "screen_brightness_nits": 250,
        "screen_type": "IPS",
        "processor_model": "12th  Generation Intel\u00ae Core\u2122 i3-1215U",
        "processor_cores": 6,
        "processor_threads": 8,
        "processor_base_clock_ghz": 1.2,
        "processor_max_clock_ghz": 4.4,
        "gpu_model": "Intel\u00ae UHD Graphics",
        "ram_size_gb": 8,
        "ram_type": "DDR4",
        "storage_size_gb": 512,
        "storage_type": "M.2 PCIe NVMe, SSD",
        "wifi_standard": "Wi-Fi 802.11ac",
        "bluetooth_version": null,
        "usb_type_c_ports": null,
        "usb_type_a_ports": 3,
        "hdmi_ports": 1,
        "audio_jack_ports": 1,
        "keyboard_type": null,
        "audio_feature_1": null,
        "battery_capacity_wh": 54,
        "battery_cells": 4
    }
}