{
    "url": "https://www.neptun.mk/categories/prenosni_kompjuteri/ASUS-Vivobook-Pro-15-OLED-K6502VU-OLED-MA931X-i9-13900H-16GB-DDR5-1TB-WIN11PRO",
    "title": "\u041b\u0410\u041f\u0422\u041e\u041f ASUS VIVOBOOK PRO 15 OLED K6502VU-OLED-MA931X I9-13900H/16GB DDR5/1TB/ RTX 4050 6GB/WIN11PRO",
    "warranty_months": 24,
    "regular_price_mkd": 104999,
    "happy_price_mkd": 94999,
    "category": "prenosni_kompjuteri",
    "device_type": "Laptop",
    "description": "\u041b\u0430\u043f\u0442\u043e\u043f\n\u0414\u0438\u0441\u043f\u043b\u0435\u0458:15.6\" (39.6cm)\n\u0420\u0435\u0437\u043e\u043b\u0443\u0446\u0438\u0458\u0430:(2880 x 1620) 2.8K OLED, 120Hz, 600nits\n\u041f\u0440\u043e\u0446\u0435\u0441\u043e\u0440:Intel Core i9-13900H 2.6 GHz (24MB Cache, up to 5.4 GHz, 14 cores, 20 Threads)\n\u0413\u0440\u0430\u0444\u0438\u043a\u0430:NVIDIA GeForce RTX 4050 6GB GDDR6\nRAM \u043c\u0435\u043c\u043e\u0440\u0438\u0458\u0430:16GB DDR5\n\u0414\u0438\u0441\u043a (Storage):1TB M.2 NVMe PCIe 4.0 SSD\n\u041e\u043f\u0435\u0440\u0430\u0442\u0438\u0432\u0435\u043d \u0441\u0438\u0441\u0442\u0435\u043c: Windows 11 Pro\n\u041a\u0430\u043c\u0435\u0440\u0430:1080p FHD camera//With privacy shutter\nWi-Fi 6(802.11ax) (Dual band) 2*2 + Bluetooth 5.3\n\u041f\u043e\u0440\u0442\u0438:\n1x USB 3.2 Gen 2 Type-C support display / power delivery\n2x USB 3.2 Gen 1 Type-A\n1x Thunderbolt 4 supports display / power delivery\n1x HDMI 2.1 FRL\n1x 3.5mm Combo Audio Jack\n1x RJ45 Gigabit Ethernet\n1x DC-in\nSD 4.0 card reader\n\u0410\u0443\u0434\u0438\u043e:\n\u0412\u0433\u0440\u0430\u0434\u0435\u043d\u0438 \u0437\u0432\u0443\u0447\u043d\u0438\u0446\u0438\n\u0412\u0433\u0440\u0430\u0434\u0435\u043d \u043c\u0438\u043a\u0440\u043e\u0444\u043e\u043d\nharman/kardon (Mainstream)\n\u0411\u0430\u0442\u0435\u0440\u0438\u0458\u0430:70WHrs, 3S1P, 3-cell Li-ion",
    "features": {
        "screen_size_inches": 15.6,
        "screen_resolution": "2880 x 1620",
        "screen_refresh_rate_hz": 120,
        "screen_brightness_nits": 600,
        "screen_type": "OLED",
        "processor_model": "Intel Core i9-13900H",
        "processor_cores": 14,
        "processor_threads": 20,
        "processor_base_clock_ghz": 2.6,
        "processor_max_clock_ghz": 5.4,
        "gpu_model": "NVIDIA GeForce RTX 4050",
        "gpu_memory_gb": 6,
        "ram_size_gb": 16,
        "ram_type": "DDR5",
        "storage_size_gb": 1000,
        "storage_type": "M.2 NVMe PCIe 4.0 SSD",
        "operating_system": "Windows 11 Pro",
        "wifi_standard": "Wi-Fi 6",
        "bluetooth_version": 5.3,
        "usb_type_c_ports": 1,
        "usb_type_a_ports": 2,
        "hdmi_ports": 1,
        "audio_jack_ports": 1,
        "card_reader": "SD 4.0",
        "audio_feature_1": "harman/kardon (Mainstream)",
        "battery_capacity_wh": 70
    }
}