{
    "url": "https://www.neptun.mk/categories/prenosni_kompjuteri/LENOVO-IdeaPad-1-15AMN7-R3-7320U-8GB-512GB-82VG0066RM",
    "title": "\u041b\u0410\u041f\u0422\u041e\u041f LENOVO IDEAPAD 1 15AMN7 R3-7320U/8GB/512GB",
    "warranty_months": 24,
    "regular_price_mkd": 22999,
    "happy_price_mkd": 19999,
    "category": "prenosni_kompjuteri",
    "device_type": "Laptop",
    "description": "\u041b\u0430\u043f\u0442\u043e\u043f\n\u0414\u0438\u0441\u043f\u043b\u0435\u0458:15.6\" (39.6cm)\n\u0420\u0435\u0437\u043e\u043b\u0443\u0446\u0438\u0458\u0430:(1920x1080) FHD TN 220nits Anti-glare\nChipset:AMD SoC Platform\n\u041f\u0440\u043e\u0446\u0435\u0441\u043e\u0440:AMD Ryzen 3 7320U (4C / 8T, 2.4 / 4.1GHz, 2MB L2 / 4MB L3)\n\u0413\u0440\u0430\u0444\u0438\u043a\u0430:Integrated AMD Radeon 610M Graphics\nRAM \u043c\u0435\u043c\u043e\u0440\u0438\u0458\u0430:8GB LPDDR5-5500\n\u0414\u0438\u0441\u043a (Storage):512GB SSD M.2 2242 PCIe 4.0x4 NVMe\n\u0411\u0435\u0437 \u043e\u043f\u0435\u0440\u0430\u0442\u0438\u0432\u0435\u043d \u0441\u0438\u0441\u0442\u0435\u043c\n\u0410\u0443\u0434\u0438\u043e:High Definition (HD) Audio\n\u0417\u0432\u0443\u0447\u043d\u0438\u0446\u0438:Stereo speakers, 1.5W x2, Dolby Audio\n\u041a\u0430\u043c\u0435\u0440\u0430:HD 720p with Privacy Shutter\n\u041c\u0438\u043a\u0440\u043e\u0444\u043e\u043d:2x, Array\nWLAN + Bluetooth: 11ac 2x2 + BT5.0\n\u041f\u043e\u0440\u0442\u0438:\n1x USB 2.0\n1x USB 3.2 Gen 1\n1x USB-C 3.2 Gen 1 (support data transfer only)\n1x HDMI 1.4b\n1x Card reader\n1x Headphone / microphone combo jack (3.5mm)\n1x Power connector\n\u0410\u0434\u0430\u043f\u0442\u0435\u0440 - 65W Round Tip (3-pin)\n\u0411\u0430\u0442\u0435\u0440\u0438\u0458\u0430:Integrated 42Wh - MobileMark 2018: 9 hr",
    "features": {
        "screen_size_inches": 15.6,
        "screen_resolution": "1920x1080",
        "screen_brightness_nits": 220,
        "screen_type": "FHD TN",
        "processor_model": "AMD Ryzen 3 7320U",
        "processor_cores": 4,
        "processor_threads": 8,
        "processor_base_clock_ghz": 2.4,
        "processor_max_clock_ghz": 4.1,
        "gpu_model": "Integrated AMD Radeon 610M Graphics",
        "ram_size_gb": 8,
        "ram_type": "LPDDR5-5500",
        "storage_size_gb": 512,
        "storage_type": "SSD M.2 2242 PCIe 4.0x4 NVMe",
        "wifi_standard": "11ac 2x2",
        "bluetooth_version": "BT5.0",
        "usb_type_c_ports": 1,
        "usb_type_a_ports": 2,
        "hdmi_ports": 1,
        "card_reader": "1x",
        "audio_feature_1": "Dolby Audio",
        "battery_capacity_wh": 42,
        "security_feature_1": "Privacy Shutter"
    }
}