{
    "url": "https://www.neptun.mk/categories/prenosni_kompjuteri/ASUS-Vivobook-Pro-15-OLED-K6502VU-OLED-MA731X-i7-13700H-16GB-DDR5-1TB-RTX-4050-6GB-WIN11PRO",
    "title": "\u041b\u0410\u041f\u0422\u041e\u041f ASUS VIVOBOOK PRO 15 OLED K6502VU-OLED-MA731X I7-13700H/16GB DDR5/1TB/RTX 4050 6GB/WIN11PRO",
    "warranty_months": 24,
    "regular_price_mkd": 103999,
    "happy_price_mkd": 89999,
    "category": "prenosni_kompjuteri",
    "device_type": "Laptop",
    "description": "\u041b\u0430\u043f\u0442\u043e\u043f\n\u0414\u0438\u0441\u043f\u043b\u0435\u0458:15.6 (39.6cm)\n\u0420\u0435\u0437\u043e\u043b\u0443\u0446\u0438\u0458\u0430:(2880x1620) OLED, 120 Hz\n\u041f\u0440\u043e\u0446\u0435\u0441\u043e\u0440:Intel Core i7-13700H Processor 2.3 GHz (24M Cache, up to 4.7 GHz, 6P+8E cores)\n\u0413\u0440\u0430\u0444\u0438\u043a\u0430:NVIDIA Geforce RTX 4050 6GB GDDR6\nRAM \u043c\u0435\u043c\u043e\u0440\u0438\u0458\u0430:16GB DDR5\n\u0414\u0438\u0441\u043a (Storage):1TB M.2 NVMe PCIe 4.0 SSD\n\u041e\u043f\u0435\u0440\u0430\u0442\u0438\u0432\u0435\u043d \u0441\u0438\u0441\u0442\u0435\u043c: Windows 11 Pro\n\u041a\u0430\u043c\u0435\u0440\u0430:1080p FHD camera\nWi-Fi 6E(802.11ax) (Dual band) 2*2 + Bluetooth 5\nFingerPrint\nASUS AI noise cancelation\n\u0410\u0443\u0434\u0438\u043e: Harman Kardon\n\u0412\u0433\u0440\u0430\u0434\u0435\u043d \u043c\u0438\u043a\u0440\u043e\u0444\u043e\u043d\n\u041f\u043e\u0440\u0442\u0438:\n1x USB 3.2 Gen 2 Type-C support display / power delivery\n2x USB 3.2 Gen 1 Type-A\n1x Thunderbolt 4 supports display / power delivery\n1x HDMI 2.1 FRL\n1x 3.5mm Combo Audio Jack\n1x RJ45 Gigabit Ethernet\n1x DC-in\nSD 4.0 card reader\n150W AC Adapter\n\u0411\u0430\u0442\u0435\u0440\u0438\u0458\u0430:70WHrs, 3S1P, 3-cell Li-ion",
    "features": {
        "screen_size_inches": 15.6,
        "screen_resolution": "2880x1620",
        "screen_refresh_rate_hz": 120,
        "processor_model": "Intel Core i7-13700H Processor",
        "processor_cores": 14,
        "gpu_model": "NVIDIA Geforce RTX 4050",
        "gpu_memory_gb": 6,
        "ram_size_gb": 16,
        "ram_type": "DDR5",
        "storage_size_gb": 1024,
        "storage_type": "M.2 NVMe PCIe 4.0 SSD",
        "operating_system": "Windows 11 Pro",
        "wifi_standard": "Wi-Fi 6E",
        "bluetooth_version": 5,
        "usb_type_c_ports": 1,
        "usb_type_a_ports": 2,
        "hdmi_ports": 2,
        "audio_jack_ports": 1,
        "card_reader": "SD 4.0",
        "audio_feature_1": "Harman Kardon",
        "battery_capacity_wh": 70,
        "battery_cells": 3,
        "security_feature_1": "FingerPrint"
    }
}