{
    "url": "https://www.neptun.mk/categories/prenosni_kompjuteri/DELL-Vostro-3535-R3-7330U-8GB-256GB",
    "title": null,
    "warranty_months": 36,
    "regular_price_mkd": 21999,
    "happy_price_mkd": 19499,
    "category": "prenosni_kompjuteri",
    "device_type": "Laptop",
    "description": "\u041b\u0430\u043f\u0442\u043e\u043f\n\u0414\u0438\u0441\u043f\u043b\u0435\u0458:15.6\" (39.6cm)\n\u0420\u0435\u0437\u043e\u043b\u0443\u0446\u0438\u0458\u0430: (1920x1080) FHD, 120Hz 250 nits WVA Anti- Glare LED Backlit Narrow Border Display\n\u041f\u0440\u043e\u0446\u0435\u0441\u043e\u0440:AMD Ryzen\u2122 3 7330U 4-core/8-thread\n\u0413\u0440\u0430\u0444\u0438\u043a\u0430: AMD Radeon\u2122 Graphics\nRAM \u043c\u0435\u043c\u043e\u0440\u0438\u0458\u0430: 8 GB, DDR4, 3200 MT/s\n\u0414\u0438\u0441\u043a (Storage):256 GB, M.2, PCIe NVMe, SSD\nWi-Fi 5 RTL8821CE, 1x1, 802.11ac, MU-MIMO, Bluetooth\u00ae wireless card\n\u041a\u0430\u043c\u0435\u0440\u0430:1080p at 30 fps FHD camera\n\u041e\u043f\u0435\u0440\u0430\u0442\u0438\u0432\u0435\u043d \u0441\u0438\u0441\u0442\u0435\u043c:Ubuntu\n\u041f\u043e\u0440\u0442\u0438:\n1 USB 3.2 Gen 1 port\n1 USB 3.2 Gen 1 Type-C\u00ae port\n1 USB 2.0 port\n1 headset (headphone and microphone combo) port\n1 HDMI 1.4 port\n1 RJ45 Ethernet port (flip-down)\n\u0411\u0430\u0442\u0435\u0440\u0438\u0458\u0430: 4 Cell, 54 Wh, integrated\n\u041f\u043e\u043b\u043d\u0430\u0447: 65 Watt AC Adapter",
    "features": {
        "screen_size_inches": 15.6,
        "screen_resolution": "1920x1080",
        "screen_refresh_rate_hz": 120,
        "screen_brightness_nits": 250,
        "processor_model": "AMD Ryzen\u2122 3 7330U",
        "processor_cores": 4,
        "processor_threads": 8,
        "gpu_model": "AMD Radeon\u2122 Graphics",
        "ram_size_gb": 8,
        "ram_type": "DDR4",
        "storage_size_gb": 256,
        "storage_type": "M.2, PCIe NVMe, SSD",
        "wifi_standard": "Wi-Fi 5",
        "bluetooth_version": null,
        "usb_type_c_ports": 1,
        "usb_type_a_ports": 2,
        "hdmi_ports": 1,
        "audio_jack_ports": 1,
        "operating_system": "Ubuntu",
        "battery_capacity_wh": 54
    }
}