{
    "url": "https://www.neptun.mk/categories/prenosni_kompjuteri/HP-15s-fq5346nia-i3-1215U-8GB-512GB-7K5K5EA",
    "title": "\u041b\u0410\u041f\u0422\u041e\u041f HP 15S FQ5346NIA I3-1215U/8GB/512GB 7K5K5EA",
    "warranty_months": 36,
    "regular_price_mkd": 29999,
    "happy_price_mkd": 19799,
    "category": "prenosni_kompjuteri",
    "device_type": "Laptop",
    "description": "\u041b\u0430\u043f\u0442\u043e\u043f\n\u0414\u0438\u0441\u043f\u043b\u0435\u0458:15.6\" (39.6 cm)\n\u0420\u0435\u0437\u043e\u043b\u0443\u0446\u0438\u0458\u0430:(1920 x 1280) FHD, micro-edge, anti-glare, 250 nits, 45% NTSC\n\u0427\u0438\u043f\u0441\u0435\u0442: Intel\u00ae Integrated SoC\n\u041f\u0440\u043e\u0446\u0435\u0441\u043e\u0440: Intel\u00ae Core\u2122 i3-1215U (up to 4.4 GHz with Intel\u00ae Turbo Boost Technology, 10 MB L3 cache, 6 cores, 8 threads)\n\u0413\u0440\u0430\u0444\u0438\u043a\u0430: Intel\u00ae UHD Graphics\nRAM \u041c\u0435\u043c\u043e\u0440\u0438\u0458\u0430: 8 GB DDR4-3200 MHz RAM (1 x 8 GB)\n\u0414\u0438\u0441\u043a (Storage): 512 GB PCIe\u00ae NVMe\u2122 M.2 SSD\n\u0411\u0435\u0437 \u043e\u043f\u0435\u0440\u0430\u0442\u0438\u0432\u0435\u043d \u0441\u0438\u0441\u0442\u0435\u043c\nRealtek RTL8822CE 802.11a/b/g/n/ac (2x2) Wi-Fi\u00ae and Bluetooth\u00ae 5 wireless card\n\u041a\u0430\u043c\u0435\u0440\u0430:HP True Vision 720p HD camera with temporal noise reduction and integrated dual array digital microphones\n\u0410\u0443\u0434\u0438\u043e:Dual speakers\n\u041f\u043e\u0440\u0442\u0438:\n1 USB Type-C\u00ae 5Gbps signaling rate\n2 USB Type-A 5Gbps signaling rate\n1 AC smart pin\n1 HDMI 1.4b\n1 headphone/microphone combo\n\u041d\u0430\u043f\u0430\u0458\u0430\u045a\u0435:45 W Smart AC power adapter\n\u0411\u0430\u0442\u0435\u0440\u0438\u0458\u0430:3-cell, 41 Wh Up to 7 hours and 30 minutes",
    "features": {
        "screen_size_inches": 15.6,
        "screen_resolution": "1920 x 1280",
        "screen_brightness_nits": 250,
        "processor_model": "Intel\u00ae Core\u2122 i3-1215U",
        "processor_cores": 6,
        "processor_threads": 8,
        "gpu_model": "Intel\u00ae UHD Graphics",
        "ram_size_gb": 8,
        "ram_type": "DDR4",
        "storage_size_gb": 512,
        "storage_type": "PCIe\u00ae NVMe\u2122 M.2 SSD",
        "wifi_standard": "Wi-Fi\u00ae and Bluetooth\u00ae 5",
        "usb_type_c_ports": 1,
        "usb_type_a_ports": 2,
        "hdmi_ports": 1,
        "audio_jack_ports": 1
    }
}