{
    "url": "https://www.neptun.mk/categories/prenosni_kompjuteri/MacBook-Pro-14-M3-PRO-11C-CPU-14C-GPU-18GB-512GB-Silver-mrx63ze-a",
    "title": "\u041b\u0410\u041f\u0422\u041e\u041f APPLE MACBOOK PRO 14 M3 PRO/11C CPU/14C GPU/18GB/512GB SILVER MRX63ZE/A",
    "warranty_months": 12,
    "regular_price_mkd": 153599,
    "happy_price_mkd": 145999,
    "category": "prenosni_kompjuteri",
    "device_type": "Laptop",
    "description": "\u041b\u0430\u043f\u0442\u043e\u043f\n\u0414\u0438\u0441\u043f\u043b\u0435\u0458:14.2\"(36cm) Liquid Retina XDR display\n\u041f\u0440\u043e\u0446\u0435\u0441\u043e\u0440:Apple M3\n11-core CPU with 5 performance cores and 6 efficiency cores\n14-core GPU\nHardware-accelerated ray tracing\n16-core Neural Engine\n150GB/s memory bandwidth\n\u0413\u0440\u0430\u0444\u0438\u043a\u0430: 14-core GPU\nRAM \u043c\u0435\u043c\u043e\u0440\u0438\u0458\u0430:18GB\n\u0414\u0438\u0441\u043a (Storage): 512GB SSD\n1080p FaceTime HD \u043a\u0430\u043c\u0435\u0440\u0430\n\u0412\u0433\u0440\u0430\u0434\u0435\u043d\u0438 \u043c\u0438\u043a\u0440\u043e\u0444\u043e\u043d\u0438\nBacklit Magic Keyboard\nTouch ID\nAmbient light sensor\nForce Touch trackpad\nBluetooth 5.3\nWireless: Wi-Fi 6E (802.11ax)\nSDXC card slot\nHDMI port\n3.5 mm headphone jack\nMagSafe 3 port\nTwo Thunderbolt / USB 4 ports with support for:\nCharging\nDisplayPort\nThunderbolt 3 (up to 40Gb/s)\nUSB 4 (up to 40Gb/s)\n\u0411\u0430\u0442\u0435\u0440\u0438\u0458\u0430: \u0434\u043e 22 \u0447\u0430\u0441\u0430\n\u041f\u043e\u043b\u043d\u0430\u0447: 70W USB-C",
    "features": {
        "screen_size_inches": 14.2,
        "screen_resolution": null,
        "screen_refresh_rate_hz": null,
        "screen_brightness_nits": null,
        "screen_type": "Liquid Retina XDR",
        "processor_model": "Apple M3",
        "processor_cores": 11,
        "processor_threads": null,
        "processor_base_clock_ghz": null,
        "processor_max_clock_ghz": null,
        "gpu_model": "14-core GPU",
        "gpu_memory_gb": null,
        "ram_size_gb": 18,
        "ram_type": null,
        "storage_size_gb": 512,
        "storage_type": "SSD",
        "operating_system": null,
        "wifi_standard": "Wi-Fi 6E",
        "bluetooth_version": 5.3,
        "usb_type_c_ports": 2,
        "usb_type_a_ports": null,
        "hdmi_ports": 1,
        "audio_jack_ports": 1,
        "card_reader": "SDXC",
        "keyboard_type": "Backlit Magic Keyboard",
        "audio_feature_1": null,
        "battery_capacity_wh": null,
        "battery_cells": null,
        "security_feature_1": "Touch ID"
    }
}