{
    "url": "https://www.neptun.mk/categories/prenosni_kompjuteri/ASUS-Zenbook-15-OLED-UM3504DA-MA280W-R5-7535U-16GB-DDR5-512GB-WIN11",
    "title": "\u041b\u0410\u041f\u0422\u041e\u041f ASUS ZENBOOK 15 OLED UM3504DA-MA280W R5-7535U/16GB DDR5/512GB/WIN11",
    "warranty_months": 24,
    "regular_price_mkd": 53999,
    "happy_price_mkd": 48999,
    "category": "prenosni_kompjuteri",
    "device_type": "Laptop",
    "description": "\u041b\u0430\u043f\u0442\u043e\u043f\n\u0414\u0438\u0441\u043f\u043b\u0435\u0458: 15.6 (39.6cm)\n\u0420\u0435\u0437\u043e\u043b\u0443\u0446\u0438\u0458\u0430:2.8K(2880 x 1620) OLED, 120Hz, 0.2ms, 400nits\n\u041f\u0440\u043e\u0446\u0435\u0441\u043e\u0440:AMD Ryzen 5 7535U Mobile Processor 2.9GHz (6-core/12-thread, 12MB cache, up to 4.55 GHz)\n\u0413\u0440\u0430\u0444\u0438\u043a\u0430:AMD Radeon Graphics\nRAM \u043c\u0435\u043c\u043e\u0440\u0438\u0458\u0430:16GB LPDDR5\n\u0414\u0438\u0441\u043a (Storage): 512GB M.2 NVMe PCIe 4.0 SSD\nBacklit Chiclet Keyboard with Num-key\n\u041e\u043f\u0435\u0440\u0430\u0442\u0438\u0432\u0435\u043d \u0441\u0438\u0441\u0442\u0435\u043c: Windows 11 Home\nWi-Fi 6E(802.11ax) (Dual band) 2*2 + Bluetooth   5.3\nFHD camera with IR function to support Windows Hello\n\u041f\u043e\u0440\u0442\u0438:\n1x USB 3.2 Gen 1 Type-A\n1x USB 3.2 Gen 2 Type-C support display / power delivery\n1x USB 4.0 Gen 3 Type-C support display / power delivery\n1x HDMI 2.1 TMDS\n1x 3.5mm Combo Audio Jack\n\u0410\u0443\u0434\u0438\u043e:Smart Amp Technology\nHarman/kardon (Premium)\n\u0412\u0433\u0440\u0430\u0434\u0435\u043d \u0437\u0432\u0443\u0447\u043d\u0438\u043a\n\u0412\u0433\u0440\u0430\u0434\u0435\u043d \u043c\u0438\u043a\u0440\u043e\u0444\u043e\u043d\n\u0411\u0430\u0442\u0435\u0440\u0438\u0458\u0430:67WHrs, 4S1P, 4-cell Li-ion\n65W AC Adapter",
    "features": {
        "screen_size_inches": 15.6,
        "screen_resolution": "2880 x 1620",
        "screen_refresh_rate_hz": 120,
        "screen_brightness_nits": 400,
        "screen_type": "OLED",
        "processor_model": "AMD Ryzen 5 7535U Mobile Processor",
        "processor_cores": 6,
        "processor_threads": 12,
        "processor_base_clock_ghz": 2.9,
        "processor_max_clock_ghz": 4.55,
        "gpu_model": "AMD Radeon Graphics",
        "ram_size_gb": 16,
        "ram_type": "LPDDR5",
        "storage_size_gb": 512,
        "storage_type": "M.2 NVMe PCIe 4.0 SSD",
        "operating_system": "Windows 11 Home",
        "wifi_standard": "Wi-Fi 6E",
        "bluetooth_version": 5.3,
        "usb_type_c_ports": 2,
        "usb_type_a_ports": 1,
        "hdmi_ports": 1,
        "audio_jack_ports": 1,
        "keyboard_type": "Backlit Chiclet Keyboard",
        "audio_feature_1": "Smart Amp Technology",
        "battery_capacity_wh": 67,
        "battery_cells": 4
    }
}