{
    "url": "https://www.neptun.mk/categories/prenosni_kompjuteri/DELL-Vostro-3520-i3-1215U-8GB-256GB",
    "title": null,
    "warranty_months": 36,
    "regular_price_mkd": 24999,
    "happy_price_mkd": 20499,
    "category": "prenosni_kompjuteri",
    "device_type": "Laptop",
    "description": "\u041b\u0430\u043f\u0442\u043e\u043f\n\u0414\u0438\u0441\u043f\u043b\u0435\u0458:15.6\" (39.6cm)\n\u0420\u0435\u0437\u043e\u043b\u0443\u0446\u0438\u0458\u0430: (1920x1080) FHD, 120Hz 250 nits WVA Anti- Glare LED Backlit Narrow Border Display\n\u041f\u0440\u043e\u0446\u0435\u0441\u043e\u0440:12th Gen Intel\u00ae Core\u2122 i3-1215U (10MB Cache, up to 4.4 GHz, 6 cores)\n\u0413\u0440\u0430\u0444\u0438\u043a\u0430: Intel\u00ae UHD Graphics\nRAM \u043c\u0435\u043c\u043e\u0440\u0438\u0458\u0430: 8 GB, 1 x 8 GB, DDR4, 3200MHz\n\u0414\u0438\u0441\u043a (Storage): 256 GB, M.2, PCIe NVMe, SSD\nWi-Fi 5 (Wi-Fi 802.11ac)+ Bluetooth 5.1\n\u041a\u0430\u043c\u0435\u0440\u0430: 720p at 30 fps HD camera Single integrated microphone\n\u041e\u043f\u0435\u0440\u0430\u0442\u0438\u0432\u0435\u043d \u0441\u0438\u0441\u0442\u0435\u043c:Ubuntu 20.04\nBacklit Keyboard + FingerPrint\n\u041f\u043e\u0440\u0442\u0438:\n2 x USB 3.2 Gen 1 port\n1 x USB 2.0 port\n1 x Audio jack\n1 x HDMI 1.4 port\n1 x Flip-Down RJ-45 port\n1 x SD 3.0 card slot\n\u0411\u0430\u0442\u0435\u0440\u0438\u0458\u0430: 3cell 41WHr\n\u041f\u043e\u043b\u043d\u0430\u0447: 65 Watt AC Adapter",
    "features": {
        "screen_size_inches": 15.6,
        "screen_resolution": "1920 x 1080",
        "screen_refresh_rate_hz": 120,
        "screen_brightness_nits": 250,
        "processor_model": "12th Gen Intel\u00ae Core\u2122 i3-1215U",
        "processor_cores": 6,
        "processor_base_clock_ghz": null,
        "processor_max_clock_ghz": 4.4,
        "gpu_model": "Intel\u00ae UHD Graphics",
        "ram_size_gb": 8,
        "ram_type": "DDR4",
        "storage_size_gb": 256,
        "storage_type": "M.2, PCIe NVMe, SSD",
        "wifi_standard": "Wi-Fi 5",
        "bluetooth_version": 5.1,
        "usb_type_c_ports": 0,
        "usb_type_a_ports": 3,
        "hdmi_ports": 1,
        "audio_jack_ports": 1,
        "card_reader": "SD 3.0",
        "keyboard_type": "Backlit Keyboard",
        "battery_capacity_wh": 41,
        "battery_cells": 3
    }
}