{
    "url": "https://www.neptun.mk/categories/prenosni_kompjuteri/HP-ProBook-450-G9-i5-1235U-8GB-512GB-6F1E6EA",
    "title": "\u041b\u0410\u041f\u0422\u041e\u041f HP PROBOOK 450 G9 I5-1235U/8GB/512GB 6F1E6EA",
    "warranty_months": 12,
    "regular_price_mkd": 42999,
    "happy_price_mkd": 29999,
    "category": "prenosni_kompjuteri",
    "device_type": "Laptop",
    "description": "\u041b\u0430\u043f\u0442\u043e\u043f\n\u0414\u0438\u0441\u043f\u043b\u0435\u0458:15.6\" (39.6cm)\n\u0420\u0435\u0437\u043e\u043b\u0443\u0446\u0438\u0458\u0430:(1920 x 1080) FHD IPS, narrow bezel, anti-glare, 250 nits, 45% NTSC\n\u041f\u0440\u043e\u0446\u0435\u0441\u043e\u0440:Intel\u00ae Core\u2122 i5-1235U (up to 4.4 GHz with Intel\u00ae Turbo Boost Technology, 12 MB L3 cache, 10 cores, 12 threads)\n\u0413\u0440\u0430\u0444\u0438\u043a\u0430:Intel\u00ae Iris\u00ae X? Graphics\nRAM \u043c\u0435\u043c\u043e\u0440\u0438\u0458\u0430:8 GB DDR4-3200 MHz\n\u0414\u0438\u0441\u043a (Storage):512 GB PCIe\u00ae NVMe\u2122 M.2 SSD\n\u0411\u0435\u0437 \u043e\u043f\u0435\u0440\u0430\u0442\u0438\u0432\u0435\u043d \u0441\u0438\u0441\u0442\u0435\u043c (FreeDOS)\n\u041a\u0430\u043c\u0435\u0440\u0430:720p HD privacy camera\nWi-Fi 6 802.11ax\nBluetooth\u00ae 5.2\n\u041f\u043e\u0440\u0442\u0438:\n3 SuperSpeed USB Type-A\n1 SuperSpeed USB Type-C\u00ae\n1 headphone/microphone combo\n1 AC power\n1 RJ-45\n1 HDMI 2.1b\nPower:HP Smart 65 W External AC power adapter\n\u0411\u0430\u0442\u0435\u0440\u0438\u0458\u0430:HP Long Life 3-cell, 51 Wh Li-ion",
    "features": {
        "screen_size_inches": 15.6,
        "screen_resolution": "1920 x 1080",
        "screen_brightness_nits": 250,
        "screen_type": "FHD IPS",
        "processor_model": "Intel\u00ae Core\u2122 i5-1235U",
        "processor_cores": 10,
        "processor_threads": 12,
        "processor_base_clock_ghz": null,
        "processor_max_clock_ghz": 4.4,
        "gpu_model": "Intel\u00ae Iris\u00ae X? Graphics",
        "ram_size_gb": 8,
        "ram_type": "DDR4",
        "storage_size_gb": 512,
        "storage_type": "PCIe\u00ae NVMe\u2122 M.2 SSD",
        "operating_system": "\u0411\u0435\u0437 \u043e\u043f\u0435\u0440\u0430\u0442\u0438\u0432\u0435\u043d \u0441\u0438\u0441\u0442\u0435\u043c (FreeDOS)",
        "wifi_standard": "Wi-Fi 6 802.11ax",
        "bluetooth_version": 5.2,
        "usb_type_c_ports": 1,
        "usb_type_a_ports": 3,
        "hdmi_ports": 1,
        "audio_jack_ports": 1,
        "battery_capacity_wh": 51
    }
}