{
    "url": "https://www.neptun.mk/categories/prenosni_kompjuteri/HP-Pavilion-15-eg2188nia-i5-1235U-8GB-512GB-MX550-2GB-GDDR6-797A8EA",
    "title": "\u041b\u0410\u041f\u0422\u041e\u041f HP PAVILION 15-EG2188NIA I5-1235U/8GB/512GB/MX550 2GB GDDR6 797A8EA",
    "warranty_months": 36,
    "regular_price_mkd": 53999,
    "happy_price_mkd": 35999,
    "category": "prenosni_kompjuteri",
    "device_type": "Laptop",
    "description": "\u041b\u0430\u043f\u0442\u043e\u043f\n\u0414\u0438\u0441\u043f\u043b\u0435\u0458:15.6\" (39.6 cm)\n\u0420\u0435\u0437\u043e\u043b\u0443\u0446\u0438\u0458\u0430:(1920 x 1080) FHD,  IPS, micro-edge, anti-glare, 250 nits, 45% NTSC\nChipset: Intel\u00ae Integrated SoC\n\u041f\u0440\u043e\u0446\u0435\u0441\u043e\u0440: Intel\u00ae Core\u2122 i5-1235U (up to 4.4 GHz with Intel\u00ae Turbo Boost Technology, 12 MB L3 cache, 10 cores, 12 threads)\n\u0413\u0440\u0430\u0444\u0438\u043a\u0430:NVIDIA\u00ae GeForce\u00ae MX550 2 GB GDDR6\nRAM \u043c\u0435\u043c\u043e\u0440\u0438\u0458\u0430: 8 GB DDR4-3200 MHz (1 x 8 GB)\n\u0414\u0438\u0441\u043a (Storage): 512GB SSD PCIe\u00ae NVMe\u2122\n\u0411\u0435\u0437 \u043e\u043f\u0435\u0440\u0430\u0442\u0438\u0432\u0435\u043d \u0441\u0438\u0441\u0442\u0435\u043c\nMediaTek Wi-Fi 6 MT7921 (2x2) and Bluetooth\u00ae 5.3 wireless card (supporting gigabit data rate)\nHP Wide Vision 720p HD camera with temporal noise reduction and integrated dual array digital microphones\n\u0410\u0443\u0434\u0438\u043e:Audio by B&O; Dual speakers HP Audio Boost\n\u041f\u043e\u0440\u0442\u0438:\n1 USB Type-C\u00ae 10Gbps signaling rate (USB Power Delivery, DisplayPort\u2122 1.4, HP Sleep and Charge)\n2 USB Type-A 5Gbps signaling rate\n1 AC smart pin\n1 HDMI 2.1\n1 headphone/microphone combo\n65 W Smart AC power adapter\n\u0411\u0430\u0442\u0435\u0440\u0438\u0458\u0430: 3-cell, 41 Wh Li-ion",
    "features": {
        "screen_size_inches": 15.6,
        "screen_resolution": "1920 x 1080",
        "screen_brightness_nits": 250,
        "screen_type": "IPS",
        "processor_model": "Intel\u00ae Core\u2122 i5-1235U",
        "processor_cores": 10,
        "processor_threads": 12,
        "processor_max_clock_ghz": 4.4,
        "gpu_model": "NVIDIA\u00ae GeForce\u00ae MX550",
        "gpu_memory_gb": 2,
        "ram_size_gb": 8,
        "ram_type": "DDR4",
        "storage_size_gb": 512,
        "storage_type": "SSD",
        "wifi_standard": "Wi-Fi 6",
        "bluetooth_version": 5.3,
        "usb_type_c_ports": 1,
        "usb_type_a_ports": 2,
        "hdmi_ports": 1,
        "audio_jack_ports": 1,
        "audio_feature_1": "Audio by B&O",
        "battery_capacity_wh": 41,
        "battery_cells": 3
    }
}