{
    "url": "https://www.neptun.mk/categories/prenosni_kompjuteri/HP-Envy-x360-2-in-1-15-fe0002nn-OLED-Touch-i7-1355U-16GB-DDR5-1TB-RTX-3050-4GB-WIN11",
    "title": "\u041b\u0410\u041f\u0422\u041e\u041f HP ENVY X360 2-IN-1 15-FE0002NN OLED TOUCH I7-1355U/16GB DDR5/1TB/RTX 3050 4GB/WIN11",
    "warranty_months": 36,
    "regular_price_mkd": 102999,
    "happy_price_mkd": 88999,
    "category": "prenosni_kompjuteri",
    "device_type": "Laptop",
    "description": "\u041b\u0430\u043f\u0442\u043e\u043f\n\u0414\u0438\u0441\u043f\u043b\u0435\u0458:15.6\" (39.6 cm)\n\u0420\u0435\u0437\u043e\u043b\u0443\u0446\u0438\u0458\u0430:(1920 x 1080) FHD, OLED, multitouch-enabled, UWVA, edge-to-edge glass, micro-edge, Low Blue Light 500 nits\nChipset: Intel\u00ae integrated SoC\n\u041f\u0440\u043e\u0446\u0435\u0441\u043e\u0440: Intel\u00ae Core\u2122 i7-1355U (up to 5.0 GHz with Intel\u00ae Turbo Boost Technology, 12 MB L3 cache, 10 cores, 12 threads)\n\u0413\u0440\u0430\u0444\u0438\u043a\u0430:Intel\u00ae Iris\u00ae X? Graphics\nRAM \u041c\u0435\u043c\u0443\u0440\u0438\u0458\u0430: 16 GB LPDDR5-5200 MHz\n\u0414\u0438\u0441\u043a (Storage): 1 TB PCIe\u00ae NVMe\u2122 M.2 SSD\n\u041e\u043f\u0435\u0440\u0430\u0442\u0438\u0432\u0435\u043d \u0441\u0438\u0441\u0442\u0435\u043c: Windows 11 Home\nWi-Fi 6E AX211 (2x2)\nBluetooth: 5.3\n\u041a\u0430\u043c\u0435\u0440\u0430:HP Wide Vision 5MP IR camera with temporal noise reduction and integrated dual array digital microphones\n\u0410\u0443\u0434\u0438\u043e:Audio by Bang & Olufsen; Dual speakers; HP Audio Boost\n\u041f\u043e\u0440\u0442\u0438:\n2 Thunderbolt\u2122\n4 USB Type-C\u00ae\n1 USB Type-A\n1 HDMI 2.1\n1 headphone/microphone combo\nBacklit keyboard\n90 W USB Type-C\u00ae power adapter\n\u0411\u0430\u0442\u0435\u0440\u0438\u0458\u0430: 4-cell, 55 Wh Li-ion polymer",
    "features": {
        "screen_size_inches": 15.6,
        "screen_resolution": "1920 x 1080",
        "screen_brightness_nits": 500,
        "screen_type": "OLED",
        "processor_model": "Intel\u00ae Core\u2122 i7-1355U",
        "processor_cores": 10,
        "processor_threads": 12,
        "processor_max_clock_ghz": 5.0,
        "gpu_model": "Intel\u00ae Iris\u00ae X? Graphics",
        "ram_size_gb": 16,
        "ram_type": "LPDDR5",
        "storage_size_gb": 1024,
        "storage_type": "PCIe\u00ae NVMe\u2122 M.2 SSD",
        "operating_system": "Windows 11 Home",
        "wifi_standard": "Wi-Fi 6E AX211",
        "bluetooth_version": 5.3,
        "usb_type_c_ports": 4,
        "usb_type_a_ports": 1,
        "hdmi_ports": 1,
        "audio_jack_ports": 1,
        "keyboard_type": "Backlit keyboard",
        "audio_feature_1": "Audio by Bang & Olufsen",
        "battery_capacity_wh": 55
    }
}