{
    "url": "https://www.neptun.mk/categories/prenosni_kompjuteri/ASUS-Zenbook-14-UM3402YAR-KP511W-14--R5-7530U-8GB-512GB-WIN11",
    "title": "\u041bA\u041f\u0422\u041e\u041f ASUS ZENBOOK 14 UM3402YAR-KP511W 14\" R5-7530U/8GB/512GB/WIN11",
    "warranty_months": 24,
    "regular_price_mkd": 50999,
    "happy_price_mkd": 40999,
    "category": "prenosni_kompjuteri",
    "device_type": "Laptop",
    "description": "\u041b\u0430\u043f\u0442\u043e\u043f\n\u0414\u0438\u0441\u043f\u043b\u0435\u0458: 14\" (35.56cm)\n\u0420\u0435\u0437\u043e\u043b\u0443\u0446\u0438\u0458\u0430:(2560 x 1600) WQXGA, IPS, 60Hz, 400nits\n\u041f\u0440\u043e\u0446\u0435\u0441\u043e\u0440:AMD Ryzen 5 7530U Mobile Processor (6-core/12-thread, 16MB cache, up to 4.3 GHz max boost)\n\u0413\u0440\u0430\u0444\u0438\u043a\u0430:AMD Radeon\u00ae Graphics\nRAM \u043c\u0435\u043c\u043e\u0440\u0438\u0458\u0430:8GB DDR4\n\u0414\u0438\u0441\u043a (Storage):512GB M.2 NVMe PCIe 3.0 SSD\n\u041e\u043f\u0435\u0440\u0430\u0442\u0438\u0432\u0435\u043d \u0441\u0438\u0441\u0442\u0435\u043c: Windows 11 Home\n\u041a\u0430\u043c\u0435\u0440\u0430:1080p FHD camera\n\u0412\u0433\u0440\u0430\u0434\u0435\u043d \u043c\u0438\u043a\u0440\u043e\u0444\u043e\u043d\n\u0410\u0443\u0434\u0438\u043e: harman/kardon (Premium)\nWi-Fi 6E(802.11ax) (Dual band) 2*2\nBluetooth 5\nLED Backlit\nFingerPrint\n\u041f\u043e\u0440\u0442\u0438:\n1x USB 3.2 Gen 2 Type-A\n2x USB 3.2 Gen 2 Type-C support display / power delivery\n1x HDMI 2.1 TMDS\n1x 3.5mm Combo Audio Jack\nMicro SD card reader\n65W AC Adapter\n\u0411\u0430\u0442\u0435\u0440\u0438\u0458\u0430:75WHrs, 2S2P, 4-cell Li-ion",
    "features": {
        "screen_size_inches": 14,
        "screen_resolution": "2560 x 1600",
        "screen_refresh_rate_hz": 60,
        "screen_brightness_nits": 400,
        "screen_type": "WQXGA, IPS",
        "processor_model": "AMD Ryzen 5 7530U Mobile Processor",
        "processor_cores": 6,
        "processor_threads": 12,
        "processor_max_clock_ghz": 4.3,
        "gpu_model": "AMD Radeon\u00ae Graphics",
        "ram_size_gb": 8,
        "ram_type": "DDR4",
        "storage_size_gb": 512,
        "storage_type": "M.2 NVMe PCIe 3.0 SSD",
        "operating_system": "Windows 11 Home",
        "wifi_standard": "Wi-Fi 6E",
        "bluetooth_version": 5,
        "usb_type_a_ports": 1,
        "usb_type_c_ports": 2,
        "hdmi_ports": 1,
        "audio_jack_ports": 1,
        "card_reader": "Micro SD card reader",
        "audio_feature_1": "harman/kardon (Premium)",
        "battery_capacity_wh": 75,
        "battery_cells": 4,
        "security_feature_1": "FingerPrint"
    }
}