{
    "url": "https://www.neptun.mk/categories/prenosni_kompjuteri/LENOVO-IdeaPad-3-15ITL6-i5-1155G7-8GB-256GB-82H80322RM",
    "title": "\u041b\u0410\u041f\u0422\u041e\u041f LENOVO IDEAPAD 3 15ITL6 I5-1155G7/8GB/256GB",
    "warranty_months": 24,
    "regular_price_mkd": 29999,
    "happy_price_mkd": 25299,
    "category": "prenosni_kompjuteri",
    "device_type": "Laptop",
    "description": "\u041b\u0430\u043f\u0442\u043e\u043f\n\u0414\u0438\u0441\u043f\u043b\u0435\u0458:15.6\" (39.6cm)\n\u0420\u0435\u0437\u043e\u043b\u0443\u0446\u0438\u0458\u0430:(1920x1080) FHD TN 250nits Anti-glare\nChipset:Intel\u00ae SoC Platform\n\u041f\u0440\u043e\u0446\u0435\u0441\u043e\u0440: Intel\u00ae Core\u2122 i5-1155G7 (4C / 8T, 2.5 / 4.5GHz, 8MB)\n\u0413\u0440\u0430\u0444\u0438\u043a\u0430:Integrated Intel\u00ae Iris\u00ae Xe Graphics Functions as UHD Graphics\nRAM \u043c\u0435\u043c\u043e\u0440\u0438\u0458\u0430:8GB Soldered DDR4-3200\n\u0414\u0438\u0441\u043a (Storage):256GB SSD M.2 2242 PCIe\u00ae 3.0x4 NVMe\u2122\n\u0411\u0435\u0437 \u043e\u043f\u0435\u0440\u0430\u0442\u0438\u0432\u0435\u043d \u0441\u0438\u0441\u0442\u0435\u043c\n\u0410\u0443\u0434\u0438\u043e:High Definition (HD) Audio, Realtek\u00ae ALC3287 codec\n\u0417\u0432\u0443\u0447\u043d\u0438\u0446\u0438:Stereo speakers, 1.5W x2, Dolby\u00ae Audio\u2122\n\u041a\u0430\u043c\u0435\u0440\u0430:HD 720p with Privacy Shutter\n\u041c\u0438\u043a\u0440\u043e\u0444\u043e\u043d:2x, Array\nWLAN + Bluetooth: 11ac 2x2 + BT5.0\n\u041f\u043e\u0440\u0442\u0438:\n1x USB 2.0\n1x USB 3.2 Gen 1\n1x USB-C\u00ae 3.2 Gen 1 (support data transfer only)\n1x HDMI\u00ae 1.4b\n1x Card reader\n1x Headphone / microphone combo jack (3.5mm)\n1x Power connector\nPower Adapter - 65W Round Tip (2-pin, Wall-mount)\n\u0411\u0430\u0442\u0435\u0440\u0438\u0458\u0430:38Wh - MobileMark\u00ae 2018: 5.5 hr",
    "features": {
        "screen_size_inches": 15.6,
        "screen_resolution": "1920x1080",
        "screen_brightness_nits": 250,
        "screen_type": "FHD TN",
        "processor_model": "Intel\u00ae Core\u2122 i5-1155G7",
        "processor_cores": 4,
        "processor_threads": 8,
        "processor_base_clock_ghz": 2.5,
        "processor_max_clock_ghz": 4.5,
        "gpu_model": "Integrated Intel\u00ae Iris\u00ae Xe Graphics Functions as UHD Graphics",
        "ram_size_gb": 8,
        "ram_type": "DDR4-3200",
        "storage_size_gb": 256,
        "storage_type": "SSD M.2 2242 PCIe\u00ae 3.0x4 NVMe\u2122",
        "wifi_standard": "11ac 2x2",
        "bluetooth_version": 5.0,
        "usb_type_c_ports": 1,
        "usb_type_a_ports": 2,
        "hdmi_ports": 1,
        "audio_jack_ports": 1,
        "card_reader": "Card reader",
        "battery_capacity_wh": 38
    }
}