{
    "url": "https://www.neptun.mk/categories/prenosni_kompjuteri/LENOVO-IdeaPad-3-15IAU7-i5-1235U-16GB-512GB",
    "title": "\u041b\u0410\u041f\u0422\u041e\u041f LENOVO IDEAPAD 3 15IAU7 I5-1235U/16GB/512GB",
    "warranty_months": 24,
    "regular_price_mkd": 33999,
    "happy_price_mkd": 29999,
    "category": "prenosni_kompjuteri",
    "device_type": "Laptop",
    "description": "\u041b\u0430\u043f\u0442\u043e\u043f\n\u0414\u0438\u0441\u043f\u043b\u0435\u0439:15.6\" (39.6cm)\n\u0420\u0435\u0437\u043e\u043b\u0443\u0446\u0438\u0458\u0430:(1920x1080) FHD, IPS 300nits Anti-glare\n\u0427\u0438\u043f\u0441\u0435\u0442: Intel\u00ae SoC Platform\n\u041f\u0440\u043e\u0446\u0435\u0441\u043e\u0440: Intel\u00ae Core\u2122 i5-1235U, 10C (2P + 8E) / 12T, P-core 1.3 / 4.4GHz, E-core 0.9 / 3.3GHz, 12MB\n\u0413\u0440\u0430\u0444\u0438\u043a\u0430:Integrated Intel\u00ae Iris\u00ae Xe Graphics\nRAM \u043c\u0435\u043c\u043e\u0440\u0438\u0458\u0430: 16GB DDR4-3200\n\u0414\u0438\u0441\u043a (Storage): 512GB SSD M.2 2242 PCIe\u00ae 4.0x4 NVMe\u2122\nWi-Fi\u00ae 6, 11ax 2x2 + BT5.1\n\u041f\u043e\u0440\u0442\u0438:\n1x USB 2.0\n1x USB 3.2 Gen 1\n1x USB-C\u2122 3.2 Gen 1 (support data transfer, Power Delivery and DisplayPort\u2122 1.2)\n1x HDMI\u2122 1.4b\n1x Card reader\n1x Headphone / microphone combo jack (3.5mm)\n1x Power connector\n\u0411\u0435\u0437 \u043e\u043f\u0435\u0440\u0430\u0442\u0438\u0432\u0435\u043d \u0441\u0438\u0441\u0442\u0435\u043c\n\u0410\u0443\u0434\u0438\u043e:High Definition (HD) Audio\n\u0417\u0432\u0443\u0447\u043d\u0438\u0446\u0438:Stereo speakers, 1.5W x2, Dolby\u00ae Audio\u2122\n\u041a\u0430\u043c\u0435\u0440\u0430: HD 720p with Privacy Shutter\nPower Adapter - 65W Round Tip (3-pin)\n\u0411\u0430\u0442\u0435\u0440\u0438\u0458\u0430:45Wh",
    "features": {
        "screen_size_inches": 15.6,
        "screen_resolution": "1920x1080",
        "screen_brightness_nits": 300,
        "screen_type": "IPS",
        "processor_model": "Intel\u00ae Core\u2122 i5-1235U",
        "processor_cores": 10,
        "processor_threads": 12,
        "processor_base_clock_ghz": 1.3,
        "processor_max_clock_ghz": 4.4,
        "gpu_model": "Integrated Intel\u00ae Iris\u00ae Xe Graphics",
        "ram_size_gb": 16,
        "ram_type": "DDR4",
        "storage_size_gb": 512,
        "storage_type": "SSD",
        "wifi_standard": "Wi-Fi 6",
        "bluetooth_version": 5.1,
        "usb_type_c_ports": 1,
        "usb_type_a_ports": 2,
        "hdmi_ports": 1,
        "audio_jack_ports": 1,
        "card_reader": "Card reader",
        "audio_feature_1": "Dolby\u00ae Audio\u2122",
        "battery_capacity_wh": 45
    }
}