{
    "url": "https://www.neptun.mk/categories/prenosni_kompjuteri/HP-250-G9-i5-1235U-8GB-256GB-6F1Z9EA",
    "title": "\u041b\u0410\u041f\u0422\u041e\u041f HP 250 G9 I5-1235U/8GB/256GB",
    "warranty_months": 12,
    "regular_price_mkd": 35999,
    "happy_price_mkd": 22999,
    "category": "prenosni_kompjuteri",
    "device_type": "Laptop",
    "description": "\u041b\u0430\u043f\u0442\u043e\u043f\n\u0414\u0438\u0441\u043f\u043b\u0435\u0435:15.6\" (39.6cm)\n\u0420\u0435\u0437\u043e\u043b\u0443\u0446\u0438\u0458\u0430:(1920x1080) FHD, SVA, narrow bezel, anti-glare, 250 nits, 45% NTSC\n\u041f\u0440\u043e\u0446\u0435\u0441\u043e\u0440:Intel\u00ae Core\u2122 i5-1235U (up to 4.4 GHz with Intel\u00ae Turbo Boost Technology, 12 MB L3 cache, 10 cores, 12 threads)\n\u0413\u0440\u0430\u0444\u0438\u043a\u0430:Intel\u00ae Iris\u00ae X\u1d49 Graphics\nRAM \u043c\u0435\u043c\u043e\u0440\u0438\u0458\u0430: 8 GB DDR4-3200 MHz\n\u0414\u0438\u0441\u043a (Storage):256GB SSD PCIe\u00ae\n\u041d\u0435\u043c\u0430 \u043e\u043f\u0435\u0440\u0430\u0442\u0438\u0432\u0435\u043d \u0441\u0438\u0441\u0442\u0435\u043c\nRealtek RTL8822CE 802.11a/b/g/n/ac (2x2) Wi-Fi\u00ae and Bluetooth\u00ae 5 wireless card\nWLAN-Standard 802.11a/b/g/n/ac\n\u041a\u0430\u043c\u0435\u0440\u0430:720p HD camera\n\u041f\u043e\u0440\u0442\u0438:\n2 SuperSpeed USB Type-A 5Gbps signaling rate\n1 SuperSpeed USB Type-C\u00ae 5Gbps signaling rate\n1 RJ-45\n1 headphone/microphone combo\n1 HDMI 1.4b\n1 AC power\nPower:HP Smart 45 W External AC power adapter\n\u0411\u0430\u0442\u0435\u0440\u0438\u0458\u0430:3-cell, 41 Wh Li-ion",
    "features": {
        "screen_size_inches": 15.6,
        "screen_resolution": "1920x1080",
        "screen_brightness_nits": 250,
        "screen_type": "SVA",
        "processor_model": "Intel\u00ae Core\u2122 i5-1235U",
        "processor_cores": 10,
        "processor_threads": 12,
        "processor_max_clock_ghz": 4.4,
        "gpu_model": "Intel\u00ae Iris\u00ae X\u1d49 Graphics",
        "ram_size_gb": 8,
        "ram_type": "DDR4-3200 MHz",
        "storage_size_gb": 256,
        "storage_type": "SSD PCIe\u00ae",
        "wifi_standard": "802.11a/b/g/n/ac",
        "bluetooth_version": 5,
        "usb_type_c_ports": 1,
        "usb_type_a_ports": 2,
        "hdmi_ports": 1,
        "audio_jack_ports": 1,
        "battery_capacity_wh": 41,
        "battery_cells": 3
    }
}