{
    "url": "https://www.neptun.mk/categories/prenosni_kompjuteri/LENOVO-Yoga-6-13ABR8-13-3--Touch-R5-7530U-16GB-512GB-WIN11-83B20038RM",
    "title": "\u041b\u0410\u041f\u0422\u041e\u041f LENOVO YOGA 6 13ABR8 13.3\" TOUCH R5-7530U/16GB/512GB/WIN11 83B20038RM",
    "warranty_months": 24,
    "regular_price_mkd": 56999,
    "happy_price_mkd": 47999,
    "category": "prenosni_kompjuteri",
    "device_type": "Laptop",
    "description": "\u041b\u0430\u043f\u0442\u043e\u043f\n\u041f\u043e\u0434a\u0440o\u043a-Lenovo\u00ae Digital Pen\n\u0414\u0438\u0441\u043f\u043b\u0435\u0458:13.3\" (33.7)\n\u0420\u0435\u0437\u043e\u043b\u0443\u0446\u0438\u0458\u0430:(1920x1200) WUXGA IPS 300nits Glossy, 100% sRGB, Dolby\u00ae Vision\u2122, T\u00dcV Low Blue Light, Touch\n\u0415\u043a\u0440\u0430\u043d \u043d\u0430 \u0434\u043e\u043f\u0438\u0440: OGM, 10-point Multi-touch\nChipset:AMD SoC Platform\n\u041f\u0440\u043e\u0446\u0435\u0441\u043e\u0440: AMD Ryzen\u2122 5 7530U (6C / 12T, 2.0 / 4.5GHz, 3MB L2 / 16MB L3)\n\u0413\u0440\u0430\u0444\u0438\u043a\u0430:Integrated AMD Radeon\u2122 Graphics\nRAM \u043c\u0435\u043c\u043e\u0440\u0438\u0458\u0430:16GB LPDDR4x-4266\n\u0414\u0438\u0441\u043a (Storage):512GB SSD M.2 2242 PCIe\u00ae 4.0x4 NVMe\u00ae\n\u041e\u043f\u0435\u0440\u0430\u0442\u0438\u0432\u0435\u043d \u0441\u0438\u0441\u0442\u0435\u043c: Windows\u00ae 11 Home\n\u0410\u0443\u0434\u0438\u043e:High Definition (HD) Audio, Realtek\u00ae ALC3287 codec\n\u0417\u0432\u0443\u0447\u043d\u0438\u0446\u0438:Stereo speakers, 2W x2, optimized with Dolby\u00ae Atmos\u00ae\n\u041a\u0430\u043c\u0435\u0440\u0430:FHD 1080p + IR with Privacy Shutter\n\u041c\u0438\u043a\u0440\u043e\u0444\u043e\u043d:2x, Array\nBacklit\nWLAN + Bluetooth: Wi-Fi\u00ae 6, 11ax 2x2 + BT5.1\n\u041f\u043e\u0440\u0442\u0438:\n1x USB 3.2 Gen 1\n1x USB 3.2 Gen 1 (Always On)\n2x USB-C\u00ae 3.2 Gen 1 (support data transfer, Power Delivery 3.0 and DisplayPort\u2122 1.4)\n1x HDMI\u00ae 2.1, up to 4K/60Hz\n1x microSD card reader\n1x Headphone / microphone combo jack (3.5mm)\nPower Adapter - 45W USB-C\u00ae (3-pin)\n\u0411\u0430\u0442\u0435\u0440\u0438\u0458\u0430:Integrated 59Wh - MobileMark\u00ae 2018@200nits: 12.5 hr",
    "features": {
        "screen_size_inches": 13.3,
        "screen_resolution": "1920x1200",
        "screen_brightness_nits": 300,
        "screen_type": "WUXGA IPS",
        "processor_model": "AMD Ryzen\u2122 5 7530U",
        "processor_cores": 6,
        "processor_threads": 12,
        "processor_base_clock_ghz": 2.0,
        "processor_max_clock_ghz": 4.5,
        "gpu_model": "Integrated AMD Radeon\u2122 Graphics",
        "ram_size_gb": 16,
        "ram_type": "LPDDR4x",
        "storage_size_gb": 512,
        "storage_type": "SSD",
        "operating_system": "Windows\u00ae 11 Home",
        "wifi_standard": "Wi-Fi 6",
        "bluetooth_version": 5.1,
        "usb_type_c_ports": 2,
        "usb_type_a_ports": 2,
        "hdmi_ports": 1,
        "audio_jack_ports": 1,
        "card_reader": "microSD",
        "keyboard_type": "Backlit",
        "audio_feature_1": "Dolby\u00ae Atmos\u00ae",
        "battery_capacity_wh": 59
    }
}