{
    "url": "https://www.neptun.mk/categories/prenosni_kompjuteri/LENOVO--IdeaPad--Slim--3--15ABR8-R7-7730U-16GB-512GB",
    "title": "\u041b\u0410\u041f\u0422\u041e\u041f LENOVO IDEAPAD SLIM 3 15ABR8 R7-7730U/16GB/512GB",
    "warranty_months": 24,
    "regular_price_mkd": 36999,
    "happy_price_mkd": 33999,
    "category": "prenosni_kompjuteri",
    "device_type": "Laptop",
    "description": "\u041b\u0430\u043f\u0442\u043e\u043f\n\u0414\u0438\u0441\u043f\u043b\u0435\u0439:15.6\" (39.6cm)\n\u0420\u0435\u0437\u043e\u043b\u0443\u0446\u0438\u0458\u0430:(1920x1080) FHD, TN, 250nits, Anti-glare\n\u0427\u0438\u043f\u0441\u0435\u0442: AMD SoC Platform\n\u041f\u0440\u043e\u0446\u0435\u0441\u043e\u0440: AMD Ryzen\u2122 7 7730U (8C / 16T, 2.0 / 4.5GHz, 4MB L2 / 16MB L3)\n\u0413\u0440\u0430\u0444\u0438\u043a\u0430:AMD Radeon\u00ae Graphics\nRAM \u043c\u0435\u043c\u043e\u0440\u0438\u0458\u0430: 16GB DDR4-3200\n\u0414\u0438\u0441\u043a (Storage): 512GB SSD M.2 2280 PCIe\u00ae 3.0x4 NVMe\u00ae\nWi-Fi\u00ae 6, 11ax 2x2 + BT5.2\nBacklit keyboard\n\u041f\u043e\u0440\u0442\u0438:\n2x USB 3.2 Gen 1\n1x USB-C\u00ae 3.2 Gen 1 (support data transfer, Power Delivery and DisplayPort\u2122 1.2)\n1x HDMI\u00ae 1.4\n1x Headphone / microphone combo jack (3.5mm)\n1x Card reader\n1x Power connector\n\u0411\u0435\u0437 \u043e\u043f\u0435\u0440\u0430\u0442\u0438\u0432\u0435\u043d \u0441\u0438\u0441\u0442\u0435\u043c\n\u0410\u0443\u0434\u0438\u043e:High Definition (HD) Audio\n\u0417\u0432\u0443\u0447\u043d\u0438\u0446\u0438:Stereo speakers, 1.5W x2, Dolby\u00ae Audio\u2122\n\u041a\u0430\u043c\u0435\u0440\u0430: FHD 1080p with Privacy Shutter\n\u0411\u0430\u0442\u0435\u0440\u0438\u0458\u0430: \u0438\u043d\u0442\u0435\u0433\u0440\u0438\u0440\u0430\u043d\u0430 47Wh\n\u041f\u043e\u043b\u043d\u0430\u0447: 65W Round Tip (3-pin)",
    "features": {
        "screen_size_inches": 15.6,
        "screen_resolution": "1920x1080",
        "screen_brightness_nits": 250,
        "screen_type": "FHD, TN",
        "processor_model": "AMD Ryzen\u2122 7 7730U",
        "processor_cores": 8,
        "processor_threads": 16,
        "processor_base_clock_ghz": 2.0,
        "processor_max_clock_ghz": 4.5,
        "gpu_model": "AMD Radeon\u00ae Graphics",
        "ram_size_gb": 16,
        "ram_type": "DDR4-3200",
        "storage_size_gb": 512,
        "storage_type": "SSD M.2 2280 PCIe\u00ae 3.0x4 NVMe\u00ae",
        "wifi_standard": "Wi-Fi\u00ae 6, 11ax 2x2",
        "bluetooth_version": 5.2,
        "usb_type_c_ports": 1,
        "usb_type_a_ports": 2,
        "hdmi_ports": 1,
        "audio_jack_ports": 1,
        "card_reader": "Card reader",
        "keyboard_type": "Backlit keyboard",
        "audio_feature_1": "Dolby\u00ae Audio\u2122",
        "battery_capacity_wh": 47
    }
}