{
    "url": "https://www.neptun.mk/categories/prenosni_kompjuteri/LENOVO-IdeaPad-1-15AMN7-R5-7520U-16GB-DDR5-512GB",
    "title": "\u041b\u0410\u041f\u0422\u041e\u041f LENOVO IDEAPAD 1 15AMN7 R5-7520U/16GB DDR5/512GB",
    "warranty_months": 24,
    "regular_price_mkd": 26999,
    "happy_price_mkd": 24999,
    "category": "prenosni_kompjuteri",
    "device_type": "Laptop",
    "description": "\u041b\u0430\u043f\u0442\u043e\u043f\n\u0414\u0438\u0441\u043f\u043b\u0435\u0458:15.6\" (39.6cm)\n\u0420\u0435\u0437\u043e\u043b\u0443\u0446\u0438\u0458\u0430:(1920x1080) FHD, TN 220nits Anti-glare\n\u0427\u0438\u043f\u0441\u0435\u0442: AMD SoC Platform\n\u041f\u0440\u043e\u0446\u0435\u0441\u043e\u0440: AMD Ryzen\u2122 5 7520U (4C / 8T, 2.8 / 4.3GHz, 2MB L2 / 4MB L3)\n\u0413\u0440\u0430\u0444\u0438\u043a\u0430:Integrated AMD Radeon\u2122 610M Graphics\nRAM \u043c\u0435\u043c\u043e\u0440\u0438\u0458\u0430: 16GB Soldered LPDDR5-5500\n\u0414\u0438\u0441\u043a (Storage): 512GB SSD M.2 2242 PCIe\u00ae 4.0x4 NVMe\u2122\nWLAN + Bluetooth\n11ac 2x2 + BT5.0\n\u041f\u043e\u0440\u0442\u0438:\n1x Card reader\n1x HDMI\u00ae 1.4b\n1x Headphone / microphone combo jack (3.5mm)\n1x Power connector\n1x USB 2.0\n1x USB 3.2 Gen 1\n1x USB-C\u00ae 3.2 Gen 1 (support data transfer only)\n\u0411\u0435\u0437 \u043e\u043f\u0435\u0440\u0430\u0442\u0438\u0432\u0435\u043d \u0441\u0438\u0441\u0442\u0435\u043c\n\u0410\u0443\u0434\u0438\u043e:High Definition (HD) Audio\n\u0417\u0432\u0443\u0447\u043d\u0438\u0446\u0438:Stereo speakers, 1.5W x2, Dolby\u00ae Audio\u2122\n\u041a\u0430\u043c\u0435\u0440\u0430: HD 720p with Privacy Shutter\n\u041c\u0438\u043a\u0440\u043e\u0444\u043e\u043d: 2x, Array\n\u041f\u043e\u043b\u043d\u0430\u0447: 65W Round Tip (3-pin)\n\u0411\u0430\u0442\u0435\u0440\u0438\u0458\u0430: Integrated 42Wh",
    "features": {
        "screen_size_inches": 15.6,
        "screen_resolution": "1920x1080",
        "screen_brightness_nits": 220,
        "screen_type": "TN",
        "processor_model": "AMD Ryzen\u2122 5 7520U",
        "processor_cores": 4,
        "processor_threads": 8,
        "processor_base_clock_ghz": 2.8,
        "processor_max_clock_ghz": 4.3,
        "gpu_model": "Integrated AMD Radeon\u2122 610M Graphics",
        "ram_size_gb": 16,
        "ram_type": "LPDDR5-5500",
        "storage_size_gb": 512,
        "storage_type": "SSD",
        "wifi_standard": "11ac 2x2",
        "bluetooth_version": 5.0,
        "usb_type_c_ports": 1,
        "usb_type_a_ports": 2,
        "hdmi_ports": 1,
        "audio_jack_ports": 1,
        "card_reader": "Card reader",
        "audio_feature_1": "Dolby\u00ae Audio\u2122",
        "battery_capacity_wh": 42
    }
}