{
    "url": "https://www.neptun.mk/categories/prenosni_kompjuteri/HP-250-G9-i7-1255U-8GB-512GB-6S6V4EA",
    "title": "\u041b\u0410\u041f\u0422\u041e\u041f HP 250 G9 I7-1255U/8GB/512GB 6S6V4EA",
    "warranty_months": 12,
    "regular_price_mkd": 46999,
    "happy_price_mkd": 32999,
    "category": "prenosni_kompjuteri",
    "device_type": "Laptop",
    "description": "\u041b\u0430\u043f\u0442\u043e\u043f\n\u0414\u0438\u0441\u043f\u043b\u0435\u0458:15.6\" (39.6 cm)\n\u0420\u0435\u0437\u043e\u043b\u0443\u0446\u0438\u0458\u0430:(1920 x 1080) FHD, SVA, narrow bezel, anti-glare, 250 nits, 45% NTSC\n\u041f\u0440\u043e\u0446\u0435\u0441\u043e\u0440: Intel\u00ae Core\u2122 i7-1255U (up to 4.7 GHz with Intel\u00ae Turbo Boost Technology, 12 MB L3 cache, 10 cores, 12 threads)\n\u0413\u0440\u0430\u0444\u0438\u043a\u0430:Intel\u00ae Iris\u00ae X? Graphics\nRAM \u043c\u0435\u043c\u043e\u0440\u0438\u0458\u0430: 8 GB DDR4-3200 MHz (1 x 8 GB)\n\u0414\u0438\u0441\u043a (Storage): 512GB SSD PCIe\u00ae NVMe\u2122\n\u0411\u0435\u0437 \u043e\u043f\u0435\u0440\u0430\u0442\u0438\u0432\u0435\u043d \u0441\u0438\u0441\u0442\u0435\u043c\nRealtek Wi-Fi 6 (2x2) and Bluetooth\u00ae 5.2 wireless card (supporting gigabit data rate)\n\u041a\u0430\u043c\u0435\u0440\u0430:720p HD\n\u0410\u0443\u0434\u0438\u043e:Dual stereo speakers, dual array microphones\n\u041f\u043e\u0440\u0442\u0438:\n2 SuperSpeed USB Type-A 5Gbps signaling rate\n1 SuperSpeed USB Type-C\u00ae 5Gbps signaling rate\n1 RJ-45\n1 headphone/microphone\n1 HDMI 1.4b\n1 AC power\nHP Smart 45 W External AC power adapter\n\u0411\u0430\u0442\u0435\u0440\u0438\u0458\u0430:HP Long Life 3-cell, 41 Wh Li-ion",
    "features": {
        "screen_size_inches": 15.6,
        "screen_resolution": "1920 x 1080",
        "screen_brightness_nits": 250,
        "screen_type": "SVA",
        "processor_model": "Intel\u00ae Core\u2122 i7-1255U",
        "processor_cores": 10,
        "processor_threads": 12,
        "processor_base_clock_ghz": null,
        "processor_max_clock_ghz": 4.7,
        "gpu_model": "Intel\u00ae Iris\u00ae X? Graphics",
        "ram_size_gb": 8,
        "ram_type": "DDR4-3200 MHz",
        "storage_size_gb": 512,
        "storage_type": "SSD PCIe\u00ae NVMe\u2122",
        "wifi_standard": "Wi-Fi 6",
        "bluetooth_version": 5.2,
        "usb_type_c_ports": 1,
        "usb_type_a_ports": 2,
        "hdmi_ports": 1,
        "audio_jack_ports": 1,
        "keyboard_type": null,
        "audio_feature_1": null,
        "battery_capacity_wh": 41,
        "battery_cells": 3
    }
}