{
    "url": "https://www.neptun.mk/categories/prenosni_kompjuteri/LENOVO-IdeaPad-Slim-3-15IAN8-i3-N305-8GB-DDR5-256GB",
    "title": "\u041b\u0410\u041f\u0422\u041e\u041f LENOVO IDEAPAD SLIM 3 15IAN8 I3-N305/8GB DDR5/256GB",
    "warranty_months": 24,
    "regular_price_mkd": 21999,
    "happy_price_mkd": 17999,
    "category": "prenosni_kompjuteri",
    "device_type": "Laptop",
    "description": "\u041b\u0430\u043f\u0442\u043e\u043f\n\u0414\u0438\u0441\u043f\u043b\u0435\u0458:15.6\" (39.6cm)\n\u0420\u0435\u0437\u043e\u043b\u0443\u0446\u0438\u0458\u0430:15.6\" FHD (1920x1080) TN 250nits Anti-glare\n\u0427\u0438\u043f\u0441\u0435\u0442: Intel\u00ae SoC Platform\n\u041f\u0440\u043e\u0446\u0435\u0441\u043e\u0440: Intel\u00ae Core\u2122 i3-N305 (8C / 8T, 1.8 / 3.8GHz, 6MB)\n\u0413\u0440\u0430\u0444\u0438\u043a\u0430:Integrated Intel\u00ae UHD Graphics\nRAM \u043c\u0435\u043c\u043e\u0440\u0438\u0458\u0430: 8GB Soldered LPDDR5-4800\n\u0414\u0438\u0441\u043a (Storage): 256GB SSD M.2 2242 PCIe\u00ae 4.0x4 NVMe\u2122\n\u041f\u043e\u0440\u0442\u0438:\n1x Card reader\n1x HDMI\u2122 1.4\n1x Headphone / microphone combo jack (3.5mm)\n1x Power connector\n1x USB-C\u2122 3.2 Gen 1 (support data transfer, Power Delivery and DisplayPort\u2122 1.2)\n2x USB 3.2 Gen 1\n\u0411\u0435\u0437 \u043e\u043f\u0435\u0440\u0430\u0442\u0438\u0432\u0435\u043d \u0441\u0438\u0441\u0442\u0435\u043c\n\u0410\u0443\u0434\u0438\u043e:High Definition (HD) Audio\n\u0417\u0432\u0443\u0447\u043d\u0438\u0446\u0438:Stereo speakers, 1.5W x2, optimized with Dolby\u00ae Audio\u2122\n\u041a\u0430\u043c\u0435\u0440\u0430:HD 720p with Privacy Shutter\n\u0411\u0430\u0442\u0435\u0440\u0438\u0458\u0430: 47Wh\n\u041f\u043e\u043b\u043d\u0430\u0447: 65W Round Tip (3-pin)",
    "features": {
        "screen_size_inches": 15.6,
        "screen_resolution": "1920x1080",
        "screen_brightness_nits": 250,
        "screen_type": "TN",
        "processor_model": "Intel\u00ae Core\u2122 i3-N305",
        "processor_cores": 8,
        "processor_threads": 8,
        "processor_base_clock_ghz": 1.8,
        "processor_max_clock_ghz": 3.8,
        "gpu_model": "Integrated Intel\u00ae UHD Graphics",
        "ram_size_gb": 8,
        "ram_type": "LPDDR5",
        "storage_size_gb": 256,
        "storage_type": "SSD M.2 2242 PCIe\u00ae 4.0x4 NVMe\u2122",
        "hdmi_ports": 1,
        "audio_jack_ports": 1,
        "usb_type_c_ports": 1,
        "usb_type_a_ports": 2,
        "card_reader": "Card reader",
        "battery_capacity_wh": 47
    }
}