{
    "url": "https://www.neptun.mk/categories/prenosni_kompjuteri/NB-ASUS-Vivobook-S-14-Flip-TN3402YA-LZ030W-14--Touch-R5-7530U-16GB-512GB-WIN11",
    "title": "\u041b\u0410\u041f\u0422\u041e\u041f ASUS VIVOBOOK S 14 FLIP TN3402YA-LZ030W 14\" TOUCH R5-7530U/16GB/512GB/WIN11",
    "warranty_months": 24,
    "regular_price_mkd": 50999,
    "happy_price_mkd": 46999,
    "category": "prenosni_kompjuteri",
    "device_type": "Laptop",
    "description": "\u041b\u0430\u043f\u0442\u043e\u043f\n\u041f\u043e\u0434\u0430\u0440\u043e\u043a - Active Stylus SA200H\n\u0414\u0438\u0441\u043f\u043b\u0435\u0458:14.0\" (35.5cm)\n\u0420\u0435\u0437\u043e\u043b\u0443\u0446\u0438\u0458\u0430:WUXGA(1920 x 1200) IPS, Touch screen, 60Hz, 300nits\n\u041f\u0440\u043e\u0446\u0435\u0441\u043e\u0440:AMD Ryzen 5 7530U Mobile Processor 2.0GHz (6-core/12-thread, 16MB cache, up to 4.5 GHz)\n\u0413\u0440\u0430\u0444\u0438\u043a\u0430:AMD Radeon Graphics\nRAM \u043c\u0435\u043c\u043e\u0440\u0438\u0458\u0430:16GB DDR4\n\u0414\u0438\u0441\u043a (Storage): 512GB M.2 NVMe PCIe 3.0 SSD\nLED Backlit\n\u041e\u043f\u0435\u0440\u0430\u0442\u0438\u0432\u0435\u043d \u0441\u0438\u0441\u0442\u0435\u043c: Windows 11 Home\nWi-Fi 6E(802.11ax) (Dual band) 2*2 + Bluetooth 5.3\n1080p FHD camera with privacy shutter\nFingerPrint\n\u041f\u043e\u0440\u0442\u0438:\n1x USB 2.0 Type-A\n1x USB 3.2 Gen 2 Type-A\n1x USB 3.2 Gen 2 Type-C support display / power delivery\n1x HDMI 2.1 TMDS\n1x 3.5mm Combo Audio Jack\n1x DC-in\n\u0410\u0443\u0434\u0438\u043e:Smart Amp Technology\n\u0412\u0433\u0440\u0430\u0434\u0435\u043d\u0438 \u0437\u0432\u0443\u0447\u043d\u0438\u0446\u0438\n\u0412\u0433\u0440\u0430\u0434\u0435\u043d \u043c\u0438\u043a\u0440\u043e\u0444\u043e\u043d\n\u0411\u0430\u0442\u0435\u0440\u0438\u0458\u0430:50WHrs, 3S1P, 3-cell Li-ion\n45W AC Adapter",
    "features": {
        "screen_size_inches": 14,
        "screen_resolution": "1920 x 1200",
        "screen_refresh_rate_hz": 60,
        "screen_brightness_nits": 300,
        "screen_type": "IPS",
        "processor_model": "AMD Ryzen 5 7530U",
        "processor_cores": 6,
        "processor_threads": 12,
        "processor_base_clock_ghz": 2,
        "processor_max_clock_ghz": 4.5,
        "gpu_model": "AMD Radeon Graphics",
        "ram_size_gb": 16,
        "ram_type": "DDR4",
        "storage_size_gb": 512,
        "storage_type": "M.2 NVMe PCIe 3.0 SSD",
        "operating_system": "Windows 11 Home",
        "wifi_standard": "Wi-Fi 6E",
        "bluetooth_version": 5.3,
        "usb_type_a_ports": 2,
        "usb_type_c_ports": 1,
        "hdmi_ports": 1,
        "audio_jack_ports": 1,
        "keyboard_type": "LED Backlit",
        "security_feature_1": "FingerPrint",
        "battery_capacity_wh": 50,
        "battery_cells": 3
    }
}