{
    "url": "https://www.neptun.mk/categories/prenosni_kompjuteri/LENOVO-Yoga-7-14IRL8-14--Touch-i5-1340P-16GB-DDR5-512GB-WIN11",
    "title": "LENOVO Yoga 7 14IRL8 14\" Touch i5-1340P 16GB DDR5 512GB WIN11",
    "warranty_months": 24,
    "regular_price_mkd": 62999,
    "happy_price_mkd": 56999,
    "category": "prenosni_kompjuteri",
    "device_type": "Laptop",
    "description": "\u041b\u0430\u043f\u0442\u043e\u043f\n\u0414\u0438\u0441\u043f\u043b\u0435\u0439:14\" (35.56cm)\n\u0420\u0435\u0437\u043e\u043b\u0443\u0446\u0438\u0458\u0430:(1920x1200) WUXGA OLED 400nits Glossy, 100% DCI-P3, 60Hz, Dolby\u00ae Vision\u2122, TUV Low Blue Light, DisplayHDR\u2122 True Black 500, Glass, Touch\n\u0415\u043a\u0440\u0430\u043d \u043d\u0430 \u0434\u043e\u043f\u0438\u0440: OGM, 10-point Multi-touch\nChipset:Intel\u00ae SoC Platform\n\u041f\u0440\u043e\u0446\u0435\u0441\u043e\u0440: Intel\u00ae Core\u2122 i5-1340P, 12C (4P + 8E) / 16T, P-core 1.9 / 4.6GHz, E-core 1.4 / 3.4GHz, 12MB\n\u0413\u0440\u0430\u0444\u0438\u043a\u0430:Integrated Intel\u00ae Iris\u00ae Xe Graphics\nRAM \u043c\u0435\u043c\u043e\u0440\u0438\u0458\u0430:16GB Soldered LPDDR5-5200\n\u0414\u0438\u0441\u043a (Storage):512GB SSD M.2 2242 PCIe\u00ae 4.0x4 NVMe\u2122\n\u041e\u043f\u0435\u0440\u0430\u0442\u0438\u0432\u0435\u043d \u0441\u0438\u0441\u0442\u0435\u043c: Windows\u00ae 11 Home\n\u0410\u0443\u0434\u0438\u043e:High Definition (HD) Audio, Realtek\u00ae ALC3306 codec\n\u0417\u0432\u0443\u0447\u043d\u0438\u0446\u0438:Stereo speakers, 2W x2, optimized with Dolby\u00ae Atmos\u00ae, Smart Amplifier (AMP)\n\u041a\u0430\u043c\u0435\u0440\u0430:FHD 1080p + IR with Privacy Shutter\n\u041c\u0438\u043a\u0440\u043e\u0444\u043e\u043d:2x, Array\nBacklit\nWLAN + Bluetooth: Wi-Fi\u00ae 6E, 11ax 2x2 + BT5.1\n\u041f\u043e\u0440\u0442\u0438:\n1x HDMI\u00ae 1.4b\n1x Headphone / microphone combo jack (3.5mm)\n1x USB 3.2 Gen 1 (Always On)\n1x microSD card reader\n2x Thunderbolt\u2122 4 / USB4\u00ae 40Gbps (support data transfer, Power Delivery 3.0 and DisplayPort\u2122 1.4)\nPower Adapter - 65W USB-C\u00ae (3-pin)\n\u0411\u0430\u0442\u0435\u0440\u0438\u0458\u0430:Integrated 71Wh",
    "features": {
        "screen_size_inches": 14,
        "screen_resolution": "1920x1200",
        "screen_refresh_rate_hz": 60,
        "screen_brightness_nits": 400,
        "screen_type": "WUXGA OLED",
        "processor_model": "Intel\u00ae Core\u2122 i5-1340P",
        "processor_cores": 12,
        "processor_threads": 16,
        "processor_base_clock_ghz": 1.9,
        "processor_max_clock_ghz": 4.6,
        "gpu_model": "Integrated Intel\u00ae Iris\u00ae Xe Graphics",
        "ram_size_gb": 16,
        "ram_type": "LPDDR5-5200",
        "storage_size_gb": 512,
        "storage_type": "SSD",
        "operating_system": "Windows\u00ae 11 Home",
        "wifi_standard": "Wi-Fi\u00ae 6E",
        "bluetooth_version": 5.1,
        "usb_type_c_ports": 2,
        "usb_type_a_ports": 1,
        "hdmi_ports": 1,
        "audio_jack_ports": 1,
        "card_reader": "microSD",
        "keyboard_type": "Backlit",
        "audio_feature_1": "Dolby\u00ae Atmos\u00ae",
        "battery_capacity_wh": 71
    }
}