{
    "url": "https://www.neptun.mk/categories/prenosni_kompjuteri/HP-15-fc0066nia-R3-7320U-8GB-512GB",
    "title": "\u041b\u0410\u041f\u0422\u041e\u041f HP 15-FC0066NIA R3-7320U/8GB/512GB",
    "warranty_months": 36,
    "regular_price_mkd": 22999,
    "happy_price_mkd": 20499,
    "category": "prenosni_kompjuteri",
    "device_type": "Laptop",
    "description": "\u041b\u0430\u043f\u0442\u043e\u043f\n\u0414\u0438\u0441\u043f\u043b\u0435\u0458:15.6\" (39.6cm)\n\u0420\u0435\u0437\u043e\u043b\u0443\u0446\u0438\u0458\u0430:(1920 x 1080) FHD, micro-edge, anti-glare, 250 nits, 45% NTSC\n\u041f\u0440\u043e\u0446\u0435\u0441\u043e\u0440: AMD Ryzen\u2122 3 7320U (up to 4.1 GHz max boost clock, 4 MB L3 cache, 4 cores, 8 threads)\n\u0413\u0440\u0430\u0444\u0438\u043a\u0430:AMD Radeon\u2122 Graphics\nRAM \u043c\u0435\u043c\u043e\u0440\u0438\u0458\u0430:8GB LPDDR5 5500MHz\n\u0414\u0438\u0441\u043a (Storage):512 GB PCIe\u00ae NVMe\u2122 M.2 SSD\n\u0411\u0435\u0437 \u043e\u043f\u0435\u0440\u0430\u0442\u0438\u0432\u0435\u043d \u0441\u0438\u0441\u0442\u0435\u043c\n\u0410\u0443\u0434\u0438\u043e: Dual speakers\n\u041a\u0430\u043c\u0435\u0440\u0430:720p HD\n\u041f\u043e\u0440\u0442\u0438:\n1 USB Type-C\u00ae 5Gbps signaling rate (supports data transfer only and does not support charging or external monitors)\n2 USB Type-A 5Gbps signaling rate\n1 AC smart pin\n1 HDMI 1.4b\n1 headphone/microphone combo\nWireless: Realtek Wi-Fi 6 (1x1) and Bluetooth\u00ae 5.3 wireless card\nPower: 45 W Smart AC power adapter\n\u0411\u0430\u0442\u0435\u0440\u0438\u0458\u0430:HP Long Life 3-cell, 41 Wh Li-ion",
    "features": {
        "screen_size_inches": 15.6,
        "screen_resolution": "1920 x 1080",
        "screen_brightness_nits": 250,
        "processor_model": "AMD Ryzen\u2122 3 7320U",
        "processor_cores": 4,
        "processor_threads": 8,
        "processor_max_clock_ghz": 4.1,
        "gpu_model": "AMD Radeon\u2122 Graphics",
        "ram_size_gb": 8,
        "ram_type": "LPDDR5",
        "storage_size_gb": 512,
        "storage_type": "PCIe\u00ae NVMe\u2122 M.2 SSD",
        "wifi_standard": "Wi-Fi 6",
        "bluetooth_version": 5.3,
        "usb_type_c_ports": 1,
        "usb_type_a_ports": 2,
        "hdmi_ports": 1,
        "audio_jack_ports": 1
    }
}