{
    "url": "https://www.neptun.mk/categories/prenosni_kompjuteri/MacBook-Pro-16-M3-PRO-12C-CPU-18C-GPU-18GB-512GB-Silver-mrw43ze-a",
    "title": null,
    "warranty_months": 12,
    "regular_price_mkd": 182999,
    "happy_price_mkd": 177999,
    "category": "prenosni_kompjuteri",
    "device_type": "Laptop",
    "description": [
        "\u041b\u0430\u043f\u0442\u043e\u043f\n\u0414\u0438\u0441\u043f\u043b\u0435\u0458:16.2\"(41cm) Liquid Retina XDR display\n\u041f\u0440\u043e\u0446\u0435\u0441\u043e\u0440:Apple M3\n12-core CPU with 6 performance cores and 6 efficiency cores\n18-core GPU\nHardware-accelerated ray tracing\n16-core Neural Engine\n150GB/s memory bandwidth\n\u0413\u0440\u0430\u0444\u0438\u043a\u0430: 18-core GPU\nRAM \u043c\u0435\u043c\u043e\u0440\u0438\u0458\u0430:18GB\n\u0414\u0438\u0441\u043a (Storage): 512GB SSD\n1080p FaceTime HD camera\n\u0412\u0433\u0440\u0430\u0434\u0435\u043d\u0438 \u043c\u0438\u043a\u0440\u043e\u0444\u043e\u043d\u0438\nBacklit Magic Keyboard\nTouch ID\nAmbient light sensor\nForce Touch trackpad\nBluetooth 5.3\nWireless: Wi-Fi 6E (802.11ax)\nSDXC card slot\nHDMI port\n3.5 mm headphone jack\nMagSafe 3 port\nThree Thunderbolt 4 ports with support for:\nCharging\nDisplayPort\nThunderbolt 4 (up to 40Gb/s)\nUSB 4 (up to 40Gb/s)\n\u0411\u0430\u0442\u0435\u0440\u0438\u0458\u0430: \u0434\u043e 18 \u0447\u0430\u0441\u0430\n\u041f\u043e\u043b\u043d\u0430\u0447: 96W USB-C"
    ],
    "features": {
        "screen_size_inches": 16.2,
        "screen_type": "Liquid Retina XDR",
        "processor_model": "Apple M3",
        "processor_cores": 12,
        "gpu_model": "18-core GPU",
        "ram_size_gb": 18,
        "storage_size_gb": 512,
        "storage_type": "SSD",
        "wifi_standard": "Wi-Fi 6E",
        "bluetooth_version": 5.3,
        "hdmi_ports": 1,
        "audio_jack_ports": 1,
        "card_reader": "SDXC",
        "usb_type_c_ports": 3,
        "keyboard_type": "Backlit Magic Keyboard",
        "battery_capacity_wh": null,
        "battery_cells": null
    }
}