{
    "url": "https://www.neptun.mk/categories/prenosni_kompjuteri/LENOVO-LOQ-15IRH8-i5-13500H-16GB-DDR5-512GB-RTX-4060-8GB",
    "title": "Lenovo Legion 5 LOQ-15IRH8 15.6\" i5-13500H 16GB DDR5 512GB RTX 4060 8GB",
    "warranty_months": 24,
    "regular_price_mkd": 75999,
    "happy_price_mkd": 66999,
    "category": "prenosni_kompjuteri",
    "device_type": "Laptop",
    "description": "\u041b\u0430\u043f\u0442\u043e\u043f\n\u0414\u0438\u0441\u043f\u043b\u0435\u0458:15.6\" (39.5cm)\n\u0420\u0435\u0437\u043e\u043b\u0443\u0446\u0438\u0458\u0430:(1920 x 1080) FHD, IPS 350nits Anti-glare, 45% NTSC, 144Hz, G-SYNC\u00ae\n\u041f\u0440\u043e\u0446\u0435\u0441\u043e\u0440:Intel\u00ae Core\u2122 i5-13500H, 12C (4P + 8E) / 16T, P-core 2.6 / 4.7GHz, E-core 1.9 / 3.5GHz, 18MB\n\u0413\u0440\u0430\u0444\u0438\u043a\u0430:NVIDIA\u00ae GeForce RTX\u2122 4060 8GB GDDR6, Boost Clock 2370MHz, TGP 115W\n\u0412\u043d\u0430\u0442\u0440\u0435\u0448\u043d\u0430 \u043c\u0435\u043c\u043e\u0440\u0438\u0458\u0430:16GB DDR5-5200\n\u041c\u0435\u0434\u0438\u0443\u043c \u0437\u0430 \u0441\u043a\u043b\u0430\u0434\u0438\u0440\u0430\u045a\u0435:512GB SSD M.2 2242 PCIe\u00ae 4.0x4 NVMe\u00ae\n\u0411\u0435\u0437 \u043e\u043f\u0435\u0440\u0430\u0442\u0438\u0432\u0435\u043d \u0441\u0438\u0441\u0442\u0435\u043c\n\u0410\u0443\u0434\u0438\u043e:High Definition (HD) Audio, Realtek\u00ae ALC3287 codec\n\u0417\u0432\u0443\u0447\u043d\u0438\u0446\u0438:Stereo speakers, 2W x2, optimized with Nahimic Gaming Audio\n\u041a\u0430\u043c\u0435\u0440\u0430:HD 720p with E-shutter\n\u041c\u0438\u043a\u0440\u043e\u0444\u043e\u043d:2x, Array\nEthernet:100/1000M (RJ-45)\nWLAN + Bluetooth:Wi-Fi\u00ae 6, 11ax 2x2 + BT5.1\n\u041f\u043e\u0440\u0442\u0438:\n1x USB 3.2 Gen 1\n2x USB 3.2 Gen 2\n1x USB-C\u00ae 3.2 Gen 2 (support data transfer, Power Delivery 140W and DisplayPort\u2122 1.4)\n1x HDMI\u00ae 2.1, up to 8K/60Hz\n1x Ethernet (RJ-45)\n1x Headphone / microphone combo jack (3.5mm)\n1x Power connector\n\u0410\u0434\u0430\u043f\u0442\u0435\u0440 \u0437\u0430 \u043d\u0430\u043f\u043e\u0458\u0443\u0432\u0430\u045a\u0435:230W Slim Tip (3-pin)\n\u0411\u0430\u0442\u0435\u0440\u0438\u0458\u0430:Integrated 60Wh",
    "features": {
        "screen_size_inches": 15.6,
        "screen_resolution": "1920 x 1080",
        "screen_refresh_rate_hz": 144,
        "screen_brightness_nits": 350,
        "screen_type": "IPS",
        "processor_model": "Intel\u00ae Core\u2122 i5-13500H",
        "processor_cores": 12,
        "processor_threads": 16,
        "processor_base_clock_ghz": 2.6,
        "processor_max_clock_ghz": 4.7,
        "gpu_model": "NVIDIA\u00ae GeForce RTX\u2122 4060",
        "gpu_memory_gb": 8,
        "ram_size_gb": 16,
        "ram_type": "DDR5",
        "storage_size_gb": 512,
        "storage_type": "SSD",
        "operating_system": "\u0411\u0435\u0437 \u043e\u043f\u0435\u0440\u0430\u0442\u0438\u0432\u0435\u043d \u0441\u0438\u0441\u0442\u0435\u043c",
        "wifi_standard": "Wi-Fi 6",
        "bluetooth_version": 5.1,
        "usb_type_c_ports": 1,
        "usb_type_a_ports": 2,
        "hdmi_ports": 1,
        "audio_jack_ports": 1,
        "keyboard_type": null,
        "audio_feature_1": "Nahimic Gaming Audio",
        "battery_capacity_wh": 60,
        "battery_cells": null,
        "security_feature_1": null
    }
}