{
    "url": "https://www.neptun.mk/categories/gaming_laptopi/LENOVO-IdeaPad-Gaming-3-15IAH7-i7-12650H-16GB-512GB-RTX-3060-6GB-82S900KLRM",
    "title": "\u041b\u0410\u041f\u0422\u041e\u041f LENOVO GAMING 3 15IAH7 I7-12650H/16GB/512GB/RTX 3060 6GB",
    "warranty_months": 24,
    "regular_price_mkd": 78999,
    "happy_price_mkd": 68999,
    "category": "gaming_laptopi",
    "device_type": "Gaming Laptop",
    "description": "\u041b\u0430\u043f\u0442\u043e\u043f\n\u0414\u0438\u0441\u043f\u043b\u0435\u0439:15.6\" (39.6cm)\n\u0420\u0435\u0437\u043e\u043b\u0443\u0446\u0438\u0458\u0430:(1920x1080) FHD IPS 250nits Anti-glare, 45% NTSC, 120Hz\nChipset: Intel SoC Platform\n\u041f\u0440\u043e\u0446\u0435\u0441\u043e\u0440: Intel Core i7-12650H, 10C (6P + 4E) / 16T, P-core 2.3 / 4.7GHz, E-core 1.7 / 3.5GHz, 24MB)\n\u0413\u0440\u0430\u0444\u0438\u043a\u0430: NVIDIA GeForce RTX 3060 6GB GDDR6, Boost Clock 1642MH, TGP 105W\nRAM \u043c\u0435\u043c\u043e\u0440\u0438\u0458\u0430:16GB SO-DIMM DDR4-3200\n\u0414\u0438\u0441\u043a (Storage):512GB SSD M.2 2280 PCIe 3.0x4 NVMe\n\u0411\u0435\u0437 \u043e\u043f\u0435\u0440\u0430\u0442\u0438\u0432\u0435\u043d \u0441\u0438\u0441\u0442\u0435\u043c\n\u0410\u0443\u0434\u0438\u043e: High Definition (HD) Audio, Realtek ALC3287 codec\n\u0417\u0432\u0443\u0447\u043d\u0438\u0446\u0438:Stereo speakers, 2W x2, Nahimic Audio\n\u041a\u0430\u043c\u0435\u0440\u0430:HD 720p with Privacy Shutter\n\u041c\u0438\u043a\u0440\u043e\u0444\u043e\u043d:2x, Array\nWLAN + Bluetooth: Wi-Fi 6, 11ax 2x2 + BT5.1\n\u0422\u0430\u0441\u0442\u0430\u0442\u0443\u0440\u0430: Backlit, English\n\u041f\u043e\u0440\u0442\u0438:\n2x USB 3.2 Gen 1\n1x HDMI 2.0\n1x Ethernet (RJ-45)\n1x Headphone / microphone combo jack (3.5mm)\n1x Power connector\nPower Adapter - 230W Slim Tip (3-pin)\n\u0411\u0430\u0442\u0435\u0440\u0438\u0458\u0430:Integrated 60Wh - MobileMark 2018: 7.1 hr",
    "features": {
        "screen_size_inches": 15.6,
        "screen_resolution": "1920x1080",
        "screen_type": "FHD IPS",
        "screen_refresh_rate_hz": 120,
        "processor_model": "Intel Core i7-12650H",
        "processor_cores": 10,
        "processor_threads": 16,
        "processor_base_clock_ghz": 2.3,
        "processor_max_clock_ghz": 4.7,
        "gpu_model": "NVIDIA GeForce RTX 3060",
        "gpu_memory_gb": 6,
        "ram_size_gb": 16,
        "ram_type": "SO-DIMM DDR4-3200",
        "storage_size_tb": 0.512,
        "storage_type": "SSD M.2 2280 PCIe 3.0x4 NVMe",
        "operating_system": null,
        "wifi_standard": "Wi-Fi 6",
        "bluetooth_version": 5.1,
        "usb_type_c_ports": 0,
        "usb_type_a_ports": 2,
        "hdmi_ports": 1,
        "audio_jack_ports": 1,
        "card_reader": null,
        "keyboard_type": "Backlit, English",
        "audio_feature_1": "Stereo speakers, 2W x2, Nahimic Audio",
        "battery_capacity_wh": 60,
        "battery_cells": null,
        "security_feature_1": null
    }
}