{
    "url": "https://www.neptun.mk/categories/gaming_laptopi/ASUS-TUF-Gaming-F15-FX507ZU4-LP056-i7-12700H-16GB-1TB-RTX-4050-6GB",
    "title": "\u041b\u0410\u041f\u0422\u041e\u041f ASUS TUF GAMING F15 FX507ZU4-LP056 I7-12700H/16GB/1TB/RTX 4050 6GB",
    "warranty_months": 24,
    "regular_price_mkd": 79999,
    "happy_price_mkd": 69999,
    "category": "gaming_laptopi",
    "device_type": "Gaming Laptop",
    "description": "\u041b\u0430\u043f\u0442\u043e\u043f\n\u0414\u0438\u0441\u043f\u043b\u0435\u0458:15.6\" (39.6cm)\n\u0420\u0435\u0437\u043e\u043b\u0443\u0446\u0438\u0458\u0430:(1920 x 1080) FHD IPS 144Hz\n\u041f\u0440\u043e\u0446\u0435\u0441\u043e\u0440:12th Gen Intel Core i7-12700H Processor 2.3 GHz (24M Cache, up to 4.7 GHz, 14 cores:)\n\u0413\u0440\u0430\u0444\u0438\u043a\u0430:NVIDIA GeForce RTX 4050 6GB GDDR6\nRAM \u041c\u0435\u043c\u043e\u0440\u0438\u0458\u0430:16GB DDR4\n\u0414\u0438\u0441\u043a (Storage):1TB PCIe 4.0 NVMe M.2 SSD\n\u0411\u0435\u0437 \u043e\u043f\u0435\u0440\u0430\u0442\u0438\u0432\u0435\u043d \u0441\u0438\u0441\u0442\u0435\u043c\nBacklit Chiclet Keyboard 1-Zone RGB\nLAN 10/100/1000 Mbps\nWi-Fi 6(802.11ax) (Dual band) 2*2 + Bluetooth 5.2\n\u041f\u043e\u0440\u0442\u0438:\n1x RJ45 LAN port\n1x Thunderbolt 4 support DisplayPort\n1x USB 3.2 Gen 2 Type-C support DisplayPort / power delivery / G-SYNC\n2x USB 3.2 Gen 1 Type-A\n1x HDMI 2.1 FRL\n\u041a\u0430\u043c\u0435\u0440\u0430: 720P HD\n\u0410\u0443\u0434\u0438\u043e: 1x 3.5mm Combo Audio Jack\n2-speaker system\nAI noise-canceling technology\nDolby Atmos\nHi-Res certification\nSupport Microsoft Cortana near field/Far field\nSecurity BIOS Administrator Password and User Password Protection\n\u0411\u0430\u0442\u0435\u0440\u0438\u0458\u0430:90WHrs, 4S1P, 4-cell Li-ion\n\u041f\u043e\u043b\u043d\u0430\u0447: 240W AC Adapter",
    "features": {
        "screen_size_inches": 15.6,
        "screen_resolution": "1920 x 1080",
        "screen_type": "FHD IPS",
        "screen_refresh_rate_hz": 144,
        "processor_model": "12th Gen Intel Core i7-12700H",
        "processor_cores": 14,
        "processor_threads": null,
        "processor_base_clock_ghz": 2.3,
        "processor_max_clock_ghz": 4.7,
        "gpu_model": "NVIDIA GeForce RTX 4050",
        "gpu_memory_gb": 6,
        "ram_size_gb": 16,
        "ram_type": "DDR4",
        "storage_size_tb": 1,
        "storage_type": "PCIe 4.0 NVMe M.2 SSD",
        "operating_system": null,
        "wifi_standard": "Wi-Fi 6",
        "bluetooth_version": "5.2",
        "usb_type_c_ports": 2,
        "usb_type_a_ports": 2,
        "hdmi_ports": 1,
        "audio_jack_ports": 1,
        "card_reader": null,
        "keyboard_type": "Backlit Chiclet Keyboard 1-Zone RGB",
        "audio_feature_1": "2-speaker system",
        "battery_capacity_wh": 90,
        "battery_cells": 4,
        "security_feature_1": "BIOS Administrator Password and User Password Protection"
    }
}