{
    "url": "https://www.neptun.mk/categories/gaming_laptopi/LENOVO-Legion-Slim-5-16AHP9-16--R7-8845HS-32GB-DDR5-1TB-RTX-4070-8GB",
    "title": "\u041b\u0410\u041f\u0422\u041e\u041f LENOVO LEGION SLIM 5 16AHP9 16\" R7-8845HS/32GB DDR5/1TB/RTX 4070 8GB",
    "warranty_months": 24,
    "regular_price_mkd": 115999,
    "happy_price_mkd": 103999,
    "category": "gaming_laptopi",
    "device_type": "Gaming Laptop",
    "description": "\u041b\u0430\u043f\u0442\u043e\u043f\n\u0414\u0438\u0441\u043f\u043b\u0435\u0439:16\" (40.64cm)\n\u0420\u0435\u0437\u043e\u043b\u0443\u0446\u0438\u0458\u0430:WQXGA (2560x1600), IPS 350nits Anti-glare, 100% sRGB, 165Hz, Dolby\u00ae Vision\u2122, G-SYNC\u00ae, Free-Sync Premium, Low Blue Light\n\u041f\u0440\u043e\u0446\u0435\u0441\u043e\u0440:AMD Ryzen\u2122 7 8845HS (8C / 16T, 3.8 / 5.1GHz, 8MB L2 / 16MB L3)\n\u0413\u0440\u0430\u0444\u0438\u043a\u0430:NVIDIA\u00ae GeForce RTX\u2122 4070 8GB GDDR6, Boost Clock 2175MHz, TGP 140W\n\u0412\u043d\u0430\u0442\u0440\u0435\u0448\u043d\u0430 \u043c\u0435\u043c\u043e\u0440\u0438\u0458\u0430:32GB DDR5-5600\n\u041c\u0435\u043c\u0438\u043e\u0440\u0438\u0458\u0430:1TB SSD M.2 2280 PCIe\u00ae 4.0x4 NVMe\u00ae\n\u0411\u0435\u0437 \u043e\u043f\u0435\u0440\u0430\u0442\u0438\u0432\u0435\u043d \u0441\u0438\u0441\u0442\u0435\u043c\n\u0410\u0443\u0434\u0438\u043e:High Definition (HD) Audio, Realtek\u00ae ALC3287 codec\n\u0417\u0432\u0443\u0447\u043d\u0438\u0446\u0438:Stereo speakers, 2W x2, optimized with Nahimic Audio\n\u041a\u0430\u043c\u0435\u0440\u0430:FHD 1080p with E-shutter\n\u041c\u0438\u043a\u0440\u043e\u0444\u043e\u043d:2x, Array\nEthernet:100/1000M (RJ-45)\nWi-Fi\u00ae 6E, 11ax 2x2 + BT5.3\nWhite Backlit\n\u041f\u043e\u0440\u0442\u0438:\n1x USB-A (USB 10Gbps / USB 3.2 Gen 2), Always On\n1x USB-A (USB 10Gbps / USB 3.2 Gen 2)\n1x USB-C\u00ae (USB 10Gbps / USB 3.2 Gen 2), with PD 140W and DisplayPort\u2122 1.4\n1x USB-C\u00ae (USB 10Gbps / USB 3.2 Gen 2), with DisplayPort\u2122 1.4\n1x HDMI\u00ae 2.1, up to 8K/60Hz\n1x Headphone / microphone combo jack (3.5mm)\n1x Ethernet (RJ-45)\n1x Card reader\n1x Power connector\nPower Adapter:230W Slim Tip (3-pin)\n\u0411\u0430\u0442\u0435\u0440\u0438\u0458\u0430:Integrated 80Wh",
    "features": {
        "screen_size_inches": 16,
        "screen_resolution": "WQXGA (2560x1600)",
        "screen_type": "IPS",
        "screen_refresh_rate_hz": 165,
        "processor_model": "AMD Ryzen\u2122 7 8845HS",
        "processor_cores": 8,
        "processor_threads": 16,
        "processor_base_clock_ghz": 3.8,
        "processor_max_clock_ghz": 5.1,
        "gpu_model": "NVIDIA\u00ae GeForce RTX\u2122 4070",
        "gpu_memory_gb": 8,
        "ram_size_gb": 32,
        "ram_type": "DDR5-5600",
        "storage_size_tb": 1,
        "storage_type": "SSD M.2 2280 PCIe\u00ae 4.0x4 NVMe\u00ae",
        "operating_system": null,
        "wifi_standard": "Wi-Fi\u00ae 6E",
        "bluetooth_version": 5.3,
        "usb_type_c_ports": 2,
        "usb_type_a_ports": 2,
        "hdmi_ports": 1,
        "audio_jack_ports": 1,
        "card_reader": null,
        "keyboard_type": "White Backlit",
        "audio_feature_1": "Stereo speakers, 2W x2, optimized with Nahimic Audio",
        "battery_capacity_wh": 80,
        "battery_cells": null,
        "security_feature_1": null
    }
}