{
    "url": "https://www.neptun.mk/categories/gaming_laptopi/LENOVO-Legion-Slim-5-16IRH8-16--i7-13700H-16GB-DDR5-1TB-RTX-4060-8GB",
    "title": "\u041b\u0410\u041f\u0422\u041e\u041f LENOVO LEGION SLIM 5 16IRH8 16\" I7-13700H/16GB DDR5/1TB/RTX 4060 8GB",
    "warranty_months": 24,
    "regular_price_mkd": 97999,
    "happy_price_mkd": 90999,
    "category": "gaming_laptopi",
    "device_type": "Gaming Laptop",
    "description": "\u041b\u0430\u043f\u0442\u043e\u043f\n\u0414\u0438\u0441\u043f\u043b\u0435\u0439: 16\" (40.64cm)\n\u0420\u0435\u0437\u043e\u043b\u0443\u0446\u0438\u0458\u0430:(2560x1600) WQXGA, IPS, 300nits Anti-glare, 100% sRGB, 165Hz, G-SYNC\u00ae, Low Blue Light\nChipset: Intel\u00ae SoC Platform\n\u041f\u0440\u043e\u0446\u0435\u0441\u043e\u0440:Intel\u00ae Core\u2122 i7-13700H, 14C (6P + 8E) / 20T, P-core 2.4 / 5.0GHz, E-core 1.8 / 3.7GHz, 24MB\n\u0413\u0440\u0430\u0444\u0438\u043a\u0430:NVIDIA\u00ae GeForce RTX\u2122 4060 8GB GDDR6, Boost Clock 2370MHz, TGP 125W\nRAM \u043c\u0435\u043c\u043e\u0440\u0438\u0458\u0430:16GB DDR5-5200\n\u0414\u0438\u0441\u043a (Storage):1TB SSD M.2 2280 PCIe\u00ae 4.0x4 NVMe\u00ae\n\u0411\u0435\u0436 \u043e\u043f\u0435\u0440\u0430\u0442\u0438\u0432\u0435\u043d \u0441\u0438\u0441\u0442\u0435\u043c\n\u0410\u0443\u0434\u0438\u043e: High Definition (HD) Audio, Realtek\u00ae ALC3287 codec\n\u0417\u0432\u0443\u0447\u043d\u0438\u0446\u0438:Stereo speakers, 2W x2, optimized with Nahimic Audio\n\u041a\u0430\u043c\u0435\u0440\u0430:FHD 1080p with E-shutter\n\u041c\u0438\u043a\u0440\u043e\u0444\u043e\u043d:2x, Array\n\u0422\u0430\u0441\u0442\u0430\u0442\u0443\u0440\u0430: White Backlit, English\nWireless:Wi-Fi\u00ae 6E, 11ax 2x2 + BT5.1\n\u041f\u043e\u0440\u0442\u0438:\n1x USB 3.2 Gen 2\n1x USB 3.2 Gen 2 (Always On)\n1x USB-C\u00ae 3.2 Gen 2 (support data transfer and DisplayPort\u2122 1.4)\n1x USB-C\u00ae 3.2 Gen 2 (support data transfer, Power Delivery 140W and DisplayPort\u2122 1.4)\n1x HDMI\u00ae 2.1, up to 8K/30Hz\n1x Card reader\n1x Ethernet 100/1000 (RJ-45)\n1x Headphone / microphone combo jack (3.5mm)\n1x Power connector\n\u0411\u0430\u0442\u0435\u0440\u0438\u0458\u0430:\nIntegrated 80Wh\nPower Adapter: 230W Slim Tip (3-pin)",
    "features": {
        "screen_size_inches": 16,
        "screen_resolution": "2560x1600",
        "screen_type": "WQXGA, IPS",
        "screen_refresh_rate_hz": 165,
        "processor_model": "Intel\u00ae Core\u2122 i7-13700H",
        "processor_cores": 14,
        "processor_threads": 20,
        "processor_base_clock_ghz": 2.4,
        "processor_max_clock_ghz": 5.0,
        "gpu_model": "NVIDIA\u00ae GeForce RTX\u2122 4060",
        "gpu_memory_gb": 8,
        "ram_size_gb": 16,
        "ram_type": "DDR5-5200",
        "storage_size_tb": 1,
        "storage_type": "SSD M.2 2280 PCIe\u00ae 4.0x4 NVMe\u00ae",
        "operating_system": null,
        "wifi_standard": "Wi-Fi\u00ae 6E, 11ax",
        "bluetooth_version": 5.1,
        "usb_type_c_ports": 2,
        "usb_type_a_ports": 2,
        "hdmi_ports": 1,
        "audio_jack_ports": 1,
        "card_reader": "Card reader",
        "keyboard_type": "White Backlit, English",
        "audio_feature_1": "Stereo speakers, 2W x2, optimized with Nahimic Audio",
        "battery_capacity_wh": 80,
        "battery_cells": null,
        "security_feature_1": null
    }
}