{
    "url": "https://www.neptun.mk/categories/gaming_laptopi/ASUS-ROG-Strix-G17-G713RM-KH011-R7-6800H-16GB-1TB-RTX-3060-6GB",
    "title": "\u041b\u0410\u041f\u0422\u041e\u041f ASUS ROG STRIX G17 G713RM-KH011 R7-6800H/16GB/1TB/RTX 3060 6GB",
    "warranty_months": 24,
    "regular_price_mkd": 105999,
    "happy_price_mkd": 81999,
    "category": "gaming_laptopi",
    "device_type": "Gaming Laptop",
    "description": "\u041b\u0410\u041f\u0422\u041e\u041f\n\u0414\u0438\u0441\u043f\u043b\u0435\u0439:17.3\" (43.9cm)\n\u0420\u0435\u0437\u043e\u043b\u0443\u0446\u0438\u0458\u0430:(1920 x 1080) FHD IPS 360Hz\n\u041f\u0440\u043e\u0446\u0435\u0441\u043e\u0440:AMD Rembrandt R7-H (TBD) R7-6800H\n\u0413\u0440\u0430\u0444\u0438\u043a\u0430:NVIDIA GeForce RTX 3060 6GB\n\u0412\u043d\u0430\u0442\u0440\u0435\u0448\u043d\u0430 \u043c\u0435\u043c\u043e\u0440\u0438\u0458\u0430:16GB DDR5\n\u041c\u0435\u043c\u043e\u0440\u0438\u0458\u0430:1TB SSD\n\u0411\u0435\u0437 \u043e\u043f\u0435\u0440\u0430\u0442\u0438\u0432\u0435\u043d \u0441\u0438\u0441\u0442\u0435\u043c\nLAN 10/100/1000/2500 Mbps\nWi-Fi/Bluetooth Wi-Fi 6E(802.11ax)+Bluetooth 5.2 (Dual band) 2*2\n\u041f\u043e\u0440\u0442\u0438:\n1 x RJ45 LAN port\n1 x USB 3.2 Gen 2 Type-C\n1 x USB 3.2 Gen 2 Type-C support DisplayPort / power delivery\n2 x USB 3.2 Gen 1 Type-A//1x 3.5mm Combo Audio Jack\n1 x HDMI 2.0b\n\u041e\u0441\u0432\u0435\u0442\u043b\u0435\u043d\u0430 \u0442\u0430\u0441\u0442\u0430\u0442\u0443\u0440\u0430:4-Zone RGB\n\u0417\u0432\u0443\u0447\u043d\u0438\u0446\u0438:2-speaker system with Smart Amplifier Technology\nAudio Tech AI noise-canceling technology\nDolby Atmos\nHi-Res certification\nSmart Amp Technology\n\u0411\u0430\u0442\u0435\u0440\u0438\u0458\u0430:90WHrs, 4S1P, 4-cell Li-ion",
    "features": {
        "screen_size_inches": 17.3,
        "screen_resolution": "1920 x 1080",
        "screen_type": "IPS",
        "screen_refresh_rate_hz": 360,
        "processor_model": "AMD Rembrandt R7-H (TBD) R7-6800H",
        "processor_cores": null,
        "processor_threads": null,
        "processor_base_clock_ghz": null,
        "processor_max_clock_ghz": null,
        "gpu_model": "NVIDIA GeForce RTX 3060",
        "gpu_memory_gb": 6,
        "ram_size_gb": 16,
        "ram_type": "DDR5",
        "storage_size_tb": 1,
        "storage_type": "SSD",
        "operating_system": null,
        "wifi_standard": "Wi-Fi 6E",
        "bluetooth_version": 5.2,
        "usb_type_c_ports": 2,
        "usb_type_a_ports": 2,
        "hdmi_ports": 1,
        "audio_jack_ports": 1,
        "card_reader": null,
        "keyboard_type": "4-Zone RGB",
        "audio_feature_1": "2-speaker system with Smart Amplifier Technology",
        "battery_capacity_wh": 90,
        "battery_cells": 4,
        "security_feature_1": null
    }
}