{
    "url": "https://www.neptun.mk/categories/gaming_laptopi/HP-Victus-15-fa1026nn-i7-13700H-16GB-512GB-RTX-4050-6GB",
    "title": "\u041b\u0410\u041f\u0422\u041e\u041f HP VICTUS 15-FA1026NN I7-13700H/16GB/512GB/RTX 4050 6GB",
    "warranty": "24",
    "regular_price_mkd": 72999,
    "happy_price_mkd": 68999,
    "category": "gaming_laptopi",
    "device_type": "Gaming Laptop",
    "description": "\u041b\u0430\u043f\u0442\u043e\u043f\n\u0414\u0438\u0441\u043f\u043b\u0435\u0439:15.6\" (39.6cm)\n\u0420\u0435\u0437\u043e\u043b\u0443\u0446\u0438\u0458\u0430:(1920 x 1080) FHD IPS 144Hz, 250 nits, 45% NTSC, 9ms\n\u041f\u0440\u043e\u0446\u0435\u0441\u043e\u0440:Intel\u00ae Core\u2122 i7-13700H (up to 5.0 GHz with Intel\u00ae Turbo Boost Technology, 24 MB L3 cache, 14 cores, 20 threads)\n\u0413\u0440\u0430\u0444\u0438\u043a\u0430:NVIDIA\u00ae GeForce RTX\u2122 4050 6GB GDDR6\n\u0412\u043d\u0430\u0442\u0440\u0435\u0448\u043d\u0430 \u043c\u0435\u043c\u043e\u0440\u0438\u0458\u0430: 16 GB DDR4-3200 MHz (2 x 8 GB)\n\u041c\u0435\u043c\u0438\u0440\u0438\u0458\u0430:512 GB PCIe\u00ae Gen4 NVMe\u2122 M.2 SSD 512 GB PCIe\u00ae Gen4 NVMe\u2122 TLC M.2 SSD\nWi-Fi 6 MT7921 (2x2) + Bluetooth\u00ae 5.3\n\u041a\u0430\u043c\u0435\u0440\u0430:HP True Vision 1080p FHD camera with temporal noise reduction and integrated dual array digital microphones\n\u0410\u0443\u0434\u0438\u043e:Audio by B&O; Dual speakers; HP Audio Boost\nNetwork:10/100/1000 GbE LAN\n\u041f\u043e\u0440\u0442\u0438:\n1 USB Type-A 5Gbps signaling rate\n1 USB Type-A 5Gbps signaling rate (HP Sleep and Charge)\n1 USB Type-C\u00ae 5Gbps signaling rate (DisplayPort\u2122 1.4, HP Sleep and Charge)\n1 HDMI 2.1\n1 RJ-45\n1 AC smart pin\n1 headphone/microphone combo\nPower:200 W Smart AC power adapter\n\u0411\u0430\u0442\u0435\u0440\u0438\u0458\u0430:4-cell, 70 Wh Li-ion polymer",
    "features": {
        "screen_size_inches": 15.6,
        "screen_resolution": "1920 x 1080",
        "screen_type": "FHD IPS",
        "screen_refresh_rate_hz": 144,
        "processor_model": "Intel\u00ae Core\u2122 i7-13700H",
        "processor_cores": 14,
        "processor_threads": 20,
        "processor_base_clock_ghz": null,
        "processor_max_clock_ghz": 5.0,
        "gpu_model": "NVIDIA\u00ae GeForce RTX\u2122 4050",
        "gpu_memory_gb": 6,
        "ram_size_gb": 16,
        "ram_type": "DDR4-3200 MHz",
        "storage_size_tb": 0.512,
        "storage_type": "PCIe\u00ae Gen4 NVMe\u2122 M.2 SSD",
        "operating_system": null,
        "wifi_standard": "Wi-Fi 6",
        "bluetooth_version": "5.3",
        "usb_type_c_ports": 1,
        "usb_type_a_ports": 2,
        "hdmi_ports": 1,
        "audio_jack_ports": 1,
        "card_reader": null,
        "keyboard_type": null,
        "audio_feature_1": "Audio by B&O; Dual speakers; HP Audio Boost",
        "battery_capacity_wh": 70,
        "battery_cells": 4,
        "security_feature_1": null
    }
}