{
    "url": "https://www.neptun.mk/categories/gaming_laptopi/LENOVO-IdeaPad-Gaming-3-15ARH7-R5-6600H-16GB-DDR5-512GB-SSD-RTX-3050-4GB",
    "title": "\u041b\u0410\u041f\u0422\u041e\u041f LENOVO GAMING 3 15ARH7 R5-6600H/16GB DDR5/512GB/RTX 3050 4GB",
    "warranty_months": 24,
    "regular_price_mkd": 45999,
    "happy_price_mkd": 41999,
    "category": "gaming_laptopi",
    "device_type": "Gaming Laptop",
    "description": [
        "\u041b\u0430\u043f\u0442\u043e\u043f\n\u0414\u0438\u0441\u043f\u043b\u0435\u0458:15.6\" (39.5cm)\n\u0420\u0435\u0437\u043e\u043b\u0443\u0446\u0438\u0458\u0430:FHD (1920x1080) IPS 250nits Anti-glare, 45% NTSC, 120Hz, FreeSync\u2122\n\u041f\u0440\u043e\u0446\u0435\u0441\u043e\u0440:AMD Ryzen\u2122 5 6600H (6C / 12T, 3.3 / 4.5GHz, 3MB L2 / 16MB L3)\n\u0413\u0440\u0430\u0444\u0438\u043a\u0430:NVIDIA\u00ae GeForce RTX\u2122 3050 4GB GDDR6, Boost Clock 1740MHz, TGP 85W\n\u0412\u043d\u0430\u0442\u0440\u0435\u0448\u043d\u0430 \u043c\u0435\u043c\u043e\u0440\u0438\u0458\u0430:16GB DDR5-4800\n\u041c\u0435\u043c\u043e\u0440\u0438\u0458\u0430:512GB SSD M.2 2242 PCIe\u00ae 4.0x4 NVMe\u00ae\n\u0411\u0435\u0437 \u043e\u043f\u0435\u0440\u0430\u0442\u0438\u0432\u0435\u043d \u0441\u0438\u0441\u0442\u0435\u043c\n\u0410\u0443\u0434\u0438\u043e:High Definition (HD) Audio, Realtek\u00ae ALC3287 codec\n\u0417\u0432\u0443\u0447\u043d\u0438\u043a:Stereo speakers, 2W x2, Nahimic Audio\n\u041a\u0430\u043c\u0435\u0440\u0430:HD 720p with Privacy Shutter\n\u041c\u0438\u043a\u0440\u043e\u0444\u043e\u043d:2x, Array\nEthernet:100/1000M (RJ-45)\nWi-Fi\u00ae 6, 11ax 2x2 + BT5.1\nWhite Backlit\n\u041f\u043e\u0440\u0442\u0438:\n2x USB 3.2 Gen 1\n1x USB-C\u00ae 3.2 Gen 2 (support data transfer, Power Delivery 3.0 and DisplayPort\u2122 1.4)\n1x HDMI\u00ae 2.0\n1x Headphone / microphone combo jack (3.5mm)\n1x Ethernet (RJ-45)\n1x Power connector\nPower Adapter:170W Slim Tip (3-pin)\n\u0411\u0430\u0442\u0435\u0440\u0438\u0458\u0430:Integrated 45Wh"
    ],
    "features": {
        "screen_size_inches": 15.6,
        "screen_resolution": "FHD (1920x1080)",
        "screen_type": "IPS",
        "screen_refresh_rate_hz": 120,
        "processor_model": "AMD Ryzen\u2122 5 6600H",
        "processor_cores": 6,
        "processor_threads": 12,
        "processor_base_clock_ghz": 3.3,
        "processor_max_clock_ghz": 4.5,
        "gpu_model": "NVIDIA\u00ae GeForce RTX\u2122 3050",
        "gpu_memory_gb": 4,
        "ram_size_gb": 16,
        "ram_type": "DDR5",
        "storage_size_tb": 0.512,
        "storage_type": "SSD",
        "operating_system": null,
        "wifi_standard": "Wi-Fi\u00ae 6, 11ax",
        "bluetooth_version": 5.1,
        "usb_type_c_ports": 1,
        "usb_type_a_ports": 2,
        "hdmi_ports": 1,
        "audio_jack_ports": 1,
        "card_reader": null,
        "keyboard_type": "White Backlit",
        "audio_feature_1": "Stereo speakers, 2W x2, Nahimic Audio",
        "battery_capacity_wh": 45,
        "battery_cells": null,
        "security_feature_1": null
    }
}