{
    "url": "https://www.neptun.mk/categories/gaming_laptopi/ACER-Predator-Helios-300-PH315-55-95CR-i9-12900H-16GB-DDR5-1TB-RTX-3070-8GB",
    "title": "ACER Predator Helios 300 PH315-55-95CR",
    "warranty_months": 24,
    "regular_price_mkd": 92999,
    "happy_price_mkd": 76999,
    "category": "gaming_laptopi",
    "device_type": "Gaming Laptop",
    "description": "\u041b\u0430\u043f\u0442\u043e\u043f\n\u0414\u0438\u0441\u043f\u043bej:Acer ComfyView\u00ae 15.6\" (39.6 cm)\n\u0420\u0435\u0437\u043e\u043b\u0443\u0446\u0438\u0458\u0430:(1920 x 1080) FHD, IPS, 165Hz, NVIDIA G-SYNC\u00ae\n\u041f\u0440\u043e\u0446\u0435\u0441\u043e\u0440: 12th Gen Intel\u00ae Core\u2122 i9-12900H, 14 Core\u2122, 24MB\n\u0413\u0440\u0430\u0444\u0438\u043a\u0430:NVIDIA\u00ae GeForce\u00ae RTX\u2122 3070 8 GB GDDR6 VRAM\nRAM \u043c\u0435\u043c\u043e\u0440\u0438\u0458\u0430: 16GB DDR5 (1 x 16)\n\u0414\u0438\u0441\u043a (Storage):1TB SSD PCIe\n\u0411\u0435\u0436\u0438\u0447\u0435\u043d \u043e\u043f\u0441\u0435\u0433:\n\u041f\u043e\u0440\u0442\u0438:\n1x (HDMI 2.1 with HDCP support)\n2x DisplayPort\u00ae (1xMiniDispalyPort)\n1x via USB Type-C) Thunderbolt Thunderbolt\u2122 4 (via USB Type-C) USB 3.2\n4x (1x USB Type -C Gen2)\n1x Gen2 (mit Power-Off USB Charging)\n2x Gen1\nEthernet (RJ-45)\n1x headphone/speaker jack\nLAN: Killer\u00ae Ethernet E2600\nIntel\u00ae Killer\u2122 Wireless Wi-Fi 6E\nBluetooth\u00ae 5.2\nKeyboard Backlight\n\u0410\u0443\u0434\u0438\u043e: Acer TrueHarmony\n\u0412\u0433\u0440\u0430\u0434\u0435\u043d\u0438 \u0437\u0432\u0443\u0447\u043d\u0438\u0446\u0438\n\u0412\u0433\u0440\u0430\u0434\u0435\u043d \u043c\u0438\u043a\u0440\u043e\u0444\u043e\u043d\n\u0411\u0430\u0442\u0435\u0440\u0438\u0458\u0430:90Wh Li-ion 4-cell battery\nPower:280 W\n\u0422\u0435\u0436\u0438\u043d\u0430: 2.6kg",
    "features": {
        "screen_size_inches": 15.6,
        "screen_resolution": "1920 x 1080",
        "screen_type": "IPS",
        "screen_refresh_rate_hz": 165,
        "processor_model": "12th Gen Intel\u00ae Core\u2122 i9-12900H",
        "processor_cores": 14,
        "processor_threads": 24,
        "processor_base_clock_ghz": null,
        "processor_max_clock_ghz": null,
        "gpu_model": "NVIDIA\u00ae GeForce\u00ae RTX\u2122 3070",
        "gpu_memory_gb": 8,
        "ram_size_gb": 16,
        "ram_type": "DDR5",
        "storage_size_tb": 1,
        "storage_type": "SSD PCIe",
        "operating_system": null,
        "wifi_standard": "Wi-Fi 6E",
        "bluetooth_version": 5.2,
        "usb_type_c_ports": 2,
        "usb_type_a_ports": 4,
        "hdmi_ports": 1,
        "audio_jack_ports": 1,
        "card_reader": null,
        "keyboard_type": null,
        "audio_feature_1": "Acer TrueHarmony",
        "battery_capacity_wh": 90,
        "battery_cells": 4,
        "security_feature_1": null
    }
}