{
    "url": "https://www.neptun.mk/categories/gaming_laptopi/HP-Victus-16-r0078nia-16-1--i5-13500H-16GB-DDR5-512GB-RTX-4050-6GB",
    "title": "\u041b\u0410\u041f\u0422\u041e\u041f HP VICTUS 16-R0078NIA 16.1\" I5-13500H/16GB DDR5/512GB/RTX 4050 6GB",
    "warranty_months": 12,
    "regular_price_mkd": 72999,
    "happy_price_mkd": 63999,
    "category": "gaming_laptopi",
    "device_type": "Gaming Laptop",
    "description": "\u041b\u0430\u043f\u0442\u043e\u043f\n\u0414\u0438\u0441\u043f\u043b\u0435\u0439:16.1\" (40.9cm)\n\u0420\u0435\u0437\u043e\u043b\u0443\u0446\u0438\u0458\u0430:(1920 x 1080) FHD IPS 144 Hz, micro-edge, anti-glare, 250 nits, 45% NTSC\n\u041f\u0440\u043e\u0446\u0435\u0441\u043e\u0440:Intel\u00ae Core\u2122 i5-13500H (up to 4.7 GHz with Intel\u00ae Turbo Boost Technology, 18 MB L3 cache, 12 cores, 16 threads)\n\u0413\u0440\u0430\u0444\u0438\u043a\u0430:NVIDIA\u00ae GeForce RTX\u2122 4050 6 GB GDDR6\n\u0412\u043d\u0430\u0442\u0440\u0435\u0448\u043d\u0430 \u043c\u0435\u043c\u043e\u0440\u0438\u0458\u0430:16 GB DDR5-5200 MHz RAM (2 x 8 GB)\n\u041c\u0435\u043c\u043e\u0440\u0438\u0458\u0430:512 GB PCIe\u00ae Gen4 NVMe\u2122 TLC M.2 SSD\nWi-Fi 6 MT7921 (2x2) + Bluetooth\u00ae 5.3\n\u041a\u0430\u043c\u0435\u0440\u0430:HP True Vision 1080p FHD camera with temporal noise reduction and integrated dual array digital microphones\n\u0410\u0443\u0434\u0438\u043e:Audio by B&O; Dual speakers; HP Audio Boost\nNetwork:10/100/1000 GbE LAN\n\u0410\u0443\u0434\u0438\u043e: B&O; Dual speakers; HP Audio Boost\n\u041f\u043e\u0440\u0442\u0438:\n1 USB Type-A 5Gbps signaling rate (HP Sleep and Charge)\n1 USB Type-C\u00ae 5Gbps signaling rate (USB Power Delivery, DisplayPort\u2122 1.4, HP Sleep and Charge)\n2 USB Type-A 5Gbps signaling rate\n1 HDMI 2.1\n1 RJ-45\n1 AC smart pin\n1 headphone/microphone combo[\nPower:230 W Smart AC power adapter\n\u0411\u0430\u0442\u0435\u0440\u0438\u0458\u0430:4-cell, 70 Wh Li-ion polymer",
    "features": {
        "screen_size_inches": 16.1,
        "screen_resolution": "1920 x 1080",
        "screen_type": "FHD IPS",
        "screen_refresh_rate_hz": 144,
        "processor_model": "Intel\u00ae Core\u2122 i5-13500H",
        "processor_cores": 12,
        "processor_threads": 16,
        "processor_base_clock_ghz": null,
        "processor_max_clock_ghz": 4.7,
        "gpu_model": "NVIDIA\u00ae GeForce RTX\u2122 4050",
        "gpu_memory_gb": 6,
        "ram_size_gb": 16,
        "ram_type": "DDR5-5200 MHz",
        "storage_size_tb": 0.512,
        "storage_type": "PCIe\u00ae Gen4 NVMe\u2122 TLC M.2 SSD",
        "operating_system": null,
        "wifi_standard": "Wi-Fi 6 MT7921 (2x2)",
        "bluetooth_version": "5.3",
        "usb_type_c_ports": 1,
        "usb_type_a_ports": 3,
        "hdmi_ports": 1,
        "audio_jack_ports": 1,
        "card_reader": null,
        "keyboard_type": null,
        "audio_feature_1": "Audio by B&O; Dual speakers; HP Audio Boost",
        "battery_capacity_wh": 70,
        "battery_cells": 4,
        "security_feature_1": null
    }
}