{
    "url": "https://www.neptun.mk/categories/gaming_laptopi/LENOVO-Legion-Pro-7-16IRX9H-16--i9-14900HX-32GB-DDR5-1TB-RTX-4080-12GB",
    "title": "LENOVO LEGION PRO 7 16IRX9H 16\" I9-14900HX/32GB DDR5/1TB/RTX 4080 12GB",
    "warranty_months": 24,
    "regular_price_mkd": 187999,
    "happy_price_mkd": 175999,
    "category": "gaming_laptopi",
    "device_type": "Gaming Laptop",
    "description": "\u041b\u0430\u043f\u0442\u043e\u043f\n\u0414\u0438\u0441\u043f\u043b\u0435\u0439:16\" (40.64cm)\n\u0420\u0435\u0437\u043e\u043b\u0443\u0446\u0438\u0458\u0430:WQXGA (2560x1600), IPS 500nits Anti-glare, 100% DCI-P3, 240Hz, DisplayHDR\u2122 400, Dolby\u00ae Vision\u00ae, G-SYNC\u00ae, Low Blue Light, High Gaming Performance\n\u041f\u0440\u043e\u0446\u0435\u0441\u043e\u0440:Intel\u00ae Core\u2122 i9-14900HX, 24C (8P + 16E) / 32T, P-core 2.2 / 5.8GHz, E-core 1.6 / 4.1GHz, 36MB\n\u0413\u0440\u0430\u0444\u0438\u043a\u0430:NVIDIA\u00ae GeForce RTX\u2122 4080 12GB GDDR6, Boost Clock 2280MHz, TGP 175W\n\u0412\u043d\u0430\u0442\u0440\u0435\u0448\u043d\u0430 \u043c\u0435\u043c\u043e\u0440\u0438\u0458\u0430:32GB DDR5-5600\n\u041c\u0435\u043c\u043e\u0432\u0438\u0458\u0430:1TB SSD M.2 2280 PCIe\u00ae 4.0x4 NVMe\u00ae\n\u0411\u0435\u0437 \u043e\u043f\u0435\u0440\u0430\u0442\u0438\u0432\u0435\u043d \u0441\u0438\u0441\u0442\u0435\u043c\n\u0410\u0443\u0434\u0438\u043e:    High Definition (HD) Audio, Realtek\u00ae ALC3306 codec\n\u0417\u0432\u0443\u0447\u043d\u0438\u0446\u0438:Stereo speakers, 2W x2, audio by HARMAN, optimized with Nahimic Audio, Smart Amplifier (AMP)\n\u041a\u0430\u043c\u0435\u0440\u0430:FHD 1080p with E-shutter\n\u041c\u0438\u043a\u0440\u043e\u0444\u043e\u043d:2x, Array\nEthernet:100/1000M (RJ-45)\nIntel\u00ae Killer Wi-Fi\u00ae 6E AX1675i, 11ax 2x2 + BT5.3\nRGB Backlit (with Lighting Lens)\n\u041f\u043e\u0440\u0442\u0438:\n1x USB-A (USB 5Gbps / USB 3.2 Gen 1), Always On\n3x USB-A (USB 5Gbps / USB 3.2 Gen 1)\n1x USB-C\u00ae (USB 10Gbps / USB 3.2 Gen 2), with Lenovo\u00ae PD 140W and DisplayPort\u2122 1.4\n1x USB-C\u00ae (Thunderbolt\u2122 4 / USB4\u00ae 40Gbps), with DisplayPort\u2122 1.4\n1x HDMI\u00ae 2.1, up to 8K/60Hz\n1x Headphone / microphone combo jack (3.5mm)\n1x Ethernet (RJ-45)\n1x Power connector\nPower Adapter:330W Slim Tip Tiny GaN (3-pin)\n\u0411\u0430\u0442\u0435\u0440\u0438\u0458\u0430:Integrated 99.9Wh",
    "features": {
        "screen_size_inches": 16,
        "screen_resolution": "WQXGA (2560x1600)",
        "screen_type": "IPS",
        "screen_refresh_rate_hz": 240,
        "processor_model": "Intel\u00ae Core\u2122 i9-14900HX",
        "processor_cores": 24,
        "processor_threads": 32,
        "processor_base_clock_ghz": 2.2,
        "processor_max_clock_ghz": 5.8,
        "gpu_model": "NVIDIA\u00ae GeForce RTX\u2122 4080",
        "gpu_memory_gb": 12,
        "ram_size_gb": 32,
        "ram_type": "DDR5",
        "storage_size_tb": 1,
        "storage_type": "SSD M.2 2280 PCIe\u00ae 4.0x4 NVMe\u00ae",
        "operating_system": null,
        "wifi_standard": "Wi-Fi 6E AX1675i",
        "bluetooth_version": "5.3",
        "usb_type_c_ports": 2,
        "usb_type_a_ports": 4,
        "hdmi_ports": 1,
        "audio_jack_ports": 1,
        "card_reader": null,
        "keyboard_type": "RGB Backlit",
        "audio_feature_1": "Stereo speakers, 2W x2, audio by HARMAN, optimized with Nahimic Audio, Smart Amplifier (AMP)",
        "battery_capacity_wh": 99.9,
        "battery_cells": null,
        "security_feature_1": null
    }
}