{
    "url": "https://www.neptun.mk/categories/gaming_laptopi/ASUS-ROG-Zephyrus-G14-GA403UU-QS055W-14--OLED-R9-8945HS-16GB-DDR5X-1TB-RTX-4050-6GB-WIN11",
    "title": "\u041b\u0410\u041f\u0422\u041e\u041f ASUS ROG ZEPHYRUS G14 GA403UU-QS055W 14\" OLED R9-8945HS/16GB DDR5X/1TB/RTX 4050 6GB/WIN11",
    "warranty_months": 24,
    "regular_price_mkd": 112999,
    "happy_price_mkd": 104999,
    "category": "gaming_laptopi",
    "device_type": "Gaming Laptop",
    "description": "\u041b\u0430\u043f\u0442\u043e\u043f\n\u0414\u0438\u0441\u043f\u043b\u0435\u0439: 14\" (39.6cm)\n\u0420\u0435\u0437\u043e\u043b\u0443\u0446\u0438\u0458\u0430:(2880 x 1800) 3\u041a, OLED, 120Hz, 0.2ms, 500 nits, 16:10\n\u041f\u0440\u043e\u0446\u0435\u0441\u043e\u0440:AMD Ryzen\u00ae 9 8945HS, 4GHz (24MB Cache, up to 5.2 GHz, 8 cores, 16 Threads)\n\u0413\u0440\u0430\u0444\u0438\u043a\u0430:NVIDIA GeForce RTX 4050 6GB GDDR6\nRAM \u043c\u0435\u043c\u043e\u0440\u0438\u0458\u0430:16GB DDR5X\n\u0414\u0438\u0441\u043a (Storage):1TB M.2 2280 PCIe Gen4 SSD\n\u041e\u043f\u0435\u0440\u0430\u0442\u0438\u0432\u0435\u043d \u0441\u0438\u0441\u0442\u0435\u043c:Windows 11 Home\nWi-Fi 6E(802.11ax) (Triple band) 2*2 + Bluetooth 5.3\n\u041f\u043e\u0440\u0442\u0438:\n1x Type C USB 4 support DisplayPort    / power delivery\n1x USB 3.2 Gen 2 Type-C support DisplayPor\n2x USB 3.2 Gen 2 Type-A\n1x card reader (microSD) (UHS-II)\n1x HDMI 2.1 FRL\n1x 3.5mm Combo Audio Jack\n\u0412\u0433\u0440\u0430\u0434\u0435\u043d\u0438 3 \u043c\u0438\u043a\u0440\u043e\u0444\u043e\u043d\u0438\nBacklit Chiclet Keyboard 1-Zone RGB\n4x \u0437\u0432\u0443\u0447\u043d\u0438\u0446\u0438 (4-speaker (dual force woofer) system with Smart Amplifier Technology)\n\u0410\u0443\u0434\u0438\u043e:Tech AI noise-canceling - Dolby Atmos\nHi-Res certification\nSmart Amp Technology\nSecurity BIOS Administrator Password and User Password Protection\n\u0411\u0430\u0442\u0435\u0440\u0438\u0458\u0430:73WHrs, 4S1P, 4-cell Li-ion",
    "features": {
        "screen_size_inches": 14,
        "screen_resolution": "2880 x 1800",
        "screen_type": "OLED",
        "screen_refresh_rate_hz": 120,
        "processor_model": "AMD Ryzen\u00ae 9 8945HS",
        "processor_cores": 8,
        "processor_threads": 16,
        "processor_base_clock_ghz": 4,
        "processor_max_clock_ghz": 5.2,
        "gpu_model": "NVIDIA GeForce RTX 4050",
        "gpu_memory_gb": 6,
        "ram_size_gb": 16,
        "ram_type": "DDR5X",
        "storage_size_tb": 1,
        "storage_type": "M.2 2280 PCIe Gen4 SSD",
        "operating_system": "Windows 11 Home",
        "wifi_standard": "Wi-Fi 6E",
        "bluetooth_version": 5.3,
        "usb_type_c_ports": 2,
        "usb_type_a_ports": 2,
        "hdmi_ports": 1,
        "audio_jack_ports": 1,
        "card_reader": "microSD (UHS-II)",
        "keyboard_type": "Backlit Chiclet Keyboard 1-Zone RGB",
        "audio_feature_1": "4-speaker (dual force woofer) system with Smart Amplifier Technology",
        "battery_capacity_wh": 73,
        "battery_cells": 4,
        "security_feature_1": "BIOS Administrator Password and User Password Protection"
    }
}