{
    "url": "https://www.neptun.mk/categories/gaming_laptopi/DELL-G15-5530-i7-13650HX-16GB-1TB-RTX-4060-8GB",
    "title": "\u041b\u0410\u041f\u0422\u041e\u041f DELL G15 5530 I7-13650HX/16GB/1TB/RTX 4060",
    "warranty_months": 36,
    "regular_price_mkd": 99999,
    "happy_price_mkd": 93999,
    "category": "gaming_laptopi",
    "device_type": "Gaming Laptop",
    "description": "\u041b\u0430\u043f\u0442\u043e\u043f\n\u0414\u0438\u0441\u043f\u043b\u0435\u0458:15.6\" (39.6cm)\n\u0420\u0435\u0437\u043e\u043b\u0443\u0446\u0438\u0458\u0430: (1920 x 1080) FHD 120Hz, WVA, Anti-Glare, 250 nit, Narrow Border, LED-Backlit\n\u041f\u0440\u043e\u0446\u0435\u0441\u043e\u0440:13th Gen Intel\u00ae Core\u2122 i7-13650HX (24MB Cache, 14 Cores)\n\u0413\u0440\u0430\u0444\u0438\u043a\u0430:NVIDIA GeForce RTX 4060 8GB GDDR6\nRAM \u041c\u0435\u043c\u043e\u0440\u0438\u0458\u0430: 16 GB 4800 MHz (1 x 8 GB)\n\u0414\u0438\u0441\u043a (Storage): 1TB SSD\nWi-Fi 5 (Wi-Fi 802.11ac)+ Bluetooth 5.0\n\u041a\u0430\u043c\u0435\u0440\u0430:720p at 30 fps HD camera Single integrated microphone\n\u041f\u043e\u0440\u0442\u0438:\nUSB 3.2 Gen 1 Type-A\nUSB 3.2 Gen 1 Type-A\nUSB-C 3.2 Gen 2 with Display Port Alt-Mode\n1 headset (headphone and microphone combo) port\n1 RJ45 Ethernet port (flip-down)\n\u0411\u0430\u0442\u0435\u0440\u0438\u0458\u0430: 4 Cell, 54 Wh, integrated\n\u041f\u043e\u0437\u0430\u0434\u0438\u043d\u0441\u043a\u043e \u043e\u0441\u0432\u0435\u0442\u043b\u0443\u0432\u0430\u045a\u0435 \u043d\u0430 \u0442\u0430\u0441\u0442\u0430\u0442\u0443\u0440\u0430\u0442\u0430 (backlit keyboard)\nCarbon Black",
    "features": {
        "screen_size_inches": 15.6,
        "screen_resolution": "1920 x 1080",
        "screen_type": null,
        "screen_refresh_rate_hz": 120,
        "processor_model": "13th Gen Intel\u00ae Core\u2122 i7-13650HX",
        "processor_cores": 14,
        "processor_threads": null,
        "processor_base_clock_ghz": null,
        "processor_max_clock_ghz": null,
        "gpu_model": "NVIDIA GeForce RTX 4060",
        "gpu_memory_gb": 8,
        "ram_size_gb": 16,
        "ram_type": "4800 MHz",
        "storage_size_tb": 1,
        "storage_type": "SSD",
        "operating_system": null,
        "wifi_standard": "Wi-Fi 5 (Wi-Fi 802.11ac)",
        "bluetooth_version": 5.0,
        "usb_type_c_ports": 1,
        "usb_type_a_ports": 2,
        "hdmi_ports": null,
        "audio_jack_ports": 1,
        "card_reader": null,
        "keyboard_type": "backlit keyboard",
        "audio_feature_1": null,
        "battery_capacity_wh": 54,
        "battery_cells": 4,
        "security_feature_1": null
    }
}