{
    "url": "https://www.neptun.mk/categories/gaming_laptopi/ASUS-ROG-Strix-G16-G614JVR-N3086-16--i9-14900HX-16GB-DDR5-1TB-RTX-4060-8GB",
    "title": "ASUS ROG STRIX G16 G614JVR-N3086 16\" I9-14900HX/16GB DDR5/1TB/RTX 4060 8GB",
    "warranty_months": 24,
    "regular_price_mkd": 99999,
    "happy_price_mkd": 92999,
    "category": "gaming_laptopi",
    "device_type": "Gaming Laptop",
    "description": "\u041b\u0430\u043f\u0442\u043e\u043f\n\u0414\u0438\u0441\u043f\u043b\u0435\u0439:16\" (40.6cm)\n\u0420\u0435\u0437\u043e\u043b\u0443\u0446\u0438\u0458\u0430:(1920 x 1200) WUXGA, IPS, 165Hz\n\u041f\u0440\u043e\u0446\u0435\u0441\u043e\u0440:Intel Core i9-14900HX (36M Cache, up to 5.8 GHz, 24 cores)\n\u0413\u0440\u0430\u0444\u0438\u043a\u0430:NVIDIA GeForce RTX 4060 8GB GDDR6\nNVIDIA G-Sync\nRAM \u043c\u0435\u043c\u043e\u0440\u0438\u0458\u0430:16GB DDR5\n\u0414\u0438\u0441\u043a (Storage):1TB PCIe 4.0 NVMe M.2 SSD\n\u0411\u0435\u0437 \u043e\u043f\u0435\u0440\u0430\u0442\u0438\u0432\u0435\u043d \u0441\u0438\u0441\u0442\u0435\u043c\nLAN 10/100/1000 Mbps\nWi-Fi 6E(802.11ax) (Triple band) 2*2 + Bluetooth 5.3\n\u041f\u043e\u0440\u0442\u0438:\n1x RJ45 LAN port\n1x Thunderbolt    4 support DisplayPort\n1x USB 3.2 Gen 2 Type-C support DisplayPort    / power delivery / G-SYNC\n2x USB 3.2 Gen 2 Type-A\n1x HDMI 2.1 FRL\n1x 3.5mm Combo Audio Jack\n720P HD camera\n\u0412\u0433\u0440\u0430\u0434\u0435\u043d \u043c\u0438\u043a\u0440\u043e\u0444\u043e\u043d\nBacklit Chiclet Keyboard 4-Zone RGB\n\u0417\u0432\u0443\u0447\u043d\u0438\u0446\u0438:\u0441\u0438\u0441\u0442\u0435\u043c \u0441\u043e 2 \u0437\u0432\u0443\u0447\u043d\u0438\u0446\u0438 \u0441\u043e Smart Amplifier Technology\n\u0410\u0443\u0434\u0438\u043e:\nTech AI noise-canceling - Dolby Atmos,Hi-Res certification\nAI noise-canceling technology\nDolby Atmos\nHi-Res certification\nSmart Amp Technology\nSecurity BIOS Administrator Password and User Password Protection\n\u0411\u0430\u0442\u0435\u0440\u0438\u0458\u0430:90WHrs, 4S1P, 4-cell Li-ion",
    "features": {
        "screen_size_inches": 16,
        "screen_resolution": "1920 x 1200",
        "screen_type": "IPS",
        "screen_refresh_rate_hz": 165,
        "processor_model": "Intel Core i9-14900HX",
        "processor_cores": 24,
        "processor_threads": null,
        "processor_base_clock_ghz": null,
        "processor_max_clock_ghz": 5.8,
        "gpu_model": "NVIDIA GeForce RTX 4060",
        "gpu_memory_gb": 8,
        "ram_size_gb": 16,
        "ram_type": "DDR5",
        "storage_size_tb": 1,
        "storage_type": "PCIe 4.0 NVMe M.2 SSD",
        "operating_system": null,
        "wifi_standard": "Wi-Fi 6E",
        "bluetooth_version": 5.3,
        "usb_type_c_ports": 2,
        "usb_type_a_ports": 2,
        "hdmi_ports": 1,
        "audio_jack_ports": 1,
        "card_reader": null,
        "keyboard_type": "Backlit Chiclet Keyboard 4-Zone RGB",
        "audio_feature_1": "\u0441\u0438\u0441\u0442\u0435\u043c \u0441\u043e 2 \u0437\u0432\u0443\u0447\u043d\u0438\u0446\u0438 \u0441\u043e Smart Amplifier Technology",
        "battery_capacity_wh": 90,
        "battery_cells": 4,
        "security_feature_1": "BIOS Administrator Password and User Password Protection"
    }
}