{
    "url": "https://www.neptun.mk/categories/gaming_laptopi/GNB-ASUS-TUF-Gaming-F15-FX507VV4-LP061-i7-13700H-16GB-1TB-RTX-4060-8GB",
    "title": "\u041bA\u041f\u0422\u041e\u041f ASUS TUF GAMING F15 FX507VV4-LP061 I7-13700H/16GB/1TB/RTX 4060 8GB",
    "warranty_months": 24,
    "regular_price_mkd": 87999,
    "happy_price_mkd": 80999,
    "category": "gaming_laptopi",
    "device_type": "Gaming Laptop",
    "description": "\u041b\u0430\u043f\u0442\u043e\u043f\n\u0414\u0438\u0441\u043f\u043b\u0435\u0439:15.6\" (39.6cm)\n\u0420\u0435\u0437\u043e\u043b\u0443\u0446\u0438\u0458\u0430:(1920 x 1080) FHD, IPS, 16:9, 144Hz\n\u041f\u0440\u043e\u0446\u0435\u0441\u043e\u0440:Intel Core i7-13700H Processor 2.4 GHz (24M Cache, up to 5 GHz, 14 cores: 6 P-cores and 8)\n\u0413\u0440\u0430\u0444\u0438\u043a\u0430: NVIDIA GeForce RTX 4060 8GB GDDR6\nRAM \u043c\u0435\u043c\u043e\u0440\u0438\u0458\u0430:16GB DDR4 3200Mhz\n\u0414\u0438\u0441\u043a (Storage):1TB PCIe 4.0 NVMe M.2 SSD\n\u0411\u0435\u0437 \u043e\u043f\u0435\u0440\u0430\u0442\u0438\u0432\u0435\u043d \u0441\u0438\u0441\u0442\u0435\u043c\nLAN 10/100/1000 Mbps\nWi-Fi 6(802.11ax) (Dual band) 2*2 + Bluetooth 5.2 (*Bluetooth version may change with OS version different.)\n\u041f\u043e\u0440\u0442\u0438:\n1x RJ45 LAN port\n1x Thunderbolt 4 support DisplayPort\n1x USB 3.2 Gen 2 Type-C support DisplayPort / power delivery / G-SYNC\n2x USB 3.2 Gen 1 Type-A\n1x HDMI 2.1 FRL\n1x 3.5mm Combo Audio Jack\n\u041a\u0430\u043c\u0435\u0440\u0430: 720P HD camera\n\u0412\u0433\u0440\u0430\u0434\u0435\u043d \u043c\u0438\u043a\u0440\u043e\u043a\u0444\u043e\u043d\n\u041e\u0441\u0432\u0435\u0442\u043b\u0435\u043d\u0430 \u0442\u0430\u0441\u0442\u0430\u0442\u0443\u0440\u0430 RGB\n2 \u0437\u0432\u0443\u0447\u043d\u0438\u0446\u0438\n\u0410\u0443\u0434\u0438\u043e:Tech AI noise-canceling\nSecurity BIOS Administrator Password and User Password Protection\n\u0411\u0430\u0442\u0435\u0440\u0438\u0458\u0430:90WHrs, 4S1P, 4-cell Li-ion\n\u041f\u043e\u043b\u043d\u0430\u0447: 240W AC Adapter, Output: 20V DC, 12A, 240W, Input: 100~240C AC 50/60Hz universal",
    "features": {
        "screen_size_inches": 15.6,
        "screen_resolution": "1920 x 1080",
        "screen_type": "FHD",
        "screen_refresh_rate_hz": 144,
        "processor_model": "Intel Core i7-13700H Processor",
        "processor_cores": 14,
        "processor_threads": null,
        "processor_base_clock_ghz": 2.4,
        "processor_max_clock_ghz": 5,
        "gpu_model": "NVIDIA GeForce RTX 4060",
        "gpu_memory_gb": 8,
        "ram_size_gb": 16,
        "ram_type": "DDR4",
        "storage_size_tb": 1,
        "storage_type": "PCIe 4.0 NVMe M.2 SSD",
        "operating_system": null,
        "wifi_standard": "Wi-Fi 6",
        "bluetooth_version": 5.2,
        "usb_type_c_ports": 2,
        "usb_type_a_ports": 2,
        "hdmi_ports": 1,
        "audio_jack_ports": 1,
        "card_reader": null,
        "keyboard_type": "\u041e\u0441\u0432\u0435\u0442\u043b\u0435\u043d\u0430 \u0442\u0430\u0441\u0442\u0430\u0442\u0443\u0440\u0430 RGB",
        "audio_feature_1": "Tech AI noise-canceling",
        "battery_capacity_wh": 90,
        "battery_cells": 4,
        "security_feature_1": "BIOS Administrator Password and User Password Protection"
    }
}