{
    "url": "https://www.neptun.mk/categories/gaming_laptopi/LENOVO-LOQ-15IRH8-i5-13420H-16GB-DDR5-512GB-RTX-4050-6GB",
    "title": "\u041b\u0410\u041f\u0422\u041e\u041f LENOVO LOQ 15IRH8 I5-13420H/16GB DDR5/512GB/RTX 4050 6GB",
    "warranty_months": 24,
    "regular_price_mkd": 65999,
    "happy_price_mkd": 58999,
    "category": "gaming_laptopi",
    "device_type": "Gaming Laptop",
    "description": "\u041b\u0430\u043f\u0442\u043e\u043f\n\u0414\u0438\u0441\u043f\u043b\u0435\u0458: 15.6\" (39.5cm)\n\u0420\u0435\u0437\u043e\u043b\u0443\u0446\u0438\u0458\u0430:(1920x1080) FHD, IPS, 350nits, Anti-glare, 45% NTSC, 144Hz, G-SYNC\u00ae\nChipset: Intel\u00ae SoC Platform\n\u041f\u0440\u043e\u0446\u0435\u0441\u043e\u0440:Intel\u00ae Core\u2122 i5-13420H, 8C (4P + 4E) / 12T, P-core 2.1 / 4.6GHz, E-core 1.5 / 3.4GHz, 12MB\n\u0413\u0440\u0430\u0444\u0438\u0447\u043a\u0430:NVIDIA\u00ae GeForce RTX\u2122 4050 6GB GDDR6, Boost Clock 2370MHz, TGP 95W\nRAM \u043c\u0435\u043c\u043e\u0440\u0438\u0458\u0430:16GB DDR5-5200\n\u0414\u0438\u0441\u043a (Storage):512GB SSD M.2 2242 PCIe\u00ae 4.0x4 NVMe\u00ae\n\u0411\u0435\u0437 \u043e\u043f\u0435\u0440\u0430\u0442\u0438\u0432\u0435\u043d \u0441\u0438\u0441\u0442\u0435\u043c\n\u0410\u0443\u0434\u0438\u043e: High Definition (HD) Audio, Realtek\u00ae ALC3287 codec\n\u0417\u0432\u0443\u0447\u043d\u0438\u043a:Stereo speakers, 2W x2, optimized with Nahimic Gaming Audio\n\u041a\u0430\u043c\u0435\u0440\u0430:FHD 1080p with E-shutter\n\u041c\u0438\u043a\u0440\u043e\u0444\u043e\u043d:2x, Array\n\u0422\u0430\u0441\u0442\u0430\u0442\u0443\u0440\u0430: White Backlit, English\nWireless:Wi-Fi\u00ae 6, 11ax 2x2 + BT5.1\n\u041f\u043e\u0440\u0442\u0438:\n1x Ethernet (RJ-45)\n1x HDMI\u00ae 2.1, up to 8K/60Hz\n1x Headphone / microphone combo jack (3.5mm)\n1x Power connector\n1x USB 3.2 Gen 1\n1x USB-C\u00ae 3.2 Gen 2 (support data transfer, Power Delivery 140W and DisplayPort\u2122 1.4)\n2x USB 3.2 Gen 2\n\u0411\u0430\u0442\u0435\u0440\u0438\u0458\u0430: Integrated 60Wh\nPower Adapter: 170W Slim Tip (3-pin)",
    "features": {
        "screen_size_inches": 15.6,
        "screen_resolution": "1920x1080",
        "screen_type": "FHD",
        "screen_refresh_rate_hz": 144,
        "processor_model": "Intel\u00ae Core\u2122 i5-13420H",
        "processor_cores": 8,
        "processor_threads": 12,
        "processor_base_clock_ghz": 2.1,
        "processor_max_clock_ghz": 4.6,
        "gpu_model": "NVIDIA\u00ae GeForce RTX\u2122 4050",
        "gpu_memory_gb": 6,
        "ram_size_gb": 16,
        "ram_type": "DDR5-5200",
        "storage_size_tb": 0.512,
        "storage_type": "SSD",
        "operating_system": null,
        "wifi_standard": "Wi-Fi\u00ae 6",
        "bluetooth_version": 5.1,
        "usb_type_c_ports": 1,
        "usb_type_a_ports": 3,
        "hdmi_ports": 1,
        "audio_jack_ports": 1,
        "card_reader": null,
        "keyboard_type": "White Backlit, English",
        "audio_feature_1": "Stereo speakers, 2W x2, optimized with Nahimic Gaming Audio",
        "battery_capacity_wh": 60,
        "battery_cells": null,
        "security_feature_1": null
    }
}