{
    "url": "https://www.neptun.mk/categories/gaming_laptopi/LENOVO-LOQ-15IAX9-i5-12450HX-16GB-DDR5-512GB-RTX-2050-4GB",
    "title": "Лаптоп LENOVO LOQ 15IAX9 i5-12450HX/16GB DDR5/512GB/RTX 2050 4GB",
    "warranty_months": 24,
    "regular_price_mkd": 47999,
    "happy_price_mkd": 43999,
    "category": "gaming_laptopi",
    "device_type": "Gaming Laptop",
    "description": "Лаптоп\nДисплеј:15.6\" (39.5cm)\nРезолуција:FHD (1920x1080) IPS 300nits Anti-glare, 100% sRGB, 144Hz, G-SYNC®\nПроцесор:Intel® Core™ i5-12450HX, 8C (4P + 4E) / 12T, P-core up to 4.4GHz, E-core up to 3.1GHz, 12MB\nГрафика:NVIDIA® GeForce RTX™ 2050 4GB GDDR6, Boost Clock 1575MHz, TGP 65W\nВнатрешна меморија:16GB DDR5-4800\nМеморија:512GB SSD M.2 2242 PCIe® 4.0x4 NVMe®\nБез оперативен систем\nАудио:High Definition (HD) Audio, Realtek® ALC3287 codec\nЗвучник:Stereo speakers, 2W x2, optimized with Nahimic Audio\nКамера:HD 720p with E-shutter\nМикрофон:2x, Array\nEthernet:100/1000M (RJ-45)\nWi-Fi® 6, 11ax 2x2 + BT5.2\nWhite Backlit\nПорти:\n3x USB-A (USB 5Gbps / USB 3.2 Gen 1)\n1x USB-C® (USB 10Gbps / USB 3.2 Gen 2), with PD 140W and DisplayPort™ 1.4\n1x HDMI® 2.1, up to 8K/60Hz\n1x Headphone / microphone combo jack (3.5mm)\n1x Ethernet (RJ-45)\n1x Power connector\nPower Adapter:135W Slim Tip (3-pin)\nБатерија:Integrated 60Wh",
    "features": {
        "screen_size_inches": 15.6,
        "screen_resolution": "1920x1080",
        "screen_type": "IPS",
        "screen_refresh_rate_hz": 144,
        "processor_model": "Intel® Core™ i5-12450HX",
        "processor_cores": 8,
        "processor_threads": 12,
        "processor_base_clock_ghz": 4.4,
        "processor_max_clock_ghz": 3.1,
        "gpu_model": "NVIDIA® GeForce RTX™ 2050",
        "gpu_memory_gb": 4,
        "ram_size_gb": 16,
        "ram_type": "DDR5",
        "storage_size_tb": 0.512,
        "storage_type": "SSD",
        "operating_system": null,
        "wifi_standard": "Wi-Fi® 6, 11ax",
        "bluetooth_version": 5.2,
        "usb_type_c_ports": 1,
        "usb_type_a_ports": 3,
        "hdmi_ports": 1,
        "audio_jack_ports": 1,
        "card_reader": null,
        "keyboard_type": "White Backlit",
        "audio_feature_1": "Stereo speakers, 2W x2, optimized with Nahimic Audio",
        "battery_capacity_wh": 60,
        "battery_cells": null,
        "security_feature_1": null
    }
}