{
    "url": "https://www.neptun.mk/categories/gaming_laptopi/DELL-G16-7630-16--i9-13900HX-32GB-DDR5-1TB-RTX-4060-8GB",
    "title": "\u041b\u0410\u041f\u0422\u041e\u041f DELL G16 7630 16\" I9-13900HX/32GB DDR5/1TB/RTX 4060 8GB",
    "warranty_months": 36,
    "regular_price_mkd": 129999,
    "happy_price_mkd": 111999,
    "category": "gaming_laptopi",
    "device_type": "Gaming Laptop",
    "description": "\u041b\u0430\u043f\u0442\u043e\u043f\n\u0414\u0438\u0441\u043f\u043b\u0435\u0439:16\" (40.64cm)\n\u0420\u0435\u0437\u043e\u043b\u0443\u0446\u0438\u0458\u0430: (2560 x 1600) QHD+, 240Hz, 3ms, DCI-P3 100%, ComfortViewPlus, NVIDIA G-SYNC+DDS Display\n\u041f\u0440\u043e\u0446\u0435\u0441\u043e\u0440:13th Gen Intel\u00ae Core\u2122 ) i9-13900HX (36 MB cache, 24 cores, 32 threads, up to 5.40 GHz Turbo)\n\u0413\u0440\u0430\u0444\u0438\u043a\u0430:NVIDIA\u00ae GeForce RTX\u2122 4060, 8 GB GDDR6\nRAM \u041c\u0435\u043c\u043e\u0440\u0438\u0458\u0430: 32GB (2 x 16GB), DDR5, 4800 MT/s\n\u0414\u0438\u0441\u043a (Storage): 1 TB, M.2, PCIe NVMe, SSD\n\u041c\u0440\u0435\u0436\u043d\u0430 \u043a\u0430\u0440\u0442\u0438\u0447\u043a\u0430: Killer E3100 PCI-e Gigabit ethernet controller\nWi-Fi 6 AX201, 2x2, 802.11ax, Bluetooth\u00ae 5.2\n\u041a\u0430\u043c\u0435\u0440\u0430:Integrated widescreen HD (720p) Webcam with Single Array Digital Microphone\n\u041f\u043e\u0440\u0442\u0438:\n1 x headset (headphone and microphone combo) port\n1 x RJ45 Ethernet port\n3 x USB 3.2 Gen 1 ports\n1 x HDMI 2.1 port\n1 x Thunderbolt\u2122 4 port with DisplayPort\u2122\n1 USB-C 3.2 Gen 2 port with DisplayPort\u2122\n\u0411\u0430\u0442\u0435\u0440\u0438\u0458\u0430: 6-Cell Battery, 86WHr (Integrated)\n\u041f\u043e\u0437\u0430\u0434\u0438\u043d\u0441\u043a\u043e \u043e\u0441\u0432\u0435\u0442\u043b\u0443\u0432\u0430\u045a\u0435 \u043d\u0430 \u0442\u0430\u0441\u0442\u0430\u0442\u0443\u0440\u0430\u0442\u0430 (backlit keyboard)\n\u0422\u0435\u0436\u0438\u043d\u0430: 2.87kg",
    "features": {
        "screen_size_inches": 16,
        "screen_resolution": "2560 x 1600",
        "screen_type": "QHD+",
        "screen_refresh_rate_hz": 240,
        "processor_model": "13th Gen Intel\u00ae Core\u2122 ) i9-13900HX",
        "processor_cores": 24,
        "processor_threads": 32,
        "processor_base_clock_ghz": null,
        "processor_max_clock_ghz": 5.4,
        "gpu_model": "NVIDIA\u00ae GeForce RTX\u2122 4060",
        "gpu_memory_gb": 8,
        "ram_size_gb": 32,
        "ram_type": "DDR5",
        "storage_size_tb": 1,
        "storage_type": "M.2, PCIe NVMe, SSD",
        "operating_system": null,
        "wifi_standard": "Wi-Fi 6 AX201, 2x2, 802.11ax",
        "bluetooth_version": 5.2,
        "usb_type_c_ports": 2,
        "usb_type_a_ports": 3,
        "hdmi_ports": 1,
        "audio_jack_ports": 1,
        "card_reader": null,
        "keyboard_type": "backlit keyboard",
        "audio_feature_1": null,
        "battery_capacity_wh": 86,
        "battery_cells": 6,
        "security_feature_1": null
    }
}