{
    "url": "https://www.neptun.mk/categories/gaming_laptopi/ASUS-ROG-Zephyrus-G16-GU605MI-QR153W-16--OLED-Ultra-7-155H-32GB-DDR5X-1TB-RTX-4070-8GB-WIN11",
    "title": "\u041b\u0410\u041f\u0422\u041e\u041f ASUS ROG ZEPHYRUS G16 GU605MI-QR153W 16\" OLED ULTRA 7 155H/32GB DDR5X/1TB/RTX 4070 8GB/WIN11",
    "warranty_months": 24,
    "regular_price_mkd": 159999,
    "happy_price_mkd": 147999,
    "category": "gaming_laptopi",
    "device_type": "Gaming Laptop",
    "description": "\u041b\u0410\u041f\u0422\u041e\u041f\n\u0414\u0438\u0441\u043f\u043b\u0435\u0439:16.0\" (40.6cm)\n\u0420\u0435\u0437\u043e\u043b\u0443\u0446\u0438\u0458\u0430:(2560 x 1600) 2.5K, WQXGA OLED 240Hz, 0.2ms, 500 nits\n\u041f\u0440\u043e\u0446\u0435\u0441\u043e\u0440:Intel\u00ae Core\u2122 Ultra 7 155H, 16-Cores, 24M Cache, up to 4.80 GHz\n\u0413\u0440\u0430\u0444\u0438\u043a\u0430:Nvidia Geforce RTX 4070 8GB GDDR6\nRAM \u043c\u0435\u043c\u043e\u0440\u0438\u0458\u0430:32GB DDR5X\n\u0414\u0438\u0441\u043a (Storage):1TB PCIe 4.0 NVMe M.2 SSD\n\u041e\u043f\u0435\u0440\u0430\u0442\u0438\u0432\u0435\u043d \u0441\u0438\u0441\u0442\u0435\u043c:Windows 11 Home\nAdaptive-Sync technology: G-Sync\nWi-Fi 6E(802.11ax) (Triple band) 2*2 + Bluetooth 5.3\n\u041f\u043e\u0440\u0442\u0438:\n1x Thunderbolt 4 support DisplayPort / power delivery\n1x USB 3.2 Gen 2 Type-C support DisplayPort    / power delivery\n2x USB 3.2 Gen 2 Type-A\n1x card reader (SD) (UHS-II, 312MB/s)\n1x HDMI 2.1 FRL\n1x 3.5mm Combo Audio Jack\n\u041a\u0430\u043c\u0435\u0440\u0430: 1080P FHD IR Camera for Windows Hello\n\u0412\u0433\u0440\u0430\u0434\u0435\u043d\u0438 \u043c\u0438\u043a\u0440\u043e\u0444\u043e\u043d\u0438\nBacklit Chiclet Keyboard 1-Zone RGB\nAura Sync\n\u0417\u0432\u0443\u0447\u043d\u0438\u0446\u0438:4-speaker (dual force woofer) system with Smart Amplifier Technology\n\u0410\u0443\u0434\u0438\u043e:Tech AI noise-canceling\nDolby Atmos\nHi-Res certification\nSmart Amp Technology\nSecurity BIOS Administrator Password and User Password Protection\n\u0411\u0430\u0442\u0435\u0440\u0438\u0458\u0430:90WHrs, 4S1P, 4-cell Li-ion",
    "features": {
        "screen_size_inches": 16,
        "screen_resolution": "2560 x 1600",
        "screen_type": "OLED",
        "screen_refresh_rate_hz": 240,
        "processor_model": "Intel\u00ae Core\u2122 Ultra 7 155H",
        "processor_cores": 16,
        "processor_threads": null,
        "processor_base_clock_ghz": null,
        "processor_max_clock_ghz": 4.8,
        "gpu_model": "Nvidia Geforce RTX 4070",
        "gpu_memory_gb": 8,
        "ram_size_gb": 32,
        "ram_type": "DDR5X",
        "storage_size_tb": 1,
        "storage_type": "PCIe 4.0 NVMe M.2 SSD",
        "operating_system": "Windows 11 Home",
        "wifi_standard": "Wi-Fi 6E",
        "bluetooth_version": 5.3,
        "usb_type_c_ports": 2,
        "usb_type_a_ports": 2,
        "hdmi_ports": 1,
        "audio_jack_ports": 1,
        "card_reader": "SD (UHS-II, 312MB/s)",
        "keyboard_type": "Backlit Chiclet Keyboard 1-Zone RGB",
        "audio_feature_1": "4-speaker (dual force woofer) system with Smart Amplifier Technology",
        "battery_capacity_wh": 90,
        "battery_cells": 4,
        "security_feature_1": "BIOS Administrator Password and User Password Protection"
    }
}