{
    "url": "https://www.neptun.mk/categories/gaming_laptopi/HP-OMEN-16-wd0001nn-i5-13420H-16GB-DDR5-512GB-RTX-4050-6GB-WIN11",
    "title": "\u041b\u0410\u041f\u0422\u041e\u041f HP OMEN 16-WD0001NN I5-13420H/16GB/512GB/RTX 4050 6GB/WIN11",
    "warranty_months": 36,
    "regular_price_mkd": 82999,
    "happy_price_mkd": 66999,
    "category": "gaming_laptopi",
    "device_type": "Gaming Laptop",
    "description": "\u041b\u0430\u043f\u0442\u043e\u043f\n\u0414\u0438\u0441\u043f\u043b\u0435\u0439:16.1\" (40.9cm)\n\u0420\u0435\u0437\u043e\u043b\u0443\u0446\u0438\u0458\u0430:(1920 x 1080) FHD IPS 144 Hz\nIntel\u00ae integrated SoC\n\u041f\u0440\u043e\u0446\u0435\u0441\u043e\u0440:Intel\u00ae Core\u2122 i5-13420H (up to 4.6 GHz with Intel\u00ae Turbo Boost Technology, 12 MB L3 cache, 8 cores, 12 threads)\n\u0413\u0440\u0430\u0444\u0438\u043a\u0430:NVIDIA\u00ae GeForce RTX\u2122 4050 6 GB GDDR6\nRAM \u043c\u0435\u043c\u043e\u0440\u0438\u0458\u0430:16GB DDR5\n\u0414\u0438\u0441\u043a (Storage):512 SSD\nIntel\u00ae Wi-Fi 6E AX211 (2x2) and Bluetooth\u00ae 5.3 wireless card (supporting gigabit data rate)\n\u041a\u0430\u043c\u0435\u0440\u0430:HP True Vision 1080p FHD\n\u0410\u0443\u0434\u0438\u043e:Audio by B&O; DTS:X\u00ae Ultra, Dual speakers, HP Audio Boost\nIntegrated 10/100/1000 GbE LAN\n\u041e\u043f\u0435\u0440\u0430\u0442\u0438\u0432\u0435\u043d \u0441\u0438\u0441\u0442\u0435\u043c: Windows 11 Home\n\u041f\u043e\u0440\u0442\u0438:\n1 SuperSpeed USB Type-C\u00ae 5Gbps signaling rate (DisplayPort\u2122 1.4, HP Sleep and Charge)\n1 SuperSpeed USB Type-A 5Gbps signaling rate (HP Sleep and Charge)\n2 SuperSpeed USB Type-A 5Gbps signaling rate\n1 USB Type-A 5Gbps signaling rate (HP Sleep and Charge)\n1 USB Type-C\u00ae 5Gbps signaling rate (USB Power Delivery, DisplayPort\u2122 1.4, HP Sleep and Charge)\n2 USB Type-A 5Gbps signaling rate\n1 HDMI 2.1\n1 RJ-45\n1 AC smart pin\n1 headphone/microphone combo\nPower:230 W Smart AC power adapter\n\u0411\u0430\u0442\u0435\u0440\u0438\u0458\u0430:6-cell, 83 Wh Li-ion polymer",
    "features": {
        "screen_size_inches": 16.1,
        "screen_resolution": "1920 x 1080",
        "screen_type": "FHD IPS",
        "screen_refresh_rate_hz": 144,
        "processor_model": "Intel\u00ae Core\u2122 i5-13420H",
        "processor_cores": 8,
        "processor_threads": 12,
        "processor_base_clock_ghz": null,
        "processor_max_clock_ghz": 4.6,
        "gpu_model": "NVIDIA\u00ae GeForce RTX\u2122 4050",
        "gpu_memory_gb": 6,
        "ram_size_gb": 16,
        "ram_type": "DDR5",
        "storage_size_tb": 0.512,
        "storage_type": "SSD",
        "operating_system": "Windows 11 Home",
        "wifi_standard": "Wi-Fi 6E",
        "bluetooth_version": "5.3",
        "usb_type_c_ports": 2,
        "usb_type_a_ports": 5,
        "hdmi_ports": 1,
        "audio_jack_ports": 1,
        "card_reader": null,
        "keyboard_type": null,
        "audio_feature_1": "Audio by B&O; DTS:X\u00ae Ultra, Dual speakers, HP Audio Boost",
        "battery_capacity_wh": 83,
        "battery_cells": 6,
        "security_feature_1": null
    }
}