{
    "url": "https://www.neptun.mk/categories/gaming_laptopi/ASUS-ROG-Zephyrus-G16-GU603ZV-N4008W-16--i7-12700H-16GB-1TB-RTX-4060-8GB-WIN11",
    "title": "\u041b\u0410\u041f\u0422\u041e\u041f ASUS ROG ZEPHYRUS G16 GU603ZV-N4008W 16\" I7-12700H/16GB/1TB/RTX 4060 8GB/WIN11",
    "warranty_months": 24,
    "regular_price_mkd": 119999,
    "happy_price_mkd": 99999,
    "category": "gaming_laptopi",
    "device_type": "Gaming Laptop",
    "description": "\u041b\u0430\u043f\u0442\u043e\u043f\n\u0414\u0438\u0441\u043f\u043b\u0435\u0439:16.0\" (40.6cm)\n\u0420\u0435\u0437\u043e\u043b\u0443\u0446\u0438\u0458\u0430:(2560 x 1600) WQXGA IPS 240Hz\n\u041f\u0440\u043e\u0446\u0435\u0441\u043e\u0440:12th Gen Intel Core i7-12700H Processor 2.3 GHz (24M Cache, up to 4.7 GHz, 14 cores)\n\u0413\u0440\u0430\u0444\u0438\u043a\u0430:GeForce RTX 4060 8GB GDDR6\nRAM \u043c\u0435\u043c\u043e\u0440\u0438\u0458\u0430:16GB DDR4\n\u0414\u0438\u0441\u043a (Storage):1TB PCIe 4.0 NVMe M.2 SSD\n\u041e\u043f\u0435\u0440\u0430\u0442\u0438\u0432\u0435\u043d \u0441\u0438\u0441\u0442\u0435\u043c:Windows 11 Home\nLAN 10/100/1000 Mbps\nWi-Fi 6E(802.11ax) (Triple band) 2*2 + Bluetooth 5.2\n\u041f\u043e\u0440\u0442\u0438:\n1x RJ45 LAN port\n1x Thunderbolt 4 support DisplayPort / power delivery\n1x USB 3.2 Gen 2 Type-C support DisplayPort / power delivery / G-SYNC\n2x USB 3.2 Gen 2 Type-A\n1x card reader (microSD) (UHS-II, 312MB/s)\n1x HDMI 2.1 FRL\n1x 3.5mm Combo Audio Jack\n720P HD IR Camera for Windows Hello\n\u0412\u0433\u0440\u0430\u0434\u0435\u043d \u043c\u0438\u043a\u0440\u043e\u0444\u043e\u043d\n\u041e\u0441\u0432\u0435\u0442\u043b\u0435\u043d\u0430 \u0442\u0430\u0441\u0442\u0430\u0442\u0443\u0440\u0430 RGB\n\u0417\u0432\u0443\u0447\u043d\u0438\u0446\u0438:2x 2W speaker\n\u0410\u0443\u0434\u0438\u043e:Tech AI noise-canceling - Dolby Atmos\nSecurity BIOS Administrator Password and User Password Protection\n\u0411\u0430\u0442\u0435\u0440\u0438\u0458\u0430:90WHrs, 4S1P, 4-cell Li-ion",
    "features": {
        "screen_size_inches": 16.0,
        "screen_resolution": "2560 x 1600",
        "screen_type": "WQXGA IPS",
        "screen_refresh_rate_hz": 240,
        "processor_model": "12th Gen Intel Core i7-12700H Processor",
        "processor_cores": 14,
        "processor_threads": null,
        "processor_base_clock_ghz": 2.3,
        "processor_max_clock_ghz": 4.7,
        "gpu_model": "GeForce RTX 4060",
        "gpu_memory_gb": 8,
        "ram_size_gb": 16,
        "ram_type": "DDR4",
        "storage_size_tb": 1,
        "storage_type": "PCIe 4.0 NVMe M.2 SSD",
        "operating_system": "Windows 11 Home",
        "wifi_standard": "Wi-Fi 6E",
        "bluetooth_version": 5.2,
        "usb_type_c_ports": 2,
        "usb_type_a_ports": 2,
        "hdmi_ports": 1,
        "audio_jack_ports": 1,
        "card_reader": "microSD (UHS-II, 312MB/s)",
        "keyboard_type": "\u041e\u0441\u0432\u0435\u0442\u043b\u0435\u043d\u0430 \u0442\u0430\u0441\u0442\u0430\u0442\u0443\u0440\u0430 RGB",
        "audio_feature_1": "Tech AI noise-canceling - Dolby Atmos",
        "battery_capacity_wh": 90,
        "battery_cells": 4,
        "security_feature_1": "BIOS Administrator Password and User Password Protection"
    }
}