{
    "url": "https://www.neptun.mk/categories/gaming_laptopi/Gigabyte-G6X-9MG-16--i7-13650HX-16GB-DDR5-1TB-RTX-4050-6GB",
    "title": "GIGABYTE G6X 9MG 16\" I7-13650HX/16GB DDR5/1TB/RTX 4050 6GB",
    "warranty_months": 24,
    "regular_price_mkd": "70.999",
    "happy_price_mkd": "64.999",
    "category": "gaming_laptopi",
    "device_type": "Gaming Laptop",
    "description": "\u041b\u0430\u043f\u0442\u043e\u043f\n\u0414\u0438\u0441\u043f\u043b\u0435\u0439:16\"(40.64cm)\n\u0420\u0435\u0437\u043e\u043b\u0443\u0446\u0438\u0458\u0430:(1920x1200) WUXGA 165Hz Display ?45% NTSC, MUX Switch?\n\u041f\u0440\u043e\u0446\u0435\u0441\u043e\u0440:Intel\u00ae Core\u2122 i7-13650HX Processor (24M Cache, up to 4.9 GHz, 14 cores : 6 P-core and 8 E-core)\n\u0413\u0440\u0430\u0444\u0438\u043a\u0430:NVIDIA\u00ae GeForce RTX\u2122 4050 Laptop GPU 6GB GDDR6\nRAM \u043c\u0435\u043c\u043e\u0440\u0438\u0458\u0430: 16GB DDR5-4800MHz\n\u0414\u0438\u0441\u043a (Storage):1\u0422\u0412 M.2 PCIe\u00ae Gen4x4 NVMe\u2122\n\u0411\u0435\u0437 \u043e\u043f\u0435\u0440\u0430\u0442\u0438\u0432\u0435\u043d \u0441\u0438\u0441\u0442\u0435\u043c\nRGB Backlit Keyboard (15 colors, with 10-key)\nWi-Fi: Intel\u00ae Wi-Fi 6E (802.11ax 2x2)\nBluetooth\u00ae V5.2\nLAN: 1G\n1 x Type-A support USB3.2 Gen1\n1 x Audio Jack support mic / headphone combo\n1 x Type-C support USB3.2 Gen2, Power Delivery 3.0\n1 x Type-A support USB3.2 Gen2\n1 x Type-C support USB3.2 Gen2, DisplayPort\u2122 1.4\n1 x DC in\n1 x HDMI 2.1\n1 x RJ-45\n\u0417\u0432\u0443\u0447\u043d\u0438\u0446\u0438: 2x 2W\n\u041c\u0438\u043a\u0440\u043e\u0444\u043e\u043d\nDolby Atmos\u00ae\n\u0412\u0435\u0431 \u043a\u0430\u043c\u0435\u0440\u0430: HD (720p)\n\u0411\u0430\u0442\u0435\u0440\u0438\u0458\u0430:Lithium-Ion 73Wh\n\u041f\u043e\u043b\u043d\u0430\u0447: 180W AC Adapter, 100W PD\n\u0422\u0435\u0436\u0438\u043d\u0430: ~2.5kg",
    "features": {
        "screen_size_inches": 16,
        "screen_resolution": "1920x1200",
        "screen_type": "WUXGA",
        "screen_refresh_rate_hz": 165,
        "processor_model": "Intel\u00ae Core\u2122 i7-13650HX Processor",
        "processor_cores": 14,
        "processor_threads": 20,
        "processor_base_clock_ghz": null,
        "processor_max_clock_ghz": 4.9,
        "gpu_model": "NVIDIA\u00ae GeForce RTX\u2122 4050 Laptop GPU",
        "gpu_memory_gb": 6,
        "ram_size_gb": 16,
        "ram_type": "DDR5-4800MHz",
        "storage_size_tb": 1,
        "storage_type": "M.2 PCIe\u00ae Gen4x4 NVMe\u2122",
        "operating_system": null,
        "wifi_standard": "Wi-Fi 6E",
        "bluetooth_version": "V5.2",
        "usb_type_c_ports": 2,
        "usb_type_a_ports": 3,
        "hdmi_ports": 1,
        "audio_jack_ports": 1,
        "card_reader": null,
        "keyboard_type": "RGB Backlit Keyboard (15 colors, with 10-key)",
        "audio_feature_1": "Dolby Atmos\u00ae",
        "battery_capacity_wh": 73,
        "battery_cells": null,
        "security_feature_1": null
    }
}