{
    "url": "https://www.neptun.mk/categories/gaming_laptopi/LENOVO-LOQ-15IRX9-i7-13650HX-16GB-DDR5-1TB-RTX-4050-6GB",
    "title": "Лаптоп LENOVO LOQ 15IRX9 i7-13650HX/16GB DDR5/1TB/RTX 4050 6GB",
    "warranty_months": 24,
    "regular_price_mkd": 71999,
    "happy_price_mkd": 65999,
    "category": "gaming_laptopi",
    "device_type": "Gaming Laptop",
    "description": "Лаптоп\nДисплеј:15.6\" (39.5cm)\nРезолуција:(1920 x 1080) FHD, IPS, 300nits, Anti-glare, 144Hz, G-SYNC®\nПроцесор:Intel® Core™ i7-13650HX, 14C (6P + 8E) / 20T, P-core 2.6 / 4.9GHz, E-core 1.9 / 3.6GHz, 24MB\nГрафика:NVIDIA® GeForce RTX® 4050 6GB GDDR6, Boost Clock 2370MHz, TGP 105W\nВнатрешна меморија:16GB DDR5-4800\nМедиум за снимање:1TB SSD M.2 2242 PCIe® 4.0x4 NVMe™\nБез оперативен систем\nАудио:High Definition (HD) Audio, Realtek® ALC3287 codec\nЗвучници:Stereo speakers, 2W x2, optimized with Nahimic Audio\nКамера:FHD 1080p with E-shutter\nМикрофон:2x, Array\nEthernet:100/1000M (RJ-45)\nWi-Fi® 6, 11ax 2x2 + BT5.2\nWhite Backlit\nПорти:\n3x USB-A (USB 5Gbps / USB 3.2 Gen 1)\n1x USB-C® (USB 10Gbps / USB 3.2 Gen 2), with PD 140W and DisplayPort™ 1.4\n1x HDMI™ 2.1, up to 8K/60Hz\n1x Headphone / microphone combo jack (3.5mm)\n1x Ethernet (RJ-45)\n1x Power connector\nPower Adapter:170W Slim Tip (3-pin)\nБатерија:Integrated 60Wh",
    "features": {
        "screen_size_inches": 15.6,
        "screen_resolution": "1920 x 1080",
        "screen_type": "FHD, IPS, Anti-glare",
        "screen_refresh_rate_hz": 144,
        "processor_model": "Intel® Core™ i7-13650HX",
        "processor_cores": 14,
        "processor_threads": 20,
        "processor_base_clock_ghz": 2.6,
        "processor_max_clock_ghz": 4.9,
        "gpu_model": "NVIDIA® GeForce RTX® 4050",
        "gpu_memory_gb": 6,
        "ram_size_gb": 16,
        "ram_type": "DDR5-4800",
        "storage_size_tb": 1,
        "storage_type": "SSD M.2 2242 PCIe® 4.0x4 NVMe™",
        "operating_system": null,
        "wifi_standard": "Wi-Fi® 6, 11ax 2x2",
        "bluetooth_version": "BT5.2",
        "usb_type_c_ports": 1,
        "usb_type_a_ports": 3,
        "hdmi_ports": 1,
        "audio_jack_ports": 1,
        "card_reader": null,
        "keyboard_type": "White Backlit",
        "audio_feature_1": "Stereo speakers, 2W x2, optimized with Nahimic Audio",
        "battery_capacity_wh": 60,
        "battery_cells": null,
        "security_feature_1": null
    }
}