{
    "url": "https://www.neptun.mk/categories/gaming_laptopi/ASUS-ROG-Strix-G16-G614JI-N3093-16--i7-13650HX-16GB-DDR5-1TB-RTX-4070-8GB",
    "title": "ASUS ROG Strix G16 G614JI-N3093",
    "warranty_months": 24,
    "regular_price_mkd": 114999,
    "happy_price_mkd": 105999,
    "category": "gaming_laptopi",
    "device_type": "Gaming Laptop",
    "description": "16'' (40.6cm)\n(1920 x 1200) WUXGA, IPS, 165Hz\nIntel Core i7-13650HX, 2.6 GHz 24M Cache, up to 4.9 GHz, 14 cores\nNVIDIA GeForce RTX 4070 8GB GDDR6\nNVIDIA G-Sync\n16GB DDR5\n1TB PCIe 4.0 NVMe M.2 SSD\nLAN 10/100/1000 Mbps\nWi-Fi 6E(802.11ax) (Triple band) 2*2 + Bluetooth 5.2\n1x RJ45 LAN port\n1x Thunderbolt 4 support DisplayPort\n1x USB 3.2 Gen 2 Type-C support DisplayPort / power delivery / G-SYNC\n2x USB 3.2 Gen 2 Type-A\n1x HDMI 2.1 FRL\n1x 3.5mm Combo Audio Jack\n720P HD camera\nBacklit Chiclet Keyboard 4-Zone RGB\n\u0437\u0432\u0443\u0447\u043d\u0438\u0446\u0438 \u0441\u043e 2 \u0437\u0432\u0443\u0447\u043d\u0438\u0446\u0438 \u0441\u043e Smart Amplifier Technology\nTech AI noise-canceling\nDolby Atmos\nHi-Res certification\nAI noise-canceling technology\nDolby Atmos\nSmart Amp Technology\nSecurity BIOS Administrator Password and User Password Protection\n90WHrs, 4S1P, 4-cell Li-ion\n\u0410\u0434\u0430\u043f\u0442\u0435\u0440: 280W",
    "features": {
        "screen_size_inches": 16,
        "screen_resolution": "1920 x 1200",
        "screen_type": "IPS",
        "screen_refresh_rate_hz": 165,
        "processor_model": "Intel Core i7-13650HX",
        "processor_cores": 14,
        "processor_threads": null,
        "processor_base_clock_ghz": 2.6,
        "processor_max_clock_ghz": 4.9,
        "gpu_model": "NVIDIA GeForce RTX 4070",
        "gpu_memory_gb": 8,
        "ram_size_gb": 16,
        "ram_type": "DDR5",
        "storage_size_tb": 1,
        "storage_type": "PCIe 4.0 NVMe M.2 SSD",
        "operating_system": null,
        "wifi_standard": "Wi-Fi 6E",
        "bluetooth_version": 5.2,
        "usb_type_c_ports": 2,
        "usb_type_a_ports": 2,
        "hdmi_ports": 1,
        "audio_jack_ports": 1,
        "card_reader": null,
        "keyboard_type": "Backlit Chiclet Keyboard 4-Zone RGB",
        "audio_feature_1": "\u0437\u0432\u0443\u0447\u043d\u0438\u0446\u0438 \u0441\u043e 2 \u0437\u0432\u0443\u0447\u043d\u0438\u0446\u0438 \u0441\u043e Smart Amplifier Technology",
        "battery_capacity_wh": 90,
        "battery_cells": 4,
        "security_feature_1": "BIOS Administrator Password and User Password Protection"
    }
}