{
    "url": "https://www.neptun.mk/categories/monitori1/SAMSUNG-LS25BG400EUXEN-25--FLAT-240Hz-IPS-FHD",
    "title": "\u041c\u041e\u041d\u0418\u0422\u041e\u0420 SAMSUNG LS25BG400EUXEN 25\"(62.2CM), FLAT, 240HZ, IPS, FHD",
    "warranty_months": 24,
    "regular_price_mkd": 13999,
    "happy_price_mkd": 12999,
    "category": "monitori1",
    "device_type": "Monitor",
    "description": "\u041c\u043e\u043d\u0438\u0442\u043e\u0440\n\u0415\u043a\u0440\u0430\u043d:25\"(62.2cm), IPS, FHD\n\u0420\u0435\u0437\u043e\u043b\u0443\u0446\u0438\u0458\u0430:1,920 x 1,080\nIPS \u043f\u0430\u043d\u0435\u043b\nFlat\n\u041e\u0441\u0432\u0435\u0442\u043b\u0435\u043d\u043e\u0441\u0442:400cd/m2\nAspect Ratio - 16:9\n\u0421\u0442\u0430\u0442\u0438\u0447\u0435\u043d \u0441\u043e\u043e\u0434\u043d\u043e\u0441 \u043d\u0430 \u043a\u043e\u043d\u0442\u0440\u0430\u0441\u0442:1000:1\n\u0412\u0440\u0435\u043c\u0435 \u043d\u0430 \u0440\u0435\u0430\u043a\u0446\u0438\u0458\u0430:1ms(GTG)\nRefresh rate: 240Hz\n\u041f\u043e\u0434\u0440\u0436\u0430\u043d\u0438 \u0431\u043e\u0438:16.7M\n\u0410\u0433\u043e\u043b \u043d\u0430 \u0432\u0438\u0434\u043b\u0438\u0432\u043e\u0441\u0442 178\u00b0/178\u00b0\nContrast Ratio (Dynamic): Mega DCR\nEye Saver Mode\nEco Saving Plus\nEco Light Sensor\nFlicker Free\nAMD FreeSync Premium\nBlack Equalizer\nLow Input Lag Mode\nVirtual AIM Point\nRefresh Rate Optimizor\nSuper Arena Gaming UX\nAuto Source Switch+\nAdaptive Picture\nUltrawide Game View\nHDMI, Display Port\nErgonomic information:\nTilt (Angle): -3.0\u00b0(\u00b12.0\u00b0) ~ +22.0\u00b0(\u00b12.0\u00b0)\nSwivel: -15.0\u00b0(\u00b12.0\u00b0) ~ +15.0\u00b0(\u00b12.0\u00b0)\nPivot: -92.0\u00b0(\u00b12.0\u00b0) ~ +92.0\u00b0(\u00b12.0\u00b0)\nHAS(Height Adjustable Stand): 120.0\u00b15.0mm",
    "features": {
        "screen_size_inches": 25,
        "screen_resolution": "1,920 x 1,080",
        "screen_refresh_rate_hz": 240,
        "screen_brightness_nits": 400,
        "screen_type": "Flat",
        "panel_type": "IPS",
        "aspect_ratio": "16:9",
        "contrast_ratio_static": "1000:1",
        "response_time_ms": 1,
        "supported_colors_million": 16.7,
        "viewing_angle_horiz_degrees": 178,
        "viewing_angle_vert_degrees": 178,
        "hdmi_ports": 1,
        "displayport_ports": 1,
        "ergonomics": "Tilt (Angle): -3.0\u00b0(\u00b12.0\u00b0) ~ +22.0\u00b0(\u00b12.0\u00b0)\nSwivel: -15.0\u00b0(\u00b12.0\u00b0) ~ +15.0\u00b0(\u00b12.0\u00b0)\nPivot: -92.0\u00b0(\u00b12.0\u00b0) ~ +92.0\u00b0(\u00b12.0\u00b0)\nHAS(Height Adjustable Stand): 120.0\u00b15.0mm"
    }
}