{
    "url": "https://www.neptun.mk/categories/monitori1/SAMSUNG-27--LS27AG300NRXEN-FLAT-144Hz-VA-FHD",
    "title": "\u041c\u041e\u041d\u0418\u0422\u041e\u0420 SAMSUNG 27\"(68.6CM) LS27AG300NRXEN FLAT, 144HZ, VA, FHD",
    "warranty_months": 24,
    "regular_price_mkd": 12999,
    "happy_price_mkd": null,
    "category": "monitori1",
    "device_type": "Monitor",
    "description": "\u041c\u043e\u043d\u0438\u0442\u043e\u0440\n\u0415\u043a\u0440\u0430\u043d: 27\"(68.6cm)\n\u0420\u0435\u0437\u043e\u043b\u0443\u0446\u0438\u0458\u0430: (1,920 x 1,080)\n\u0421\u043e\u043e\u0434\u043d\u043e\u0441 \u043d\u0430 \u0441\u043b\u0438\u043a\u0430: 16:9\n\u0412\u0438\u0434 \u043d\u0430 \u043f\u0430\u043d\u0435\u043b: VA\nFlat-\u0440\u0430\u043ce\u043d \u0434\u0438\u0441\u043f\u043b\u0435\u0458\n\u0421\u0432\u0435\u0442\u043b\u0438\u043d\u0430: 250 cd/m2\n\u0411\u0440\u0437\u0438\u043d\u0430 \u043d\u0430 \u043e\u0441\u0432\u0435\u0436\u0443\u0432\u0430\u045a\u0435: Max 144Hz\n\u0421\u0442\u0430\u0442\u0438\u0447\u0435\u043d \u0441\u043e\u043e\u0434\u043d\u043e\u0441 \u043d\u0430 \u043a\u043e\u043d\u0442\u0440\u0430\u0441\u0442: 3000:1\n\u0412\u0440\u0435\u043c\u0435 \u043d\u0430 \u043e\u0434\u0433\u043e\u0432\u043e\u0440: 1ms(G/G)\n\u0410\u0433\u043e\u043b \u043d\u0430 \u0433\u043b\u0435\u0434\u0430\u045a\u0435 (\u0445\u043e\u0440\u0438\u0437\u043e\u043d\u0442\u0430\u043b\u043d\u043e/\u0432\u0435\u0440\u0442\u0438\u043a\u0430\u043b\u043d\u043e): 178\u00b0/178\u00b0\n\u041f\u0440\u0438\u043a\u0430\u0437 \u043d\u0430 \u0431\u043e\u0438: Max 16.7M\nEco Saving Plus\n\u0420\u0435\u0436\u0438\u043c Eye Saver\n\u0420\u0435\u0436\u0438\u043c \u0437\u0430 \u0438\u0433\u0440\u0438\nFlicker Free\nFreeSync Premium \u0442\u0435\u0445\u043d\u043e\u043b\u043e\u0433\u0438\u0458\u0430\nBlack Equalizer\nRefresh Rate Optimizor\nHDMI, DisplayPort\nHAS (\u043f\u043e\u0434\u043b\u043e\u0433\u0430 \u0441\u043e \u043c\u043e\u0436\u043d\u043e\u0441\u0442 \u0437\u0430 \u043f\u043e\u0434\u0435\u0441\u0443\u0432\u0430\u045a\u0435): 120.0 \u00b1 5.0 mm\n\u041d\u0430\u0432\u0430\u043b\u0443\u0432\u0430\u045a\u0435: -2.0? (\u00b112.0?) ~ 25.0? (\u00b112.0?)\n\u0412\u0440\u0442\u0435\u045a\u0435: -15.0\u00b0 (\u00b112.0\u00b0) ~ 15.0\u00b0 (\u00b112.0\u00b0)\n\u0420\u043e\u0442\u0438\u0440\u0430\u045a\u0435: -2.0\u00b0 (\u00b112.0\u00b0) ~ 92.0\u00b0 (\u00b112.0\u00b0)",
    "features": {
        "screen_size_inches": 27,
        "screen_resolution": "1,920 x 1,080",
        "screen_refresh_rate_hz": 144,
        "screen_brightness_nits": 250,
        "screen_type": "Flat",
        "panel_type": "VA",
        "aspect_ratio": "16:9",
        "contrast_ratio_static": "3000:1",
        "response_time_ms": 1,
        "supported_colors_million": 16.7,
        "viewing_angle_horiz_degrees": 178,
        "viewing_angle_vert_degrees": 178,
        "hdmi_ports": 1,
        "displayport_ports": 1
    }
}