{
    "url": "https://www.neptun.mk/categories/MASINI_ZA_SADOVI/GORENJE-GS642E90W",
    "title": "GORENJE GS642E90W",
    "warranty_months": "60",
    "regular_price_mkd": "20.999",
    "happy_price_mkd": null,
    "category": "MASINI_ZA_SADOVI",
    "device_type": "Washing Machine",
    "description": [
        "Machine for washing\nEnergy class:A++\nCapacity:13 sets\nProgram for washing delicates\nFunction Speedwash\nNumber of programs:2\nSystem for gentle drum:MultiCare\nProgram for washing wool:11L\nDetergent consumption per program:3080 l\nMaximum temperature of the water in the washing drum: 60 \u00b0C\nControl:Control with display (TouchControl)\nIndicator for the end of the wash on the floor:LightSignal\nDelay start option:Delay start 0-24 hours\nFunction for tablets 3 in 1\nPossibility for connecting the washing machine to the water supply:Hot and cold\nTemperature of the water (\u00b0C): 40/55/60/65/70\nProtection from flooding:Complete protection AquaStop\nAdditional features:Additional protection of the heater\nNoise: 47 dB(A)\nDimensions:84.5 x 59.9 x 59.7cm"
    ],
    "features": {
        "energy_class": "A++",
        "capacity_sets": 13,
        "delicates_program": true,
        "speedwash_function": true,
        "num_programs": 2,
        "drum_system": "MultiCare",
        "wool_program": "11L",
        "detergent_consumption_l": 3080,
        "max_water_temperature_c": 60,
        "control_type": "Control with display (TouchControl)",
        "end_of_cycle_indicator": "LightSignal",
        "delay_start_hours": 24,
        "tablet_support": true,
        "water_connection": "Hot and cold",
        "water_temperature_c": [
            40,
            55,
            60,
            65,
            70
        ],
        "flood_protection": "Complete protection AquaStop",
        "additional_features": "Additional protection of the heater",
        "noise_db": 47,
        "dimensions_cm": "84.5 x 59.9 x 59.7cm"
    }
}